Workbook
Name \a: #REF!
Name \e: #REF!
Name _25KgNAL: #REF!
Name _42.5KgEXP: #REF!
Name _42.5KgNAL: #REF!
Name _42.5KgRIO: #REF!
Name _50_KgNAL: #REF!
Name _50KgV300: #REF!
Name _AtRisk_SimSetting_AutomaticallyGenerateReports: FALSE
Name _AtRisk_SimSetting_AutomaticResultsDisplayMode: 0
Name _AtRisk_SimSetting_ConvergenceConfidenceLevel: 0.95
Name _AtRisk_SimSetting_ConvergencePercentileToTest: 0.9
Name _AtRisk_SimSetting_ConvergencePerformMeanTest: TRUE
Name _AtRisk_SimSetting_ConvergencePerformPercentileTest: FALSE
Name _AtRisk_SimSetting_ConvergencePerformStdDeviationTest: FALSE
Name _AtRisk_SimSetting_ConvergenceTestAllOutputs: TRUE
Name _AtRisk_SimSetting_ConvergenceTestingPeriod: 100
Name _AtRisk_SimSetting_ConvergenceTolerance: 0.03
Name _AtRisk_SimSetting_LiveUpdate: TRUE
Name _AtRisk_SimSetting_LiveUpdatePeriod: -1
Name _AtRisk_SimSetting_RandomNumberGenerator: 0
Name _AtRisk_SimSetting_ReportsList: 1
Name _AtRisk_SimSetting_SimNameCount: 0
Name _AtRisk_SimSetting_SmartSensitivityAnalysisEnabled: TRUE
Name _AtRisk_SimSetting_StatisticFunctionUpdating: 1
Name _AtRisk_SimSetting_StdRecalcBehavior: 0
Name _AtRisk_SimSetting_StdRecalcWithoutRiskStatic: 0
Name _AtRisk_SimSetting_StdRecalcWithoutRiskStaticPercentile: 0.5
Name _AV20025: #REF!
Name _AV200251: #REF!
Name _AV20050: #REF!
Name _AV200501: #REF!
Name _CAL96: #REF!
Name _CEM96: #REF!
Name _EMP96: #REF!
Name _ESC96: #REF!
Name _GAS1: #REF!
Name _INF1: #REF!
Name _MES1997: #REF!
Name _MO96: #REF!
Name _MOE1: #REF!
Name _MOF1: #REF!
Name _MOL3: #REF!
Name _MOL4: #REF!
Name _MOL5: #REF!
Name _MOL6: #REF!
Name _MOL7: #REF!
Name _MP96: #REF!
Name _NAL25: #REF!
Name _Regression_Int: 1
Name A_impresión_IM: #REF!
Name A1_CVC: #REF!
Name A2_CVC: #REF!
Name A25NAL: #REF!
Name A42.5EXP: #REF!
Name A42.5KgRIO: #REF!
Name A42.5NAL: #REF!
Name A50KgV300: #REF!
Name A50NAL: #REF!
Name AACPM: #REF!

Sheet Datos
B1: Tipo | C1: UM | D1: 45901 | E1: 45931 | F1: 45962 | G1: 45992 | H1: 46023 | I1: 46054 | J1: 46082 | K1: 46113 | L1: 46143 | M1: 46174 | N1: 46204 | O1: 46235 | P1: 46266 | Q1: 46296 | R1: 46327 | S1: 46357
B2: Precios
B3: Caliza + Martillo | C3: COP/Ton | D3: =D4*0.9+(D4+D6)*0.1 -> 14277.344 | E3: =E4*0.9+(E4+E6)*0.1 -> 14277.344 | F3: =F4*0.9+(F4+F6)*0.1 -> 14277.344 | G3: =G4*0.9+(G4+G6)*0.1 -> 14277.344 | H3: =H4*H129+(H4+H6)*H130 -> 13978.132 | I3: =I4*I129+(I4+I6)*I130 -> 13978.132 | J3: =J4*J129+(J4+J6)*J130 -> 13978.132 | K3: =K4*K129+(K4+K6)*K130 -> 13978.132 | L3: =L4*L129+(L4+L6)*L130 -> 13978.132 | M3: =M4*M129+(M4+M6)*M130 -> 13978.132 | N3: =N4*N129+(N4+N6)*N130 -> 13978.132 | O3: =O4*O129+(O4+O6)*O130 -> 13978.132 | ... S3: =S4*S129+(S4+S6)*S130 -> 13978.132
B4: Caliza Explotada | C4: COP/Ton | D4: 13974.06 | E4: 13974.06 | F4: 13974.06 | G4: 13974.06 | H4: 13819.211 | I4: =H4 -> 13819.211 | J4: =I4 -> 13819.211 | K4: =J4 -> 13819.211 | L4: =K4 -> 13819.211 | M4: =L4 -> 13819.211 | N4: =M4 -> 13819.211 | O4: =N4 -> 13819.211 | P4: =O4 -> 13819.211 | ... S4: =R4 -> 13819.211
B5: Arcilla Explotada | C5: COP/Ton | D5: 11628.05 | E5: 11628.05 | F5: 11628.05 | G5: 11628.05 | H5: 10623.146 | I5: 10623.146 | J5: 10623.146 | K5: 10623.146 | L5: 10623.146 | M5: 10623.146 | N5: 10623.146 | O5: 10623.146 | P5: 10623.146 | Q5: 10623.146 | R5: 10623.146 | S5: 10623.146
B6: Costo Adicional Martillo | C6: COP/Ton | D6: 3032.84 | E6: 3032.84 | F6: 3032.84 | G6: 3032.84 | H6: 3178.4163 | I6: 3178.4163 | J6: 3178.4163 | K6: 3178.4163 | L6: 3178.4163 | M6: 3178.4163 | N6: 3178.4163 | O6: 3178.4163 | P6: 3178.4163 | Q6: 3178.4163 | R6: 3178.4163 | S6: 3178.4163
B7: Caliza Comprada a Externos | C7: COP/Ton | D7: 36831.382 | E7: 36831.382 | F7: 36831.382 | G7: 36831.382 | H7: 36831.382 | I7: 36831.382 | J7: 36831.382 | K7: 36831.382 | L7: 36831.382 | M7: 36831.382 | N7: 36831.382 | O7: 36831.382 | P7: 36831.382 | Q7: 36831.382 | R7: 36831.382 | S7: 36831.382
B8: Carbón Fino | C8: COP/Ton | D8: =D16*0.5+D17*0.5 -> 174584.14 | E8: =E16*0.5+E17*0.5 -> 174584.14 | F8: =F16*0.5+F17*0.5 -> 174584.14 | G8: =G16*0.5+G17*0.5 -> 174584.14 | H8: =H16*H136+H17*H137 -> 209813.2 | I8: =I16*I136+I17*I137 -> 209813.2 | J8: =J16*J136+J17*J137 -> 209813.2 | K8: =K16*K136+K17*K137 -> 209813.2 | L8: =L16*L136+L17*L137 -> 209813.2 | M8: =M16*M136+M17*M137 -> 209813.2 | N8: =N16*N136+N17*N137 -> 209813.2 | O8: =O16*O136+O17*O137 -> 209813.2 | ... S8: =S16*S136+S17*S137 -> 209813.2
B9: Carbón Mixto | C9: COP/Ton | D9: =D18*0.43+D19*0.36+D20*0.21 -> 142315.38 | E9: =E18*0.43+E19*0.36+E20*0.21 -> 142315.38 | F9: =F18*0.43+F19*0.36+F20*0.21 -> 142315.38 | G9: =G18*0.43+G19*0.36+G20*0.21 -> 142315.38 | H9: =H18*H138+H19*H139+H20*H140 -> 149376.25 | I9: =I18*I138+I19*I139+I20*I140 -> 149376.25 | J9: =J18*J138+J19*J139+J20*J140 -> 149376.25 | K9: =K18*K138+K19*K139+K20*K140 -> 149376.25 | L9: =L18*L138+L19*L139+L20*L140 -> 149376.25 | M9: =M18*M138+M19*M139+M20*M140 -> 149376.25 | N9: =N18*N138+N19*N139+N20*N140 -> 149376.25 | O9: =O18*O138+O19*O139+O20*O140 -> 149376.25 | ... S9: =S18*S138+S19*S139+S20*S140 -> 149376.25
B10: Carbón Bituminoso | C10: COP/Ton | D10: =D11*0.3+D12*0.3+D13*0.05+D14*0.17+D15*0.18 -> 337846.06 | E10: =E11*0.3+E12*0.3+E13*0.05+E14*0.17+E15*0.18 -> 337846.06 | F10: =F11*0.3+F12*0.3+F13*0.05+F14*0.17+F15*0.18 -> 337846.06 | G10: =G11*0.3+G12*0.3+G13*0.05+G14*0.17+G15*0.18 -> 337846.06 | H10: =H11*H131+H12*H132+H13*H133+H14*H134+H15*H135 -> 345241.54 | I10: =I11*I131+I12*I132+I13*I133+I14*I134+I15*I135 -> 345241.54 | J10: =J11*J131+J12*J132+J13*J133+J14*J134+J15*J135 -> 345241.54 | K10: =K11*K131+K12*K132+K13*K133+K14*K134+K15*K135 -> 345241.54 | L10: =L11*L131+L12*L132+L13*L133+L14*L134+L15*L135 -> 345241.54 | M10: =M11*M131+M12*M132+M13*M133+M14*M134+M15*M135 -> 345241.54 | N10: =N11*N131+N12*N132+N13*N133+N14*N134+N15*N135 -> 345241.54 | O10: =O11*O131+O12*O132+O13*O133+O14*O134+O15*O135 -> 345241.54 | ... S10: =S11*S131+S12*S132+S13*S133+S14*S134+S15*S135 -> 345241.54
B11: Sanoha | C11: COP/Ton | D11: 364231.24 | E11: 364231.24 | F11: 364231.24 | G11: 364231.24 | H11: 367329.3 | I11: 367329.3 | J11: 367329.3 | K11: 367329.3 | L11: 367329.3 | M11: 367329.3 | N11: 367329.3 | O11: 367329.3 | P11: 367329.3 | Q11: 367329.3 | R11: 367329.3 | S11: 367329.3
B12: Forero Hernandez | C12: COP/Ton | D12: 363394 | E12: 363394 | F12: 363394 | G12: 363394 | H12: 379673.75 | I12: 379673.75 | J12: 379673.75 | K12: 379673.75 | L12: 379673.75 | M12: 379673.75 | N12: 379673.75 | O12: 379673.75 | P12: 379673.75 | Q12: 379673.75 | R12: 379673.75 | S12: 379673.75
B13: Tottal Carbón | C13: COP/Ton | D13: 336354.44 | E13: 336354.44 | F13: 336354.44 | G13: 336354.44 | H13: 332646.3 | I13: 332646.3 | J13: 332646.3 | K13: 332646.3 | L13: 332646.3 | M13: 332646.3 | N13: 332646.3 | O13: 332646.3 | P13: 332646.3 | Q13: 332646.3 | R13: 332646.3 | S13: 332646.3
B14: Soluciones De Carbón Colombia | C14: COP/Ton | D14: 336354.44 | E14: 336354.44 | F14: 336354.44 | G14: 336354.44 | H14: 332646.3 | I14: 332646.3 | J14: 332646.3 | K14: 332646.3 | L14: 332646.3 | M14: 332646.3 | N14: 332646.3 | O14: 332646.3 | P14: 332646.3 | Q14: 332646.3 | R14: 332646.3 | S14: 332646.3
B15: Minas Las Margaritas | C15: COP/Ton | D15: 253113.97 | E15: 253113.97 | F15: 253113.97 | G15: 253113.97 | H15: 266435.76 | I15: 266435.76 | J15: 266435.76 | K15: 266435.76 | L15: 266435.76 | M15: 266435.76 | N15: 266435.76 | O15: 266435.76 | P15: 266435.76 | Q15: 266435.76 | R15: 266435.76 | S15: 266435.76
B16: C I Interamerican Conmina (Fortia Minerals) | C16: COP/Ton | D16: 174584.14 | E16: 174584.14 | F16: 174584.14 | G16: 174584.14 | H16: 209813.2 | I16: 209813.2 | J16: 209813.2 | K16: 209813.2 | L16: 209813.2 | M16: 209813.2 | N16: 209813.2 | O16: 209813.2 | P16: 209813.2 | Q16: 209813.2 | R16: 209813.2 | S16: 209813.2
B17: Trancora Sas | C17: COP/Ton | D17: 174584.14 | E17: 174584.14 | F17: 174584.14 | G17: 174584.14 | H17: 209813.2 | I17: 209813.2 | J17: 209813.2 | K17: 209813.2 | L17: 209813.2 | M17: 209813.2 | N17: 209813.2 | O17: 209813.2 | P17: 209813.2 | Q17: 209813.2 | R17: 209813.2 | S17: 209813.2
B18: Mixto Carbones Andino | C18: COP/Ton | D18: 141616.48 | E18: 141616.48 | F18: 141616.48 | G18: 141616.48 | H18: 148649.3 | I18: 148649.3 | J18: 148649.3 | K18: 148649.3 | L18: 148649.3 | M18: 148649.3 | N18: 148649.3 | O18: 148649.3 | P18: 148649.3 | Q18: 148649.3 | R18: 148649.3 | S18: 148649.3
B19: Mixtos Carbocoque | C19: COP/Ton | D19: 134584.14 | E19: 134584.14 | F19: 134584.14 | G19: 134584.14 | H19: 141253.2 | I19: 141253.2 | J19: 141253.2 | K19: 141253.2 | L19: 141253.2 | M19: 141253.2 | N19: 141253.2 | O19: 141253.2 | P19: 141253.2 | Q19: 141253.2 | R19: 141253.2 | S19: 141253.2
B20: Mixto Coquecol | C20: COP/Ton | D20: 157000 | E20: 157000 | F20: 157000 | G20: 157000 | H20: 164790 | I20: 164790 | J20: 164790 | K20: 164790 | L20: 164790 | M20: 164790 | N20: 164790 | O20: 164790 | P20: 164790 | Q20: 164790 | R20: 164790 | S20: 164790
B21: Flete (Boyacá - Planta)-Socha | C21: COP/Ton | D21: 108388 | E21: 112723.52 | F21: 112723.52 | G21: 112723.52 | H21: 133350 | I21: 133350 | J21: 133350 | K21: 133350 | L21: 133350 | M21: 133350 | N21: 133350 | O21: 133350 | P21: 133350 | Q21: 133350 | R21: 133350 | S21: 133350
B22: Flete (Boyacá - Planta) | C22: COP/Ton | D22: 96379 | E22: 100234.16 | F22: 100234.16 | G22: 100234.16 | H22: 123497.3 | I22: 123497.3 | J22: 123497.3 | K22: 123497.3 | L22: 123497.3 | M22: 123497.3 | N22: 123497.3 | O22: 123497.3 | P22: 123497.3 | Q22: 123497.3 | R22: 123497.3 | S22: 123497.3
... B25: Flete (Caldas - Planta) | C25: COP/Ton | D25: 60000 | E25: 62400 | F25: 62400 | G25: 62400 | H25: 68363.757 | I25: 68363.757 | J25: 68363.757 | K25: 68363.757 | L25: 68363.757 | M25: 68363.757 | N25: 68363.757 | O25: 68363.757 | P25: 68363.757 | Q25: 68363.757 | R25: 68363.757 | S25: 68363.757
B26: Cdr | C26: COP/Ton | D26: =D30*0.5+D31*0.05+D32*0.12+D33*0.15+D34*0.02+D35*0.01+D36*0.15+D37*0 -> 310957.52 | E26: =E30*0.5+E31*0.05+E32*0.12+E33*0.15+E34*0.02+E35*0.01+E36*0.15+E37*0 -> 310957.52 | F26: =F30*0.5+F31*0.05+F32*0.12+F33*0.15+F34*0.02+F35*0.01+F36*0.15+F37*0 -> 310957.52 | G26: =G30*0.5+G31*0.05+G32*0.12+G33*0.15+G34*0.02+G35*0.01+G36*0.15+G37*0 -> 310957.52 | H26: =H30*H141+H31*H142+H32*H143+H33*H144+H34*H145+H35*H146+H36*H147+H37*H148 -> 318229.74 | I26: =I30*0.5+I31*0.05+I32*0.12+I33*0.15+I34*0.02+I35*0.01+I36*0.15+I37*0 -> 318229.74 | J26: =J30*0.5+J31*0.05+J32*0.12+J33*0.15+J34*0.02+J35*0.01+J36*0.15+J37*0 -> 318229.74 | K26: =K30*0.5+K31*0.05+K32*0.12+K33*0.15+K34*0.02+K35*0.01+K36*0.15+K37*0 -> 318229.74 | L26: =L30*0.5+L31*0.05+L32*0.12+L33*0.15+L34*0.02+L35*0.01+L36*0.15+L37*0 -> 318229.74 | M26: =M30*0.5+M31*0.05+M32*0.12+M33*0.15+M34*0.02+M35*0.01+M36*0.15+M37*0 -> 318229.74 | N26: =N30*0.5+N31*0.05+N32*0.12+N33*0.15+N34*0.02+N35*0.01+N36*0.15+N37*0 -> 318229.74 | O26: =O30*0.5+O31*0.05+O32*0.12+O33*0.15+O34*0.02+O35*0.01+O36*0.15+O37*0 -> 318229.74 | P26: =P30*0.5+P31*0.05+P32*0.12+P33*0.15+P34*0.02+P35*0.01+P36*0.15+P37*0 -> 318229.74 | ... S26: =S30*0.5+S31*0.05+S32*0.12+S33*0.15+S34*0.02+S35*0.01+S36*0.15+S37*0 -> 318229.74
B27: Tdf | C27: COP/Ton | D27: =D38*0.3+D39*0.3+D40*0.4 -> 304467.55 | E27: =E38*0.3+E39*0.3+E40*0.4 -> 304467.55 | F27: =F38*0.3+F39*0.3+F40*0.4 -> 304467.55 | G27: =G38*0.3+G39*0.3+G40*0.4 -> 304467.55 | H27: =H38*H149+H39*H150+H40*H151 -> 318422.6 | I27: =I38*I149+I39*I150+I40*I151 -> 318422.6 | J27: =J38*J149+J39*J150+J40*J151 -> 318422.6 | K27: =K38*K149+K39*K150+K40*K151 -> 318422.6 | L27: =L38*L149+L39*L150+L40*L151 -> 318422.6 | M27: =M38*M149+M39*M150+M40*M151 -> 318422.6 | N27: =N38*N149+N39*N150+N40*N151 -> 318422.6 | O27: =O38*O149+O39*O150+O40*O151 -> 318422.6 | ... S27: =S38*S149+S39*S150+S40*S151 -> 318422.6
B28: Briquetas | C28: COP/Ton | D28: =+D41 -> 322952.38 | E28: =+E41 -> 322952.38 | F28: =+F41 -> 322952.38 | G28: =+G41 -> 322952.38 | H28: =+H41 -> 335465.18 | I28: =+I41 -> 335465.18 | J28: =+J41 -> 335465.18 | K28: =+K41 -> 335465.18 | ... S28: =+S41 -> 335465.18
B29: Chips | C29: COP/Ton | D29: =+D42 -> 283952.38 | E29: =+E42 -> 283952.38 | F29: =+F42 -> 283952.38 | G29: =+G42 -> 283952.38 | H29: =+H42 -> 294593.18 | I29: =+I42 -> 294593.18 | J29: =+J42 -> 294593.18 | K29: =+K42 -> 294593.18 | ... S29: =+S42 -> 294593.18
B30: Cdr Focus Green Antioquia | C30: COP/Ton | D30: 318052.38 | E30: 318052.38 | F30: 318052.38 | G30: 318052.38 | H30: 330329.98 | I30: 330329.98 | J30: 330329.98 | K30: 330329.98 | L30: 330329.98 | M30: 330329.98 | N30: 330329.98 | O30: 330329.98 | P30: 330329.98 | Q30: 330329.98 | R30: 330329.98 | S30: 330329.98
B31: Cdr Sistema Verde Cundinamarca | C31: COP/Ton | D31: 289488.34 | E31: 289488.34 | F31: 289488.34 | G31: 289488.34 | H31: 303722.76 | I31: 303722.76 | J31: 303722.76 | K31: 303722.76 | L31: 303722.76 | M31: 303722.76 | N31: 303722.76 | O31: 303722.76 | P31: 303722.76 | Q31: 303722.76 | R31: 303722.76 | S31: 303722.76
B32: Cdr Sistema Verde Antioquia | C32: COP/Ton | D32: 253952.38 | E32: 253952.38 | F32: 253952.38 | G32: 253952.38 | H32: 263153.18 | I32: 263153.18 | J32: 263153.18 | K32: 263153.18 | L32: 263153.18 | M32: 263153.18 | N32: 263153.18 | O32: 263153.18 | P32: 263153.18 | Q32: 263153.18 | R32: 263153.18 | S32: 263153.18
B33: Cdr Ecologística | C33: COP/Ton | D33: 343952.38 | E33: 343952.38 | F33: 343952.38 | G33: 343952.38 | H33: 357473.18 | I33: 357473.18 | J33: 357473.18 | K33: 357473.18 | L33: 357473.18 | M33: 357473.18 | N33: 357473.18 | O33: 357473.18 | P33: 357473.18 | Q33: 357473.18 | R33: 357473.18 | S33: 357473.18
B34: Cdr Ecopositiva | C34: COP/Ton | D34: 269488.34 | E34: 269488.34 | F34: 269488.34 | G34: 269488.34 | H34: 282762.76 | I34: 282762.76 | J34: 282762.76 | K34: 282762.76 | L34: 282762.76 | M34: 282762.76 | N34: 282762.76 | O34: 282762.76 | P34: 282762.76 | Q34: 282762.76 | R34: 282762.76 | S34: 282762.76
B35: Cdr Veolia | C35: COP/Ton | D35: 312500 | E35: 312500 | F35: 312500 | G35: 312500 | H35: 293900 | I35: 293900 | J35: 293900 | K35: 293900 | L35: 293900 | M35: 293900 | N35: 293900 | O35: 293900 | P35: 293900 | Q35: 293900 | R35: 293900 | S35: 293900
B36: Cdr Gdi-Cali | C36: COP/Ton | D36: 312500 | E36: 312500 | F36: 312500 | G36: 312500 | H36: 293900 | I36: 293900 | J36: 293900 | K36: 293900 | L36: 293900 | M36: 293900 | N36: 293900 | O36: 293900 | P36: 293900 | Q36: 293900 | R36: 293900 | S36: 293900
B37: Cdr Gdi-Zipaquirá | C37: COP/Ton | D37: 226388.34 | E37: 226388.34 | F37: 226388.34 | G37: 226388.34 | H37: 237593.96 | I37: 237593.96 | J37: 237593.96 | K37: 237593.96 | L37: 237593.96 | M37: 237593.96 | N37: 237593.96 | O37: 237593.96 | P37: 237593.96 | Q37: 237593.96 | R37: 237593.96 | S37: 237593.96
B38: Tdf Sistema Verde Cundinamarca | C38: COP/Ton | D38: 289488.34 | E38: 289488.34 | F38: 289488.34 | G38: 289488.34 | H38: 303722.76 | I38: 303722.76 | J38: 303722.76 | K38: 303722.76 | L38: 303722.76 | M38: 303722.76 | N38: 303722.76 | O38: 303722.76 | P38: 303722.76 | Q38: 303722.76 | R38: 303722.76 | S38: 303722.76
B39: Tdf Sistema Verde Antioquia | C39: COP/Ton | D39: 253952.38 | E39: 253952.38 | F39: 253952.38 | G39: 253952.38 | H39: 263153.18 | I39: 263153.18 | J39: 263153.18 | K39: 263153.18 | L39: 263153.18 | M39: 263153.18 | N39: 263153.18 | O39: 263153.18 | P39: 263153.18 | Q39: 263153.18 | R39: 263153.18 | S39: 263153.18
B40: Tdf Focus Green Cundinamarca | C40: COP/Ton | D40: 353588.34 | E40: 353588.34 | F40: 353588.34 | G40: 353588.34 | H40: 370899.56 | I40: 370899.56 | J40: 370899.56 | K40: 370899.56 | L40: 370899.56 | M40: 370899.56 | N40: 370899.56 | O40: 370899.56 | P40: 370899.56 | Q40: 370899.56 | R40: 370899.56 | S40: 370899.56
B41: Briquetas Arclad | C41: COP/Ton | D41: 322952.38 | E41: 322952.38 | F41: 322952.38 | G41: 322952.38 | H41: 335465.18 | I41: 335465.18 | J41: 335465.18 | K41: 335465.18 | L41: 335465.18 | M41: 335465.18 | N41: 335465.18 | O41: 335465.18 | P41: 335465.18 | Q41: 335465.18 | R41: 335465.18 | S41: 335465.18
... B44: Tdf Focus Green Cundinamarca | C44: COP/Ton | D44: 211556.46 | E44: 211556.46 | F44: 211556.46 | G44: 211556.46 | H44: 213675 | I44: 213675 | J44: 213675 | K44: 213675 | L44: 213675 | M44: 213675 | N44: 213675 | O44: 213675 | P44: 213675 | Q44: 213675 | R44: 213675 | S44: 213675
B45: Cdr Flete (Antioquia - Planta) | C45: COP/Ton | H45: 137393.18 | I45: 137393.18 | J45: 137393.18 | K45: 137393.18 | L45: 137393.18 | M45: 137393.18 | N45: 137393.18 | O45: 137393.18 | P45: 137393.18 | Q45: 137393.18 | R45: 137393.18 | S45: 137393.18
B46: Cdr Flete (Cundinamarca - Planta) | C46: COP/Ton | H46: 177962.76 | I46: 177962.76 | J46: 177962.76 | K46: 177962.76 | L46: 177962.76 | M46: 177962.76 | N46: 177962.76 | O46: 177962.76 | P46: 177962.76 | Q46: 177962.76 | R46: 177962.76 | S46: 177962.76
B47: Cdr Flete (Cali - Planta) | C47: COP/Ton | H47: 241500 | I47: 241500 | J47: 241500 | K47: 241500 | L47: 241500 | M47: 241500 | N47: 241500 | O47: 241500 | P47: 241500 | Q47: 241500 | R47: 241500 | S47: 241500
B48: Mineral De Hierro | C48: COP/Ton | D48: =D50*0+D51*0.7+D52*0.3 -> 315000.24 | E48: =E50*0+E51*0.7+E52*0.3 -> 315000.24 | F48: =F50*0+F51*0.7+F52*0.3 -> 315000.24 | G48: =G50*0+G51*0.7+G52*0.3 -> 315000.24 | H48: =H50*H154+H51*H155+H52*H156 -> 299941.95 | I48: =I50*I154+I51*I155+I52*I156 -> 299941.95 | J48: =J50*J154+J51*J155+J52*J156 -> 299941.95 | K48: =K50*K154+K51*K155+K52*K156 -> 299941.95 | L48: =L50*L154+L51*L155+L52*L156 -> 299941.95 | M48: =M50*M154+M51*M155+M52*M156 -> 299941.95 | N48: =N50*N154+N51*N155+N52*N156 -> 299941.95 | O48: =O50*O154+O51*O155+O52*O156 -> 299941.95 | ... S48: =S50*S154+S51*S155+S52*S156 -> 299941.95
B49: Calamina | C49: COP/Ton | D49: =D53*0.3+D54*0.6+D55*0.1+D56*0 -> 161480.29 | E49: =E53*0.3+E54*0.6+E55*0.1+E56*0 -> 161480.29 | F49: =F53*0.3+F54*0.6+F55*0.1+F56*0 -> 161480.29 | G49: =G53*0.3+G54*0.6+G55*0.1+G56*0 -> 161480.29 | H49: =H53*H157+H54*H158+H55*H159+H56*H160 -> 169514.65 | I49: =I53*I157+I54*I158+I55*I159+I56*I160 -> 169514.65 | J49: =J53*J157+J54*J158+J55*J159+J56*J160 -> 169514.65 | K49: =K53*K157+K54*K158+K55*K159+K56*K160 -> 169514.65 | L49: =L53*L157+L54*L158+L55*L159+L56*L160 -> 169514.65 | M49: =M53*M157+M54*M158+M55*M159+M56*M160 -> 169514.65 | N49: =N53*N157+N54*N158+N55*N159+N56*N160 -> 169514.65 | O49: =O53*O157+O54*O158+O55*O159+O56*O160 -> 169514.65 | ... S49: =S53*S157+S54*S158+S55*S159+S56*S160 -> 169514.65
B50: Adpr - Briceño | C50: COP/Ton | D50: 283186.33 | E50: 283186.33 | F50: 283186.33 | G50: 283186.33 | H50: 337718.92 | I50: 337718.92 | J50: 337718.92 | K50: 337718.92 | L50: 337718.92 | M50: 337718.92 | N50: 337718.92 | O50: 337718.92 | P50: 337718.92 | Q50: 337718.92 | R50: 337718.92 | S50: 337718.92
B51: Adpr - Belencito | C51: COP/Ton | D51: 317580.14 | E51: 317580.14 | F51: 317580.14 | G51: 317580.14 | H51: 328256.78 | I51: 328256.78 | J51: 328256.78 | K51: 328256.78 | L51: 328256.78 | M51: 328256.78 | N51: 328256.78 | O51: 328256.78 | P51: 328256.78 | Q51: 328256.78 | R51: 328256.78 | S51: 328256.78
B52: Tap (Payandé) | C52: COP/Ton | D52: 308980.48 | E52: 308980.48 | F52: 308980.48 | G52: 308980.48 | H52: 233874 | I52: 233874 | J52: 233874 | K52: 233874 | L52: 233874 | M52: 233874 | N52: 233874 | O52: 233874 | P52: 233874 | Q52: 233874 | R52: 233874 | S52: 233874
B53: Calamina Gerdau - Diaco | C53: COP/Ton | D53: 134416.48 | E53: 134416.48 | F53: 134416.48 | G53: 134416.48 | H53: 141103.7 | I53: 141103.7 | J53: 141103.7 | K53: 141103.7 | L53: 141103.7 | M53: 141103.7 | N53: 141103.7 | O53: 141103.7 | P53: 141103.7 | Q53: 141103.7 | R53: 141103.7 | S53: 141103.7
B54: Calamina Sidoc | C54: COP/Ton | D54: 169612.88 | E54: 169612.88 | F54: 169612.88 | G54: 169612.88 | H54: 178051.56 | I54: 178051.56 | J54: 178051.56 | K54: 178051.56 | L54: 178051.56 | M54: 178051.56 | N54: 178051.56 | O54: 178051.56 | P54: 178051.56 | Q54: 178051.56 | R54: 178051.56 | S54: 178051.56
B55: Exiros - Atlantico | C55: COP/Ton | D55: 193876.24 | E55: 193876.24 | F55: 193876.24 | G55: 193876.24 | H55: 203526.05 | I55: 203526.05 | J55: 203526.05 | K55: 203526.05 | L55: 203526.05 | M55: 203526.05 | N55: 203526.05 | O55: 203526.05 | P55: 203526.05 | Q55: 203526.05 | R55: 203526.05 | S55: 203526.05
B56: Exiro - Manizales | C56: COP/Ton | D56: 124209 | E56: 124209 | F56: 124209 | G56: 124209 | H56: 128275.45 | I56: 128275.45 | J56: 128275.45 | K56: 128275.45 | L56: 128275.45 | M56: 128275.45 | N56: 128275.45 | O56: 128275.45 | P56: 128275.45 | Q56: 128275.45 | R56: 128275.45 | S56: 128275.45
B57: Flete (Boyacá - Planta) | C57: COP/Ton | D57: 117616.48 | E57: 117616.48 | F57: 117616.48 | G57: 117616.48 | H57: 123497.3 | I57: 123497.3 | J57: 123497.3 | K57: 123497.3 | L57: 123497.3 | M57: 123497.3 | N57: 123497.3 | O57: 123497.3 | P57: 123497.3 | Q57: 123497.3 | R57: 123497.3 | S57: 123497.3
B58: Flete (Cali - Planta) | C58: COP/Ton | D58: 148565.88 | E58: 148565.88 | F58: 148565.88 | G58: 148565.88 | H58: 155994.3 | I58: 155994.3 | J58: 155994.3 | K58: 155994.3 | L58: 155994.3 | M58: 155994.3 | N58: 155994.3 | O58: 155994.3 | P58: 155994.3 | Q58: 155994.3 | R58: 155994.3 | S58: 155994.3
B59: Flete (Barranquilla - Planta) | C59: COP/Ton | D59: 171876.24 | E59: 171876.24 | F59: 171876.24 | G59: 171876.24 | H59: 180470.05 | I59: 180470.05 | J59: 180470.05 | K59: 180470.05 | L59: 180470.05 | M59: 180470.05 | N59: 180470.05 | O59: 180470.05 | P59: 180470.05 | Q59: 180470.05 | R59: 180470.05 | S59: 180470.05
B60: Flete (Cartagena - Planta) | C60: COP/Ton | D60: 171394.34 | E60: 171394.34 | F60: 171394.34 | G60: 171394.34 | H60: 179964.06 | I60: 179964.06 | J60: 179964.06 | K60: 179964.06 | L60: 179964.06 | M60: 179964.06 | N60: 179964.06 | O60: 179964.06 | P60: 179964.06 | Q60: 179964.06 | R60: 179964.06 | S60: 179964.06
B61: Flete (Cundinamarca - Planta) | C61: COP/Ton | D61: 104584.14 | E61: 104584.14 | F61: 104584.14 | G61: 104584.14 | H61: 109813.2 | I61: 109813.2 | J61: 109813.2 | K61: 109813.2 | L61: 109813.2 | M61: 109813.2 | N61: 109813.2 | O61: 109813.2 | P61: 109813.2 | Q61: 109813.2 | R61: 109813.2 | S61: 109813.2
... B63: Flete (Manizales - Planta) | C63: COP/Ton | D63: 100209 | E63: 100209 | F63: 100209 | G63: 100209 | H63: 105219.45 | I63: 105219.45 | J63: 105219.45 | K63: 105219.45 | L63: 105219.45 | M63: 105219.45 | N63: 105219.45 | O63: 105219.45 | P63: 105219.45 | Q63: 105219.45 | R63: 105219.45 | S63: 105219.45
B64: Mezcla Ponderado | C64: COP/Ton | D64: =D66*0.7+D67*0.3 -> 220867.1 | E64: =E66*0.7+E67*0.3 -> 220867.1 | F64: =F66*0.7+F67*0.3 -> 220867.1 | G64: =G66*0.7+G67*0.3 -> 220867.1 | H64: =H65*H161+H66*H162+H67*H163 -> 231674.64 | I64: =I65*I161+I66*I162+I67*I163 -> 231674.64 | J64: =J65*J161+J66*J162+J67*J163 -> 231674.64 | K64: =K65*K161+K66*K162+K67*K163 -> 231674.64 | L64: =L65*L161+L66*L162+L67*L163 -> 231674.64 | M64: =M65*M161+M66*M162+M67*M163 -> 231674.64 | N64: =N65*N161+N66*N162+N67*N163 -> 231674.64 | O64: =O65*O161+O66*O162+O67*O163 -> 231674.64 | ... S64: =S65*S161+S66*S162+S67*S163 -> 231674.64
B65: Etex | C65: COP/Ton | D65: 414921.76 | E65: 414921.76 | F65: 414921.76 | G65: 414921.76 | H65: 434838 | I65: 455710.22 | J65: 455710.22 | K65: 455710.22 | L65: 455710.22 | M65: 455710.22 | N65: 455710.22 | O65: 455710.22 | P65: 455710.22 | Q65: 455710.22 | R65: 455710.22 | S65: 455710.22 | U65: Impacto 4% flete internacional, valor de material cargado sobre camión | V65: 5447650.5 | W65: 0.4942361 | X65: Etex | Y65: 503494
B66: Yesos Prada | C66: COP/Ton | D66: 220001 | E66: 220001 | F66: 220001 | G66: 220001 | H66: 230766.97 | I66: 230766.97 | J66: 230766.97 | K66: 230766.97 | L66: 230766.97 | M66: 230766.97 | N66: 230766.97 | O66: 230766.97 | P66: 230766.97 | Q66: 230766.97 | R66: 230766.97 | S66: 230766.97 | U66: Yeso nacional impacto local IPC y SML | V66: 2769203.6 | W66: 0.25123499 | X66: Yesos Prada | Y66: 206268.72
B67: Yeso Rey Miranda | C67: COP/Ton | D67: 222888 | E67: 222888 | F67: 222888 | G67: 222888 | H67: 233792.54 | I67: 233792.54 | J67: 233792.54 | K67: 233792.54 | L67: 233792.54 | M67: 233792.54 | N67: 233792.54 | O67: 233792.54 | P67: 233792.54 | Q67: 233792.54 | R67: 233792.54 | S67: 233792.54 | U67: Yeso nacional impacto local IPC y SML | V67: 2805510.5 | W67: 0.25452892 | X67: Yeso Rey Miranda | Y67: 208976.28
B68: Flete (Cartagena Planta) | C68: COP/Ton | D68: 171394.34 | E68: 171394.34 | F68: 171394.34 | G68: 171394.34 | H68: 179964.06 | I68: 179964.06 | J68: 179964.06 | K68: 179964.06 | L68: 179964.06 | M68: 179964.06 | N68: 179964.06 | O68: 179964.06 | P68: 179964.06 | Q68: 179964.06 | R68: 179964.06 | S68: 179964.06 | U68: Proyección incremento Logistica Alión
B69: Flete (Maicao - Planta) | C69: COP/Ton | H69: 0 | I69: 0 | J69: 0 | K69: 0 | L69: 0 | M69: 0 | N69: 0 | O69: 0 | P69: 0 | Q69: 0 | R69: 0 | S69: 0 | U69: Proyección incremento Logistica Alión
B70: Flete (Mesa De Los Santos A Planta) | C70: COP/Ton | D70: 102960 | E70: 102960 | F70: 102960 | G70: 102960 | H70: 108108 | I70: 108108 | J70: 108108 | K70: 108108 | L70: 108108 | M70: 108108 | N70: 108108 | O70: 108108 | P70: 108108 | Q70: 108108 | R70: 108108 | S70: 108108 | U70: Proyección incremento Logistica Alión
B71: Sacos 50 Kg Ug | C71: COP/Saco | D71: 1033 | E71: 1033 | F71: 1033 | G71: 1033 | H71: 967 | I71: 967 | J71: 994 | K71: 994 | L71: 994 | M71: 994 | N71: 994 | O71: 994 | P71: 1026 | Q71: 1026 | R71: 1026 | S71: 1026
B72: Sacos 42,5 Kg Ug | C72: COP/Saco | D72: 950 | E72: 950 | F72: 950 | G72: 950 | H72: 935 | I72: 935 | J72: 971 | K72: 971 | L72: 971 | M72: 971 | N72: 971 | O72: 971 | P72: 1003 | Q72: 1003 | R72: 1003 | S72: 1003
B73: Sacos 25 Kg | C73: COP/Saco | D73: 725 | E73: 725 | F73: 725 | G73: 725 | H73: 714 | I73: 714 | J73: 741 | K73: 741 | L73: 741 | M73: 741 | N73: 741 | O73: 741 | P73: 766 | Q73: 766 | R73: 766 | S73: 766
B74: Sacos 42,5 Kg Art | C74: COP/Saco | D74: 930 | E74: 930 | F74: 930 | G74: 930 | H74: 887 | I74: 887 | J74: 900 | K74: 900 | L74: 900 | M74: 900 | N74: 900 | O74: 900 | P74: 930 | Q74: 930 | R74: 930 | S74: 930
B75: Sacos 50 Kg Topex | C75: COP/Saco | D75: 1095 | E75: 1095 | F75: 1095 | G75: 1095 | H75: 1095 | I75: 1095 | J75: 1137 | K75: 1137 | L75: 1137 | M75: 1137 | N75: 1137 | O75: 1137 | P75: 1174 | Q75: 1174 | R75: 1174 | S75: 1174
B76: Aditivo Cemento | C76: COP/Kgr | D76: 4195000 | E76: 4195000 | F76: 4195000 | G76: 4195000 | H76: 4396360 | I76: 4396360 | J76: 4396360 | K76: 4396360 | L76: 4396360 | M76: 4396360 | N76: 4396360 | O76: 4396360 | P76: 4396360 | Q76: 4396360 | R76: 4396360 | S76: 4396360
B77: Sal Marina | C77: COP/Ton | D77: 0 | E77: 0 | F77: 0 | G77: 0 | H77: 0 | I77: 0 | J77: 0 | K77: 0 | L77: 0 | M77: 0 | N77: 0 | O77: 0 | P77: 0 | Q77: 0 | R77: 0 | S77: 0
B78: Diesel | C78: COP/Gal | D78: 9643 | E78: 9643 | F78: 9643 | G78: 9643 | H78: 12000 | I78: 12000 | J78: 12000 | K78: 12000 | L78: 12000 | M78: 12000 | N78: 12000 | O78: 12000 | P78: 12000 | Q78: 12000 | R78: 12000 | S78: 12000
B79: Empaque y Granel | C79: COP/Ton | D79: 1328 | E79: 1328 | F79: 1328 | G79: 1328 | H79: =H80+H81/H245 -> 3895.8805 | I79: =I80+I81/I245 -> 3736.4937 | J79: =J80+J81/J245 -> 3601.6208 | K79: =K80+K81/K245 -> 3738.3364 | L79: =L80+L81/L245 -> 3812.4978 | M79: =M80+M81/M245 -> 3840.5794 | N79: =N80+N81/N245 -> 3493.4957 | O79: =O80+O81/O245 -> 3684.616 | ... S79: =S80+S81/S245 -> 3664.7335
B80: Unitario Empaque y Granel | C80: COP/Saco | H80: 1455 | I80: 1455 | J80: 1455 | K80: 1455 | L80: 1455 | M80: 1455 | N80: 1455 | O80: 1455 | P80: 1455 | Q80: 1455 | R80: 1455 | S80: 1455
B81: Fijo + Horas Extras Empaque y Granel | C81: $ | H81: 241040000 | I81: 241040000 | J81: 241040000 | K81: 241040000 | L81: 241040000 | M81: 241040000 | N81: 241040000 | O81: 241040000 | P81: 241040000 | Q81: 241040000 | R81: 241040000 | S81: 241040000
B82: Cargador Carbón | C82: COP/Ton | D82: =9525*0 -> 0 | E82: =9525*0 -> 0 | F82: =9525*0 -> 0 | G82: =9525*0 -> 0 | H82: =9982.2*0+6325 -> 6325 | I82: =9982.2*0+6325 -> 6325 | J82: =9982.2*0+6325 -> 6325 | K82: =9982.2*0+6325 -> 6325 | L82: =9982.2*0+6325 -> 6325 | M82: =9982.2*0+6325 -> 6325 | N82: =9982.2*0+6325 -> 6325 | O82: =9982.2*0+6325 -> 6325 | ... S82: =9982.2*0+6325 -> 6325
B83: Descarge Finos (Mini) | C83: COP/Ton | D83: =9082*0 -> 0 | E83: =9082*0 -> 0 | F83: =9082*0 -> 0 | G83: =9082*0 -> 0 | H83: =9517.936*0+8700 -> 8700 | I83: =9517.936*0+8700 -> 8700 | J83: =9517.936*0+8700 -> 8700 | K83: =9517.936*0+8700 -> 8700 | L83: =9517.936*0+8700 -> 8700 | M83: =9517.936*0+8700 -> 8700 | N83: =9517.936*0+8700 -> 8700 | O83: =9517.936*0+8700 -> 8700 | ... S83: =9517.936*0+8700 -> 8700
B84: Descargue De Alternos | C84: COP/Ton | D84: 9952.2293 | E84: 9952.2293 | F84: 9952.2293 | G84: =H84/1.0048 -> 10673.766 | H84: =10000*0+10725 -> 10725 | I84: =10000*0+10725 -> 10725 | J84: =10000*0+10725 -> 10725 | K84: =10000*0+10725 -> 10725 | L84: =10000*0+10725 -> 10725 | M84: =10000*0+10725 -> 10725 | N84: =10000*0+10725 -> 10725 | O84: =10000*0+10725 -> 10725 | ... S84: =10000*0+10725 -> 10725
B85: Cargue De Alternos | C85: COP/Ton | D85: 6998.9443 | E85: 6998.9443 | F85: 6998.9443 | G85: 6998.9443 | H85: =(H86*H87)/SUM(H464:H467) -> 7600.3518 | I85: =(I86*I87)/SUM(I464:I467) -> 7507.6646 | J85: =(J86*J87)/SUM(J464:J467) -> 10800.5 | K85: =(K86*K87)/SUM(K464:K467) -> 10260.475 | L85: =(L86*L87)/SUM(L464:L467) -> 6765.1483 | M85: =(M86*M87)/SUM(M464:M467) -> 15785.346 | N85: =(N86*N87)/SUM(N464:N467) -> 8208.38 | O85: =(O86*O87)/SUM(O464:O467) -> 6765.1483 | ... S85: =(S86*S87)/SUM(S464:S467) -> 11088.982
B86: Tarifa Alternos | C86: $ | H86: 240000 | I86: 240000 | J86: 240000 | K86: 240000 | L86: 240000 | M86: 240000 | N86: 240000 | O86: 240000 | P86: 240000 | Q86: 240000 | R86: 240000 | S86: 240000
B87: Horas Alternos | C87: Horas | H87: 50 | I87: 50 | J87: 50 | K87: 50 | L87: 50 | M87: 50 | N87: 50 | O87: 50 | P87: 50 | Q87: 50 | R87: 50 | S87: 50
B88: Desatasque De Carbón | C88: COP/Mes | D88: =31673857 -> 31673857 | E88: =31673857 -> 31673857 | F88: =31673857 -> 31673857 | G88: =31673857 -> 31673857 | H88: =H89/H272 -> 3861.423 | I88: =I89/I272 -> 3814.2886 | J88: =J89/J272 -> 5489.4637 | K88: =K89/K272 -> 5248.0385 | L88: =L89/L272 -> 3436.7348 | M88: =M89/M272 -> 8028.0267 | N88: =N89/N272 -> 4191.9873 | O88: =O89/O272 -> 3436.7348 | ... S88: =S89/S272 -> 5675.3261
B89: Tarifa Desatasque | C89: $ | H89: 35498552 | I89: 35498552 | J89: 35498552 | K89: 35498552 | L89: 35498552 | M89: 35498552 | N89: 35498552 | O89: 35498552 | P89: 35498552 | Q89: 35498552 | R89: 35498552 | S89: 35498552
B90: Descargue Mp'S | C90: COP/Ton | D90: 17350509 | E90: 17350509 | F90: 17350509 | G90: 17350509 | H90: =H91/SUM(H468:H473,H461:H463) -> 884.81713 | I90: =I91/SUM(I468:I473,I461:I463) -> 856.58137 | J90: =J91/SUM(J468:J473,J461:J463) -> 1027.8214 | K90: =K91/SUM(K468:K473,K461:K463) -> 1035.0477 | L90: =L91/SUM(L468:L473,L461:L463) -> 810.38414 | M90: =M91/SUM(M468:M473,M461:M463) -> 1307.9095 | N90: =N91/SUM(N468:N473,N461:N463) -> 866.54358 | O90: =O91/SUM(O468:O473,O461:O463) -> 796.06789 | ... S90: =S91/SUM(S468:S473,S461:S463) -> 1062.0695
B91: Descargue Mp'S | C91: $ | H91: 18183333 | I91: =H91 -> 18183333 | J91: =I91 -> 18183333 | K91: =J91 -> 18183333 | L91: =K91 -> 18183333 | M91: =L91 -> 18183333 | N91: =M91 -> 18183333 | O91: =N91 -> 18183333 | P91: =O91 -> 18183333 | ... S91: =R91 -> 18183333
B92: Impuesto Al Carbón | C92: COP/Ton | D92: =69787.61*25% -> 17446.903 | E92: =D92 -> 17446.903 | F92: =E92 -> 17446.903 | G92: =F92 -> 17446.903 | H92: =69787.61*1.048*50% -> 36568.708 | I92: =H92 -> 36568.708 | J92: =I92 -> 36568.708 | K92: =J92 -> 36568.708 | L92: =K92 -> 36568.708 | M92: =L92 -> 36568.708 | N92: =M92 -> 36568.708 | O92: =N92 -> 36568.708 | P92: =O92 -> 36568.708 | ... S92: =R92 -> 36568.708
B93: Puzolana La Dorada | C93: COP/Ton | D93: 99256 | E93: 99256 | F93: 99256 | G93: 99256 | H93: 104128.8 | I93: 104128.8 | J93: 104128.8 | K93: 104128.8 | L93: 104128.8 | M93: 104128.8 | N93: 104128.8 | O93: 104128.8 | P93: 104128.8 | Q93: 104128.8 | R93: 104128.8 | S93: 104128.8
B94: Flete (La Dorada A Planta) | C94: COP/Ton | D94: 54256 | E94: 54256 | F94: 54256 | G94: 54256 | H94: 56968.8 | I94: 56968.8 | J94: 56968.8 | K94: 56968.8 | L94: 56968.8 | M94: 56968.8 | N94: 56968.8 | O94: 56968.8 | P94: 56968.8 | Q94: 56968.8 | R94: 56968.8 | S94: 56968.8
B95: Cargue Clinker Pm(En La Tolva) | C95: COP/Ton | D95: 8444 | E95: 8345.63 | F95: 8345.63 | G95: 8345.63 | H95: 6160 | I95: 6160 | J95: 6160 | K95: 6160 | L95: 6160 | M95: 6160 | N95: 6160 | O95: 6160 | P95: 6160 | Q95: 6160 | R95: 6160 | S95: 6160
B96: Cargue Clinker Venta | C96: COP/Ton | D96: 8444 | E96: 8345.63 | F96: 8345.63 | G96: 8345.63 | H96: 6160 | I96: 6160 | J96: 6160 | K96: 6160 | L96: 6160 | M96: 6160 | N96: 6160 | O96: 6160 | P96: 6160 | Q96: 6160 | R96: 6160 | S96: 6160
B97: Dosificacion Sal | C97: COP/Ton | H97: 5000 | I97: 5000 | J97: 5000 | K97: 5000 | L97: 5000 | M97: 5000 | N97: 5000 | O97: 5000 | P97: 5000 | Q97: 5000 | R97: 5000 | S97: 5000
B98: Precio Regalías Arcilla | C98: COP/Ton | H98: 281.31736 | I98: 281.31736 | J98: 281.31736 | K98: 281.31736 | L98: 281.31736 | M98: 281.31736 | N98: 281.31736 | O98: 281.31736 | P98: 281.31736 | Q98: 281.31736 | R98: 281.31736 | S98: 281.31736
B99: Precio Regalías Caliza | C99: COP/Ton | H99: 118.58675 | I99: 118.58675 | J99: 118.58675 | K99: 118.58675 | L99: 118.58675 | M99: 118.58675 | N99: 118.58675 | O99: 118.58675 | P99: 118.58675 | Q99: 118.58675 | R99: 118.58675 | S99: 118.58675
B100: Ductos Del Horno | C100: COP/Ton | H100: =H101/SUM($H$260:$S$260) -> 0 | I100: =I101/SUM($H$260:$S$260) -> 0 | J100: =J101/SUM($H$260:$S$260) -> 0 | K100: =K101/SUM($H$260:$S$260) -> 0 | L100: =L101/SUM($H$260:$S$260) -> 0 | M100: =M101/SUM($H$260:$S$260) -> 0 | N100: =N101/SUM($H$260:$S$260) -> 0 | O100: =O101/SUM($H$260:$S$260) -> 0 | ... S100: =S101/SUM($H$260:$S$260) -> 0 | U100: =191056000*0 -> 0 | V100: =B100 -> Ductos Del Horno
B101: Ductos Del Horno | C101: $ | H101: 0 | I101: =H101 -> 0 | J101: =I101 -> 0 | K101: =J101 -> 0 | L101: =K101 -> 0 | M101: =L101 -> 0 | N101: =M101 -> 0 | O101: =N101 -> 0 | P101: =O101 -> 0 | ... S101: =R101 -> 0
B102: Enfriador De Parrillas/Triturad | C102: COP/Ton | H102: =H103/SUM($H$266:$S$266,$H$269:$S$269) -> 0 | I102: =I103/SUM($H$266:$S$266,$H$269:$S$269) -> 0 | J102: =J103/SUM($H$266:$S$266,$H$269:$S$269) -> 0 | K102: =K103/SUM($H$266:$S$266,$H$269:$S$269) -> 0 | L102: =L103/SUM($H$266:$S$266,$H$269:$S$269) -> 0 | M102: =M103/SUM($H$266:$S$266,$H$269:$S$269) -> 0 | N102: =N103/SUM($H$266:$S$266,$H$269:$S$269) -> 0 | O102: =O103/SUM($H$266:$S$266,$H$269:$S$269) -> 0 | ... S102: =S103/SUM($H$266:$S$266,$H$269:$S$269) -> 0 | U102: =191056000*0 -> 0 | V102: =B102 -> Enfriador De Parrillas/Triturad
B103: Enfriador De Parrillas/Triturad | C103: $ | H103: 0 | I103: =H103 -> 0 | J103: =I103 -> 0 | K103: =J103 -> 0 | L103: =K103 -> 0 | M103: =L103 -> 0 | N103: =M103 -> 0 | O103: =N103 -> 0 | P103: =O103 -> 0 | ... S103: =R103 -> 0
B104: Enfriador Horno | C104: COP/Ton | H104: =H105/SUM($H$260:$S$260) -> 184.45896 | I104: =I105/SUM($H$260:$S$260) -> 184.45896 | J104: =J105/SUM($H$260:$S$260) -> 184.45896 | K104: =K105/SUM($H$260:$S$260) -> 184.45896 | L104: =L105/SUM($H$260:$S$260) -> 184.45896 | M104: =M105/SUM($H$260:$S$260) -> 184.45896 | N104: =N105/SUM($H$260:$S$260) -> 184.45896 | O104: =O105/SUM($H$260:$S$260) -> 184.45896 | ... S104: =S105/SUM($H$260:$S$260) -> 184.45896 | U104: 158000000 | V104: Enfriador Horno
B105: Enfriador Horno | C105: $ | H105: 158000000 | I105: =H105 -> 158000000 | J105: =I105 -> 158000000 | K105: =J105 -> 158000000 | L105: =K105 -> 158000000 | M105: =L105 -> 158000000 | N105: =M105 -> 158000000 | O105: =N105 -> 158000000 | P105: =O105 -> 158000000 | ... S105: =R105 -> 158000000
...

Sheet ORD
A1: Material | B1: Proceso | C1: ORD
A2: MEZCLA PREHOMO | B2: Trituración | C2: 1
A3: CALIZA PARA ADICIONES | B3: Adiciones | C3: 2
A4: HARINA CRUDA | B4: Molienda de Crudo | C4: 3
A5: CARBON MOLIDO | B5: Molienda de Carbón | C5: 4
A6: CLINKER | B6: Clinkerización | C6: 5
A7: CEMENTO UG | B7: Cemento UG | C7: 6
A8: CEMENTO ART | B8: Cemento ART | C8: 7
A9: CEMENTO UG 50 KG | B9: CEMENTO UG 50 KG | C9: 8
A10: CEMENTO UG 42,5 KG | B10: CEMENTO UG 42,5 KG | C10: 9
A11: CEMENTO UG 25 KG | B11: CEMENTO UG 25 KG | C11: 10
A12: CEMENTO ART 42,5 KG | B12: CEMENTO ART 42,5 KG | C12: 11
A13: CEMENTO TOPEX 50 KG | B13: CEMENTO TOPEX 50 KG | C13: 14
... A18: CEMENTOS | B18: Cementos | C18: 21

Sheet Maestro
A1: Concatenado | B1: Clase de coste | C1: Denom.clase de coste | D1: Material | E1: Mat2 | F1: Proceso | G1: ORD | H1: Tp | J1: Orden | K1: Clasif
A2: =B2&D2&F2 -> 7199990001CALTLVTRITTrituración | B2: 7199990001 | C2: CONSUMOS SEMIELBORAD | D2: CALTLVTRIT | E2: MEZCLA PREHOMO | F2: Trituración | G2: 1 | H2: Caliza | J2: 700000 | K2: HARINA CRUDA
A3: =B3&D3&F3 -> 7199990001ARCTLVTRITTrituración | B3: 7199990001 | C3: CONSUMOS SEMIELBORAD | D3: ARCTLVTRIT | E3: MEZCLA PREHOMO | F3: Trituración | G3: 1 | H3: Arcilla | J3: 700001 | K3: CLINKER
A4: =B4&D4&F4 -> 7105330101CALIZATRIMolienda de Crudo | B4: 7105330101 | C4: CTO. MP CALIZAS NAL | D4: CALIZATRI | E4: HARINA CRUDA | F4: Molienda de Crudo | G4: 3 | H4: Caliza | J4: 700002 | K4: CARBON MOLIDO
A5: =B5&D5&F5 -> 7105330101MEZCPREHOMolienda de Crudo | B5: 7105330101 | C5: CTO. MP CALIZAS NAL | D5: MEZCPREHO | E5: HARINA CRUDA | F5: Molienda de Crudo | G5: 3 | H5: Prehomo | J5: 700003 | K5: CEMENTO UG
A6: =B6&D6&F6 -> 7105040101CORRHIERRMolienda de Crudo | B6: 7105040101 | C6: MP CORRECT HIERO NAL | D6: CORRHIERR | E6: HARINA CRUDA | F6: Molienda de Crudo | G6: 3 | H6: Mineral de Hierro | J6: 700004 | K6: CEMENTO UG 42,5 KG
A7: =B7&D7&F7 -> 7355050103CARBITUMIMolienda de Carbón | B7: 7355050103 | C7: CTO COMBUS SOL NAC | D7: CARBITUMI | E7: CARBON MOLIDO | F7: Molienda de Carbón | G7: 4 | H7: Carbón | J7: 700005 | K7: CALIZA PARA ADICIONES
A8: =B8&D8&F8 -> 7199990001CARBONMOLClinkerización | B8: 7199990001 | C8: CONSUMOS SEMIELBORAD | D8: CARBONMOL | E8: CLINKER | F8: Clinkerización | G8: 5 | H8: Carbón Molido | J8: 700006 | K8: CALIZA EN TOLVA TRITURADORA
A9: =B9&D9&F9 -> 7199990001HARINACRUDClinkerización | B9: 7199990001 | C9: CONSUMOS SEMIELBORAD | D9: HARINACRUD | E9: CLINKER | F9: Clinkerización | G9: 5 | H9: Crudo | J9: 700007 | K9: MEZCLA PREHOMO
A10: =B10&D10&F10 -> 735505010470000000034Clinkerización | B10: 7355050104 | C10: CTO COMBUS GAS NAC | D10: 70000000034 | E10: CLINKER | F10: Clinkerización | G10: 5 | H10: Gasoil | J10: 700008 | K10: ARCILLA EN TOLVA TRITURADORA
A11: =B11&D11&F11 -> 735505010570000000000Clinkerización | B11: 7355050105 | C11: CTO COMBUS LIQ NAC | D11: 70000000000 | E11: CLINKER | F11: Clinkerización | G11: 5 | H11: Gasoil | J11: 700070 | K11: COMBUSTIBLES ALTERNOS
A12: =B12&D12&F12 -> 7199990001CLINKER001Cemento UG | B12: 7199990001 | C12: CONSUMOS SEMIELBORAD | D12: CLINKER001 | E12: CEMENTO UG | F12: Cemento UG | G12: 6 | H12: Clinker | J12: 700034 | K12: CEMENTO ART 42,5 KG
A13: =B13&D13&F13 -> 7105450101YESO00001Cemento UG | B13: 7105450101 | C13: CTO. MP YES/ESCA NAL | D13: YESO00001 | E13: CEMENTO UG | F13: Cemento UG | G13: 6 | H13: Yeso | J13: 700037 | K13: CEMENTO ART 50 KG
A14: =B14&D14&F14 -> 7105330101CALIZATRICemento UG | B14: 7105330101 | C14: CTO. MP CALIZAS NAL | D14: CALIZATRI | E14: CEMENTO UG | F14: Cemento UG | G14: 6 | H14: Caliza Triturada | J14: 700040 | K14: CEMENTO A GRANEL ART
A15: =B15&D15&F15 -> 7199990001CLINKER001Cemento ART | B15: 7199990001 | C15: CONSUMOS SEMIELBORAD | D15: CLINKER001 | E15: CEMENTO ART | F15: Cemento ART | G15: 7 | H15: Clinker | J15: 700053 | K15: CEMENTO UG 50 KG
A16: =B16&D16&F16 -> 7105450101YESO00001Cemento ART | B16: 7105450101 | C16: CTO. MP YES/ESCA NAL | D16: YESO00001 | E16: CEMENTO ART | F16: Cemento ART | G16: 7 | H16: Yeso | J16: 700055 | K16: CEMENTO UG 50 KG
A17: =B17&D17&F17 -> 7105330101CALIZATRICemento ART | B17: 7105330101 | C17: CTO. MP CALIZAS NAL | D17: CALIZATRI | E17: CEMENTO ART | F17: Cemento ART | G17: 7 | H17: Caliza Triturada | J17: 700060 | K17: CEMENTO ART
A18: =B18&D18&F18 -> 7199990001CALTLVTRITAdiciones | B18: 7199990001 | C18: CONSUMOS SEMIELBORAD | D18: CALTLVTRIT | E18: CALIZA PARA ADICIONES | F18: Adiciones | G18: 2 | H18: Caliza | J18: 700048 | K18: CEMENTO UG 25 KG
A19: =B19&D19&F19 -> 735505010570000000000Cemento UG | B19: 7355050105 | C19: CTO COMBUS LIQ NAC | D19: 70000000000 | E19: CLINKER | F19: Cemento UG | G19: 6 | H19: Gasoil | J19: 700080 | K19: CEMENTO TOPEX 50 KG
A20: =B20&D20&F20 -> 7199990001CEMENTOARTCEMENTO ART 42,5 KG | B20: 7199990001 | C20: CONSUMOS SEMIELBORAD | D20: CEMENTOART | E20: CEMENTO ART 42,5 KG | F20: CEMENTO ART 42,5 KG | G20: 11 | H20: Cemento ART | J20: 700083 | K20: CALIZA PARA ADICIONES
A21: =B21&D21&F21 -> 736005030222000000005CEMENTO ART 42,5 KG | B21: 7360050302 | C21: CTO BOLSAS IMP | D21: 22000000005 | E21: CEMENTO ART 42,5 KG | F21: CEMENTO ART 42,5 KG | G21: 11 | H21: Sacos | J21: 700036 | K21: CEMENTO ART 42,5 KG
A22: =B22&D22&F22 -> 7199990001CEMENTOUG1CEMENTO UG 50 KG | B22: 7199990001 | C22: CONSUMOS SEMIELBORAD | D22: CEMENTOUG1 | E22: CEMENTO UG 50 KG | F22: CEMENTO UG 50 KG | G22: 8 | H22: Cemento UG | J22: 700050 | K22: CEMENTO UG 25 KG
A23: =B23&D23&F23 -> 736005030222000000008CEMENTO UG 50 KG | B23: 7360050302 | C23: CTO BOLSAS IMP | D23: 22000000008 | E23: CEMENTO UG 50 KG | F23: CEMENTO UG 50 KG | G23: 8 | H23: Sacos | J23: 700052 | K23: CEMENTO UG 42,5 KG
A24: =B24&D24&F24 -> 7199990001CEMENTO ARTCEMENTO A GRANEL ART | B24: 7199990001 | C24: CONSUMOS SEMIELBORAD | D24: CEMENTO ART | E24: CEMENTO A GRANEL ART | F24: CEMENTO A GRANEL ART | G24: 12 | H24: Cemento ART | J24: 700090 | K24: CEMENTO UG TP
A25: =B25&D25&F25 -> 7199990001CEMENTO ARTCEMENTO ART 50 KG | B25: 7199990001 | C25: CONSUMOS SEMIELBORAD | D25: CEMENTO ART | E25: CEMENTO ART 50 KG | F25: CEMENTO ART 50 KG | G25: 13 | H25: Cemento ART | J25: 700091 | K25: FIBROCEMENTO
A26: =B26&D26&F26 -> 7199990001CEMENTOUG1CEMENTO UG 42,5 KG | B26: 7199990001 | C26: CONSUMOS SEMIELBORAD | D26: CEMENTOUG1 | E26: CEMENTO UG 42,5 KG | F26: CEMENTO UG 42,5 KG | G26: 9 | H26: Cemento UG | J26: 700100 | K26: CEMENTO BIG BAG 1,5 TONELADAS
A27: =B27&D27&F27 -> 736005030222000000004CEMENTO UG 25 KG | B27: 7360050302 | C27: CTO BOLSAS IMP | D27: 22000000004 | E27: CEMENTO UG 25 KG | F27: CEMENTO UG 25 KG | G27: 10 | H27: Sacos | J27: 700064 | K27: FIBROCEMENTO
A28: =B28&D28&F28 -> 7199990001CEMENTOUG1CEMENTO UG 25 KG | B28: 7199990001 | C28: CONSUMOS SEMIELBORAD | D28: CEMENTOUG1 | E28: CEMENTO UG 25 KG | F28: CEMENTO UG 25 KG | G28: 10 | H28: Cemento UG | J28: 700120 | K28: COMBUSTIBLES ALTERNOS
A29: =B29&D29&F29 -> 736005030222000000006CEMENTO UG 42,5 KG | B29: 7360050302 | C29: CTO BOLSAS IMP | D29: 22000000006 | E29: CEMENTO UG 42,5 KG | F29: CEMENTO UG 42,5 KG | G29: 9 | H29: Sacos | J29: 700056 | K29: Cementos
A30: =B30&D30&F30 -> 7495700001REGALIASAdiciones | B30: 7495700001 | C30: SERVICIOS DE EXPLOTA | D30: REGALIAS | E30: CALIZA PARA ADICIONES | F30: Adiciones | G30: 2 | H30: Regalías
A31: =B31&D31&F31 -> 7199990001CEMENTO UG TPCEMENTO TOPEX 50 KG | B31: 7199990001 | C31: CONSUMOS SEMIELBORAD | D31: CEMENTO UG TP | E31: CEMENTO TOPEX 50 KG | F31: CEMENTO TOPEX 50 KG | G31: 14 | H31: Cemento UG TP
A32: =B32&D32&F32 -> 736005030222000000041CEMENTO TOPEX 50 KG | B32: 7360050302 | C32: CTO BOLSAS IMP | D32: 22000000041 | E32: CEMENTO TOPEX 50 KG | F32: CEMENTO TOPEX 50 KG | G32: 14 | H32: Sacos
A33: =B33&D33&F33 -> 7355250320CUERPOS MOLEDORESMolienda de Crudo | B33: 7355250320 | C33: RTOS VARIA IMPO | D33: CUERPOS MOLEDORES | E33: HARINA CRUDA | F33: Molienda de Crudo | G33: 3 | H33: Cuerpos Moledores
A34: =B34&D34&F34 -> 7355250321LAMINASMolienda de Crudo | B34: 7355250321 | C34: RTOS VARIA IMPO | D34: LAMINAS | E34: HARINA CRUDA | F34: Molienda de Crudo | G34: 3 | H34: Láminas
A35: =B35&D35&F35 -> 7355250322ANILLOS, TAPAS Y SEPARADORESMolienda de Crudo | B35: 7355250322 | C35: RTOS VARIA IMPO | D35: ANILLOS, TAPAS Y SEPARADORES | E35: HARINA CRUDA | F35: Molienda de Crudo | G35: 3 | H35: Anillos, Tapas y Separadores
A36: =B36&D36&F36 -> 7355250320CUERPOS MOLEDORES Y LAMINASMolienda de Carbón | B36: 7355250320 | C36: RTOS VARIA IMPO | D36: CUERPOS MOLEDORES Y LAMINAS | E36: CARBON MOLIDO | F36: Molienda de Carbón | G36: 4 | H36: Cuerpos Moledores y Láminas
A37: =B37&D37&F37 -> 7355250321DESCARGUE FINOS CARBONMolienda de Carbón | B37: 7355250321 | C37: RTOS VARIA IMPO | D37: DESCARGUE FINOS CARBON | E37: FINOS DE CARBON | F37: Molienda de Carbón | G37: 4 | H37: Descargue Finos Carbón
A38: =B38&D38&F38 -> 7355250320DUCTOSClinkerización | B38: 7355250320 | C38: RTOS VARIA IMPO | D38: DUCTOS | E38: CLINKER | F38: Clinkerización | G38: 5 | H38: Ductos
A39: =B39&D39&F39 -> 7355250321ENFRIADORClinkerización | B39: 7355250321 | C39: RTOS VARIA IMPO | D39: ENFRIADOR | E39: CLINKER | F39: Clinkerización | G39: 5 | H39: Enfriador
A40: =B40&D40&F40 -> 7355250323SELLADOClinkerización | B40: 7355250323 | C40: RTOS VARIA IMPO | D40: SELLADO | E40: CLINKER | F40: Clinkerización | G40: 5 | H40: Sellado
A41: =B41&D41&F41 -> 7355250324CARGUE CLINKERClinkerización | B41: 7355250324 | C41: RTOS VARIA IMPO | D41: CARGUE CLINKER | E41: CLINKER | F41: Clinkerización | G41: 5 | H41: Cargue Clinker
... A72: =B72&D72&F72 -> 7355250320PLACAS Y SEGMENTOSFibrocemento | B72: 7355250320 | C72: RTOS VARIA IMPO | D72: PLACAS Y SEGMENTOS | E72: FIBROCEMENTO | F72: Fibrocemento | G72: 16 | H72: Placas y Segmentos
A73: =B73&D73&F73 -> 735505010570000000000Cemento ART | B73: 7355050105 | C73: CTO COMBUS LIQ NAC | D73: 70000000000 | E73: CLINKER | F73: Cemento ART | G73: 7 | H73: Gasoil
A74: =B74&D74&F74 -> 735505010570000000000Cemento UG TP | B74: 7355050105 | C74: CTO COMBUS LIQ NAC | D74: 70000000000 | E74: CLINKER | F74: Cemento UG TP | G74: 15 | H74: Gasoil
A75: =B75&D75&F75 -> 735505010570000000000Fibrocemento | B75: 7355050105 | C75: CTO COMBUS LIQ NAC | D75: 70000000000 | E75: CLINKER | F75: Fibrocemento | G75: 16 | H75: Gasoil
A76: =B76&D76&F76 -> 7105330101SALMARCemento UG | B76: 7105330101 | C76: CTO. MP CALIZAS NAL | D76: SALMAR | E76: CEMENTO UG | F76: Cemento UG | G76: 9 | H76: Sal Marina
A77: =B77&D77&F77 -> 7199990001CEMENTOARTCEMENTO BIG BAG 1,5 TONELADAS | B77: 7199990001 | C77: CONSUMOS SEMIELBORAD | D77: CEMENTOART | E77: CEMENTO BIG BAG 1,5 TONELADAS | F77: CEMENTO BIG BAG 1,5 TONELADAS | G77: 19 | H77: Cemento ART
A78: =B78&D78&F78 -> 736005030222000000001CEMENTO BIG BAG 1,5 TONELADAS | B78: 7360050302 | C78: CTO BOLSAS IMP | D78: 22000000001 | E78: CEMENTO BIG BAG 1,5 TONELADAS | F78: CEMENTO BIG BAG 1,5 TONELADAS | G78: 19 | H78: Sacos
A79: =B79&D79&F79 -> 7405990999CARGUECEMENTO BIG BAG 1,5 TONELADAS | B79: 7405990999 | C79: OTROS SERVICIOS | D79: CARGUE | E79: CEMENTO BIG BAG 1,5 TONELADAS | F79: CEMENTO BIG BAG 1,5 TONELADAS | G79: 19 | H79: Cargue
A80: =B80&D80&F80 -> 7105040101CALAMINA1Molienda de Crudo | B80: 7105040101 | C80: MP CORRECT HIERO NAL | D80: CALAMINA1 | E80: HARINA CRUDA | F80: Molienda de Crudo | G80: 3 | H80: Mineral de Hierro
A81: =B81&D81&F81 -> 7355050103CARMIXTOMolienda de Carbón | B81: 7355050103 | C81: CTO COMBUS SOL NAC | D81: CARMIXTO | E81: CARBON MOLIDO | F81: Molienda de Carbón | G81: 4 | H81: Carbón
A82: =B82&D82&F82 -> 7355050103FINOSCARBMolienda de Carbón | B82: 7355050103 | C82: CTO COMBUS SOL NAC | D82: FINOSCARB | E82: CARBON MOLIDO | F82: Molienda de Carbón | G82: 4 | H82: Carbón
A83: =B83&D83&F83 -> 7355050103Combustibles AlternosCOMBUSTIBLES ALTERNOS | B83: 7355050103 | C83: CTO COMBUS SOL NAC | D83: Combustibles Alternos | E83: COMBUSTIBLES ALTERNOS | F83: COMBUSTIBLES ALTERNOS | G83: 20 | H83: Combustibles Alternos
A84: =B84&D84&F84 -> 7105240101BIOBRIQPAPCOMBUSTIBLES ALTERNOS | B84: 7105240101 | C84: MP ADICIO ACTIVA NAL | D84: BIOBRIQPAP | E84: COMBUSTIBLES ALTERNOS | F84: COMBUSTIBLES ALTERNOS | G84: 20 | H84: Briquetas
A85: =B85&D85&F85 -> 7105240101BIOCHIPMADCOMBUSTIBLES ALTERNOS | B85: 7105240101 | C85: MP ADICIO ACTIVA NAL | D85: BIOCHIPMAD | E85: COMBUSTIBLES ALTERNOS | F85: COMBUSTIBLES ALTERNOS | G85: 20 | H85: Chip de Madera
A86: =B86&D86&F86 -> 7355050101COMBURESIDCOMBUSTIBLES ALTERNOS | B86: 7355050101 | C86: CTO. COMBUSTIBLES | D86: COMBURESID | E86: COMBUSTIBLES ALTERNOS | F86: COMBUSTIBLES ALTERNOS | G86: 20 | H86: CDR
A87: =B87&D87&F87 -> 7355050101LLANTAPICACOMBUSTIBLES ALTERNOS | B87: 7355050101 | C87: CTO. COMBUSTIBLES | D87: LLANTAPICA | E87: COMBUSTIBLES ALTERNOS | F87: COMBUSTIBLES ALTERNOS | G87: 20 | H87: Llanta Picada
A88: =B88&D88&F88 -> 7105400101ADIMOLIENCemento UG | B88: 7105400101 | C88: CTO.MP COMPUESTO NAL | D88: ADIMOLIEN | E88: CEMENTO UG | F88: Cemento UG | G88: 6 | H88: Aditivo Molienda
A89: =B89&D89&F89 -> 7105400101PUZOLANACemento UG | B89: 7105400101 | C89: CTO.MP COMPUESTO NAL | D89: PUZOLANA | E89: CEMENTO UG | F89: Cemento UG | G89: 6 | H89: Puzolana
A90: =B90&D90&F90 -> 7105400101CRUDOCemento UG | B90: 7105400101 | C90: CTO.MP COMPUESTO NAL | D90: CRUDO | E90: CEMENTO UG | F90: Cemento UG | G90: 6 | H90: Finos Filtro
... A125: =B125&D125&F125 -> 7105400101EMPAQUE Y GRANELCementos | B125: 7105400101 | C125: CTO.MP COMPUESTO NAL | D125: EMPAQUE Y GRANEL | E125: Cementos | F125: Cementos | G125: 20 | H125: Empaque y Granel

Sheet Base
A1: Clase de coste | B1: Denom.clase de coste | C1: Valor/mon.inf. | D1: Cantidad total reg. | E1: Ud. cantidad contab. | F1: Clase cta. de contrapartida | G1: Cta.contrapartida | H1: Denominacion cuenta contrapartida | I1: Centro | J1: Material | K1: Orden | L1: Período | M1: Texto breve de material | N1: Fe.contabilización | O1: Fecha de documento | P1: Mat2 | Q1: Proceso | R1: ORD | S1: CN | T1: Tipo | U1: Arrastre
A2: 7105040101 | B2: MP CORRECT HIERO NAL | C2: =Datos!$I$48*D2+Datos!$H$90*Base!D2 -> 8.8179093e+08 | D2: =Datos!$H$263*Datos!$H$169*(1+Datos!$H$213) -> 2931.225 | E2: T | F2: M | G2: 1405040101 | H2: IN CORRECT HIERO NAL | I2: EC01 | J2: CORRHIERR | K2: 700000 | L2: 1 | M2: CORRECTOR DE HIERRO | P2: =VLOOKUP(K2,Maestro!J:K,2,0) -> HARINA CRUDA | Q2: =VLOOKUP(P2,Maestro!E:F,2,0) -> Molienda de Crudo | R2: =VLOOKUP(P2,ORD!$A:$C,3,0) -> 3 | S2: =A2&J2&Q2 -> 7105040101CORRHIERRMolienda de Crudo | T2: =IFERROR(VLOOKUP(S2,Maestro!$A:$H,8,0),"Producción") -> Mineral de Hierro | U2: Clinker
A3: 7105040101 | B3: MP CORRECT HIERO NAL | C3: =Datos!$H$49*D3+Datos!$H$90*D3 -> 85178561 | D3: =Datos!$H$263*Datos!$H$170*(1+Datos!$H$214) -> 499.87575 | E3: T | F3: M | G3: 1405040101 | H3: IN CORRECT HIERO NAL | I3: EC01 | J3: CALAMINA1 | K3: 700000 | L3: 1 | M3: CALAMINA | P3: =VLOOKUP(K3,Maestro!J:K,2,0) -> HARINA CRUDA | Q3: =VLOOKUP(P3,Maestro!E:F,2,0) -> Molienda de Crudo | R3: =VLOOKUP(P3,ORD!$A:$C,3,0) -> 3 | S3: =A3&J3&Q3 -> 7105040101CALAMINA1Molienda de Crudo | T3: =IFERROR(VLOOKUP(S3,Maestro!$A:$H,8,0),"Producción") -> Mineral de Hierro | U3: Clinker
A4: 7105330101 | B4: CTO. MP CALIZAS NAL | D4: =Datos!$H$263*Datos!$H$168*(1+Datos!$H$210) -> 24130.92 | E4: T | F4: M | G4: 1405330101 | H4: INV. CALIZAS NAL | I4: EC01 | J4: CALIZATRI | K4: 700000 | L4: 1 | M4: CALIZA TRITURADA | P4: =VLOOKUP(K4,Maestro!J:K,2,0) -> HARINA CRUDA | Q4: =VLOOKUP(P4,Maestro!E:F,2,0) -> Molienda de Crudo | R4: =VLOOKUP(P4,ORD!$A:$C,3,0) -> 3 | S4: =A4&J4&Q4 -> 7105330101CALIZATRIMolienda de Crudo | T4: =IFERROR(VLOOKUP(S4,Maestro!$A:$H,8,0),"Producción") -> Caliza | U4: Clinker
A5: 7105330101 | B5: CTO. MP CALIZAS NAL | D5: =Datos!$H$263*Datos!$H$167*(1+Datos!$H$212) -> 109733.16 | E5: T | F5: M | G5: 1405330101 | H5: INV. CALIZAS NAL | I5: EC01 | J5: MEZCPREHO | K5: 700000 | L5: 1 | M5: MEZCLA PREHOMO | P5: =VLOOKUP(K5,Maestro!J:K,2,0) -> HARINA CRUDA | Q5: =VLOOKUP(P5,Maestro!E:F,2,0) -> Molienda de Crudo | R5: =VLOOKUP(P5,ORD!$A:$C,3,0) -> 3 | S5: =A5&J5&Q5 -> 7105330101MEZCPREHOMolienda de Crudo | T5: =IFERROR(VLOOKUP(S5,Maestro!$A:$H,8,0),"Producción") -> Prehomo | U5: Clinker
A6: 7999999995 | B6: TRASLADO DE COSTOS | D6: =-Datos!$H$263 -> -132000 | E6: T | F6: M | G6: 1410900101 | H6: INV. SEMIELABORADO | I6: EC01 | J6: HARINACRUD | K6: 700000 | L6: 1 | M6: HARINA CRUDA | P6: =VLOOKUP(K6,Maestro!J:K,2,0) -> HARINA CRUDA | Q6: =VLOOKUP(P6,Maestro!E:F,2,0) -> Molienda de Crudo | R6: =VLOOKUP(P6,ORD!$A:$C,3,0) -> 3 | S6: =A6&J6&Q6 -> 7999999995HARINACRUDMolienda de Crudo | T6: =IFERROR(VLOOKUP(S6,Maestro!$A:$H,8,0),"Producción") -> Producción | U6: Clinker
A7: 7355250320 | B7: RTOS VARIA IMPO | C7: =Datos!$H$112*D7 -> 22058455 | D7: =Datos!$H$263 -> 132000 | I7: EC01 | J7: CUERPOS MOLEDORES | K7: 700000 | L7: 1 | M7: HARINA CRUDA | P7: =VLOOKUP(K7,Maestro!J:K,2,0) -> HARINA CRUDA | Q7: =VLOOKUP(P7,Maestro!E:F,2,0) -> Molienda de Crudo | R7: =VLOOKUP(P7,ORD!$A:$C,3,0) -> 3 | S7: =A7&J7&Q7 -> 7355250320CUERPOS MOLEDORESMolienda de Crudo | T7: =IFERROR(VLOOKUP(S7,Maestro!$A:$H,8,0),"Producción") -> Cuerpos Moledores | U7: Clinker
A8: 7355250321 | B8: RTOS VARIA IMPO | C8: =Datos!$H$114*D8 -> 15824544 | D8: =Datos!$H$263 -> 132000 | I8: EC01 | J8: LAMINAS | K8: 700000 | L8: 1 | M8: HARINA CRUDA | P8: =VLOOKUP(K8,Maestro!J:K,2,0) -> HARINA CRUDA | Q8: =VLOOKUP(P8,Maestro!E:F,2,0) -> Molienda de Crudo | R8: =VLOOKUP(P8,ORD!$A:$C,3,0) -> 3 | S8: =A8&J8&Q8 -> 7355250321LAMINASMolienda de Crudo | T8: =IFERROR(VLOOKUP(S8,Maestro!$A:$H,8,0),"Producción") -> Láminas | U8: Clinker
A9: 7355250322 | B9: RTOS VARIA IMPO | C9: =Datos!$H$118*D9 -> 65828938 | D9: =Datos!$H$263 -> 132000 | I9: EC01 | J9: ANILLOS, TAPAS Y SEPARADORES | K9: 700000 | L9: 1 | M9: HARINA CRUDA | P9: =VLOOKUP(K9,Maestro!J:K,2,0) -> HARINA CRUDA | Q9: =VLOOKUP(P9,Maestro!E:F,2,0) -> Molienda de Crudo | R9: =VLOOKUP(P9,ORD!$A:$C,3,0) -> 3 | S9: =A9&J9&Q9 -> 7355250322ANILLOS, TAPAS Y SEPARADORESMolienda de Crudo | T9: =IFERROR(VLOOKUP(S9,Maestro!$A:$H,8,0),"Producción") -> Anillos, Tapas y Separadores | U9: Clinker
A10: 7105040101 | B10: MP CORRECT HIERO NAL | C10: =Datos!$I$48*D10+Datos!$I$90*Base!D10 -> 8.9005767e+08 | D10: =Datos!$I$263*Datos!$I$169*(1+Datos!$I$213) -> 2958.9828 | E10: T | F10: M | G10: 1405040101 | H10: IN CORRECT HIERO NAL | I10: EC01 | J10: CORRHIERR | K10: 700000 | L10: 2 | M10: CORRECTOR DE HIERRO | P10: =VLOOKUP(K10,Maestro!J:K,2,0) -> HARINA CRUDA | Q10: =VLOOKUP(P10,Maestro!E:F,2,0) -> Molienda de Crudo | R10: =VLOOKUP(P10,ORD!$A:$C,3,0) -> 3 | S10: =A10&J10&Q10 -> 7105040101CORRHIERRMolienda de Crudo | T10: =IFERROR(VLOOKUP(S10,Maestro!$A:$H,8,0),"Producción") -> Mineral de Hierro | U10: Clinker
A11: 7105040101 | B11: MP CORRECT HIERO NAL | C11: =Datos!$I$49*D11+Datos!$I$90*D11 -> 85970928 | D11: =Datos!$I$263*Datos!$I$170*(1+Datos!$I$214) -> 504.60942 | E11: T | F11: M | G11: 1405040101 | H11: IN CORRECT HIERO NAL | I11: EC01 | J11: CALAMINA1 | K11: 700000 | L11: 2 | M11: CALAMINA | P11: =VLOOKUP(K11,Maestro!J:K,2,0) -> HARINA CRUDA | Q11: =VLOOKUP(P11,Maestro!E:F,2,0) -> Molienda de Crudo | R11: =VLOOKUP(P11,ORD!$A:$C,3,0) -> 3 | S11: =A11&J11&Q11 -> 7105040101CALAMINA1Molienda de Crudo | T11: =IFERROR(VLOOKUP(S11,Maestro!$A:$H,8,0),"Producción") -> Mineral de Hierro | U11: Clinker
A12: 7105330101 | B12: CTO. MP CALIZAS NAL | D12: =Datos!$I$263*Datos!$I$168*(1+Datos!$I$210) -> 24359.432 | E12: T | F12: M | G12: 1405330101 | H12: INV. CALIZAS NAL | I12: EC01 | J12: CALIZATRI | K12: 700000 | L12: 2 | M12: CALIZA TRITURADA | P12: =VLOOKUP(K12,Maestro!J:K,2,0) -> HARINA CRUDA | Q12: =VLOOKUP(P12,Maestro!E:F,2,0) -> Molienda de Crudo | R12: =VLOOKUP(P12,ORD!$A:$C,3,0) -> 3 | S12: =A12&J12&Q12 -> 7105330101CALIZATRIMolienda de Crudo | T12: =IFERROR(VLOOKUP(S12,Maestro!$A:$H,8,0),"Producción") -> Caliza | U12: Clinker
A13: 7105330101 | B13: CTO. MP CALIZAS NAL | D13: =Datos!$I$263*Datos!$I$167*(1+Datos!$I$212) -> 110772.3 | E13: T | F13: M | G13: 1405330101 | H13: INV. CALIZAS NAL | I13: EC01 | J13: MEZCPREHO | K13: 700000 | L13: 2 | M13: MEZCLA PREHOMO | P13: =VLOOKUP(K13,Maestro!J:K,2,0) -> HARINA CRUDA | Q13: =VLOOKUP(P13,Maestro!E:F,2,0) -> Molienda de Crudo | R13: =VLOOKUP(P13,ORD!$A:$C,3,0) -> 3 | S13: =A13&J13&Q13 -> 7105330101MEZCPREHOMolienda de Crudo | T13: =IFERROR(VLOOKUP(S13,Maestro!$A:$H,8,0),"Producción") -> Prehomo | U13: Clinker
A14: 7999999995 | B14: TRASLADO DE COSTOS | D14: =-Datos!$I$263 -> -133250 | E14: T | F14: M | G14: 1410900101 | H14: INV. SEMIELABORADO | I14: EC01 | J14: HARINACRUD | K14: 700000 | L14: 2 | M14: HARINA CRUDA | P14: =VLOOKUP(K14,Maestro!J:K,2,0) -> HARINA CRUDA | Q14: =VLOOKUP(P14,Maestro!E:F,2,0) -> Molienda de Crudo | R14: =VLOOKUP(P14,ORD!$A:$C,3,0) -> 3 | S14: =A14&J14&Q14 -> 7999999995HARINACRUDMolienda de Crudo | T14: =IFERROR(VLOOKUP(S14,Maestro!$A:$H,8,0),"Producción") -> Producción | U14: Clinker
A15: 7355250320 | B15: RTOS VARIA IMPO | C15: =Datos!$I$112*D15 -> 22267342 | D15: =Datos!$I$263 -> 133250 | I15: EC01 | J15: CUERPOS MOLEDORES | K15: 700000 | L15: 2 | M15: HARINA CRUDA | P15: =VLOOKUP(K15,Maestro!J:K,2,0) -> HARINA CRUDA | Q15: =VLOOKUP(P15,Maestro!E:F,2,0) -> Molienda de Crudo | R15: =VLOOKUP(P15,ORD!$A:$C,3,0) -> 3 | S15: =A15&J15&Q15 -> 7355250320CUERPOS MOLEDORESMolienda de Crudo | T15: =IFERROR(VLOOKUP(S15,Maestro!$A:$H,8,0),"Producción") -> Cuerpos Moledores | U15: Clinker
A16: 7355250321 | B16: RTOS VARIA IMPO | C16: =Datos!$I$114*D16 -> 15974398 | D16: =Datos!$I$263 -> 133250 | I16: EC01 | J16: LAMINAS | K16: 700000 | L16: 2 | M16: HARINA CRUDA | P16: =VLOOKUP(K16,Maestro!J:K,2,0) -> HARINA CRUDA | Q16: =VLOOKUP(P16,Maestro!E:F,2,0) -> Molienda de Crudo | R16: =VLOOKUP(P16,ORD!$A:$C,3,0) -> 3 | S16: =A16&J16&Q16 -> 7355250321LAMINASMolienda de Crudo | T16: =IFERROR(VLOOKUP(S16,Maestro!$A:$H,8,0),"Producción") -> Láminas | U16: Clinker
A17: 7355250322 | B17: RTOS VARIA IMPO | C17: =Datos!$I$118*D17 -> 66452318 | D17: =Datos!$I$263 -> 133250 | I17: EC01 | J17: ANILLOS, TAPAS Y SEPARADORES | K17: 700000 | L17: 2 | M17: HARINA CRUDA | P17: =VLOOKUP(K17,Maestro!J:K,2,0) -> HARINA CRUDA | Q17: =VLOOKUP(P17,Maestro!E:F,2,0) -> Molienda de Crudo | R17: =VLOOKUP(P17,ORD!$A:$C,3,0) -> 3 | S17: =A17&J17&Q17 -> 7355250322ANILLOS, TAPAS Y SEPARADORESMolienda de Crudo | T17: =IFERROR(VLOOKUP(S17,Maestro!$A:$H,8,0),"Producción") -> Anillos, Tapas y Separadores | U17: Clinker
A18: 7105040101 | B18: MP CORRECT HIERO NAL | C18: =Datos!$I$48*D18+Datos!$J$90*Base!D18 -> 6.3492394e+08 | D18: =Datos!$J$263*Datos!$J$169*(1+Datos!$J$213) -> 2109.5938 | E18: T | F18: M | G18: 1405040101 | H18: IN CORRECT HIERO NAL | I18: EC01 | J18: CORRHIERR | K18: 700000 | L18: 3 | M18: CORRECTOR DE HIERRO | P18: =VLOOKUP(K18,Maestro!J:K,2,0) -> HARINA CRUDA | Q18: =VLOOKUP(P18,Maestro!E:F,2,0) -> Molienda de Crudo | R18: =VLOOKUP(P18,ORD!$A:$C,3,0) -> 3 | S18: =A18&J18&Q18 -> 7105040101CORRHIERRMolienda de Crudo | T18: =IFERROR(VLOOKUP(S18,Maestro!$A:$H,8,0),"Producción") -> Mineral de Hierro | U18: Clinker
A19: 7105040101 | B19: MP CORRECT HIERO NAL | C19: =Datos!$J$49*D19+Datos!$J$90*D19 -> 61354199 | D19: =Datos!$J$263*Datos!$J$170*(1+Datos!$J$214) -> 359.75906 | E19: T | F19: M | G19: 1405040101 | H19: IN CORRECT HIERO NAL | I19: EC01 | J19: CALAMINA1 | K19: 700000 | L19: 3 | M19: CALAMINA | P19: =VLOOKUP(K19,Maestro!J:K,2,0) -> HARINA CRUDA | Q19: =VLOOKUP(P19,Maestro!E:F,2,0) -> Molienda de Crudo | R19: =VLOOKUP(P19,ORD!$A:$C,3,0) -> 3 | S19: =A19&J19&Q19 -> 7105040101CALAMINA1Molienda de Crudo | T19: =IFERROR(VLOOKUP(S19,Maestro!$A:$H,8,0),"Producción") -> Mineral de Hierro | U19: Clinker
A20: 7105330101 | B20: CTO. MP CALIZAS NAL | D20: =Datos!$J$263*Datos!$J$168*(1+Datos!$J$210) -> 17366.95 | E20: T | F20: M | G20: 1405330101 | H20: INV. CALIZAS NAL | I20: EC01 | J20: CALIZATRI | K20: 700000 | L20: 3 | M20: CALIZA TRITURADA | P20: =VLOOKUP(K20,Maestro!J:K,2,0) -> HARINA CRUDA | Q20: =VLOOKUP(P20,Maestro!E:F,2,0) -> Molienda de Crudo | R20: =VLOOKUP(P20,ORD!$A:$C,3,0) -> 3 | S20: =A20&J20&Q20 -> 7105330101CALIZATRIMolienda de Crudo | T20: =IFERROR(VLOOKUP(S20,Maestro!$A:$H,8,0),"Producción") -> Caliza | U20: Clinker
A21: 7105330101 | B21: CTO. MP CALIZAS NAL | D21: =Datos!$J$263*Datos!$J$167*(1+Datos!$J$212) -> 78974.624 | E21: T | F21: M | G21: 1405330101 | H21: INV. CALIZAS NAL | I21: EC01 | J21: MEZCPREHO | K21: 700000 | L21: 3 | M21: MEZCLA PREHOMO | P21: =VLOOKUP(K21,Maestro!J:K,2,0) -> HARINA CRUDA | Q21: =VLOOKUP(P21,Maestro!E:F,2,0) -> Molienda de Crudo | R21: =VLOOKUP(P21,ORD!$A:$C,3,0) -> 3 | S21: =A21&J21&Q21 -> 7105330101MEZCPREHOMolienda de Crudo | T21: =IFERROR(VLOOKUP(S21,Maestro!$A:$H,8,0),"Producción") -> Prehomo | U21: Clinker
A22: 7999999995 | B22: TRASLADO DE COSTOS | D22: =-Datos!$J$263 -> -95000 | E22: T | F22: M | G22: 1410900101 | H22: INV. SEMIELABORADO | I22: EC01 | J22: HARINACRUD | K22: 700000 | L22: 3 | M22: HARINA CRUDA | P22: =VLOOKUP(K22,Maestro!J:K,2,0) -> HARINA CRUDA | Q22: =VLOOKUP(P22,Maestro!E:F,2,0) -> Molienda de Crudo | R22: =VLOOKUP(P22,ORD!$A:$C,3,0) -> 3 | S22: =A22&J22&Q22 -> 7999999995HARINACRUDMolienda de Crudo | T22: =IFERROR(VLOOKUP(S22,Maestro!$A:$H,8,0),"Producción") -> Producción | U22: Clinker
A23: 7355250320 | B23: RTOS VARIA IMPO | C23: =Datos!$J$112*D23 -> 15875404 | D23: =Datos!$J$263 -> 95000 | I23: EC01 | J23: CUERPOS MOLEDORES | K23: 700000 | L23: 3 | M23: HARINA CRUDA | P23: =VLOOKUP(K23,Maestro!J:K,2,0) -> HARINA CRUDA | Q23: =VLOOKUP(P23,Maestro!E:F,2,0) -> Molienda de Crudo | R23: =VLOOKUP(P23,ORD!$A:$C,3,0) -> 3 | S23: =A23&J23&Q23 -> 7355250320CUERPOS MOLEDORESMolienda de Crudo | T23: =IFERROR(VLOOKUP(S23,Maestro!$A:$H,8,0),"Producción") -> Cuerpos Moledores | U23: Clinker
A24: 7355250321 | B24: RTOS VARIA IMPO | C24: =Datos!$J$114*D24 -> 11388876 | D24: =Datos!$J$263 -> 95000 | I24: EC01 | J24: LAMINAS | K24: 700000 | L24: 3 | M24: HARINA CRUDA | P24: =VLOOKUP(K24,Maestro!J:K,2,0) -> HARINA CRUDA | Q24: =VLOOKUP(P24,Maestro!E:F,2,0) -> Molienda de Crudo | R24: =VLOOKUP(P24,ORD!$A:$C,3,0) -> 3 | S24: =A24&J24&Q24 -> 7355250321LAMINASMolienda de Crudo | T24: =IFERROR(VLOOKUP(S24,Maestro!$A:$H,8,0),"Producción") -> Láminas | U24: Clinker
A25: 7355250322 | B25: RTOS VARIA IMPO | C25: =Datos!$J$118*D25 -> 47376887 | D25: =Datos!$J$263 -> 95000 | I25: EC01 | J25: ANILLOS, TAPAS Y SEPARADORES | K25: 700000 | L25: 3 | M25: HARINA CRUDA | P25: =VLOOKUP(K25,Maestro!J:K,2,0) -> HARINA CRUDA | Q25: =VLOOKUP(P25,Maestro!E:F,2,0) -> Molienda de Crudo | R25: =VLOOKUP(P25,ORD!$A:$C,3,0) -> 3 | S25: =A25&J25&Q25 -> 7355250322ANILLOS, TAPAS Y SEPARADORESMolienda de Crudo | T25: =IFERROR(VLOOKUP(S25,Maestro!$A:$H,8,0),"Producción") -> Anillos, Tapas y Separadores | U25: Clinker
A26: 7105040101 | B26: MP CORRECT HIERO NAL | C26: =Datos!$I$48*D26+Datos!$K$90*Base!D26 -> 6.5164811e+08 | D26: =Datos!$K$263*Datos!$K$169*(1+Datos!$K$213) -> 2165.1094 | E26: T | F26: M | G26: 1405040101 | H26: IN CORRECT HIERO NAL | I26: EC01 | J26: CORRHIERR | K26: 700000 | L26: 4 | M26: CORRECTOR DE HIERRO | P26: =VLOOKUP(K26,Maestro!J:K,2,0) -> HARINA CRUDA | Q26: =VLOOKUP(P26,Maestro!E:F,2,0) -> Molienda de Crudo | R26: =VLOOKUP(P26,ORD!$A:$C,3,0) -> 3 | S26: =A26&J26&Q26 -> 7105040101CORRHIERRMolienda de Crudo | T26: =IFERROR(VLOOKUP(S26,Maestro!$A:$H,8,0),"Producción") -> Mineral de Hierro | U26: Clinker
A27: 7105040101 | B27: MP CORRECT HIERO NAL | C27: =Datos!$K$49*D27+Datos!$K$90*D27 -> 62971452 | D27: =Datos!$K$263*Datos!$K$170*(1+Datos!$K$214) -> 369.22641 | E27: T | F27: M | G27: 1405040101 | H27: IN CORRECT HIERO NAL | I27: EC01 | J27: CALAMINA1 | K27: 700000 | L27: 4 | M27: CALAMINA | P27: =VLOOKUP(K27,Maestro!J:K,2,0) -> HARINA CRUDA | Q27: =VLOOKUP(P27,Maestro!E:F,2,0) -> Molienda de Crudo | R27: =VLOOKUP(P27,ORD!$A:$C,3,0) -> 3 | S27: =A27&J27&Q27 -> 7105040101CALAMINA1Molienda de Crudo | T27: =IFERROR(VLOOKUP(S27,Maestro!$A:$H,8,0),"Producción") -> Mineral de Hierro | U27: Clinker
A28: 7105330101 | B28: CTO. MP CALIZAS NAL | D28: =Datos!$K$263*Datos!$K$168*(1+Datos!$K$210) -> 17823.975 | E28: T | F28: M | G28: 1405330101 | H28: INV. CALIZAS NAL | I28: EC01 | J28: CALIZATRI | K28: 700000 | L28: 4 | M28: CALIZA TRITURADA | P28: =VLOOKUP(K28,Maestro!J:K,2,0) -> HARINA CRUDA | Q28: =VLOOKUP(P28,Maestro!E:F,2,0) -> Molienda de Crudo | R28: =VLOOKUP(P28,ORD!$A:$C,3,0) -> 3 | S28: =A28&J28&Q28 -> 7105330101CALIZATRIMolienda de Crudo | T28: =IFERROR(VLOOKUP(S28,Maestro!$A:$H,8,0),"Producción") -> Caliza | U28: Clinker
A29: 7105330101 | B29: CTO. MP CALIZAS NAL | D29: =Datos!$K$263*Datos!$K$167*(1+Datos!$K$212) -> 81052.904 | E29: T | F29: M | G29: 1405330101 | H29: INV. CALIZAS NAL | I29: EC01 | J29: MEZCPREHO | K29: 700000 | L29: 4 | M29: MEZCLA PREHOMO | P29: =VLOOKUP(K29,Maestro!J:K,2,0) -> HARINA CRUDA | Q29: =VLOOKUP(P29,Maestro!E:F,2,0) -> Molienda de Crudo | R29: =VLOOKUP(P29,ORD!$A:$C,3,0) -> 3 | S29: =A29&J29&Q29 -> 7105330101MEZCPREHOMolienda de Crudo | T29: =IFERROR(VLOOKUP(S29,Maestro!$A:$H,8,0),"Producción") -> Prehomo | U29: Clinker
A30: 7999999995 | B30: TRASLADO DE COSTOS | D30: =-Datos!$K$263 -> -97500 | E30: T | F30: M | G30: 1410900101 | H30: INV. SEMIELABORADO | I30: EC01 | J30: HARINACRUD | K30: 700000 | L30: 4 | M30: HARINA CRUDA | P30: =VLOOKUP(K30,Maestro!J:K,2,0) -> HARINA CRUDA | Q30: =VLOOKUP(P30,Maestro!E:F,2,0) -> Molienda de Crudo | R30: =VLOOKUP(P30,ORD!$A:$C,3,0) -> 3 | S30: =A30&J30&Q30 -> 7999999995HARINACRUDMolienda de Crudo | T30: =IFERROR(VLOOKUP(S30,Maestro!$A:$H,8,0),"Producción") -> Producción | U30: Clinker
A31: 7355250320 | B31: RTOS VARIA IMPO | C31: =Datos!$K$112*D31 -> 16293177 | D31: =Datos!$K$263 -> 97500 | I31: EC01 | J31: CUERPOS MOLEDORES | K31: 700000 | L31: 4 | M31: HARINA CRUDA | P31: =VLOOKUP(K31,Maestro!J:K,2,0) -> HARINA CRUDA | Q31: =VLOOKUP(P31,Maestro!E:F,2,0) -> Molienda de Crudo | R31: =VLOOKUP(P31,ORD!$A:$C,3,0) -> 3 | S31: =A31&J31&Q31 -> 7355250320CUERPOS MOLEDORESMolienda de Crudo | T31: =IFERROR(VLOOKUP(S31,Maestro!$A:$H,8,0),"Producción") -> Cuerpos Moledores | U31: Clinker
A32: 7355250321 | B32: RTOS VARIA IMPO | C32: =Datos!$K$114*D32 -> 11688584 | D32: =Datos!$K$263 -> 97500 | I32: EC01 | J32: LAMINAS | K32: 700000 | L32: 4 | M32: HARINA CRUDA | P32: =VLOOKUP(K32,Maestro!J:K,2,0) -> HARINA CRUDA | Q32: =VLOOKUP(P32,Maestro!E:F,2,0) -> Molienda de Crudo | R32: =VLOOKUP(P32,ORD!$A:$C,3,0) -> 3 | S32: =A32&J32&Q32 -> 7355250321LAMINASMolienda de Crudo | T32: =IFERROR(VLOOKUP(S32,Maestro!$A:$H,8,0),"Producción") -> Láminas | U32: Clinker
A33: 7355250322 | B33: RTOS VARIA IMPO | C33: =Datos!$K$118*D33 -> 48623647 | D33: =Datos!$K$263 -> 97500 | I33: EC01 | J33: ANILLOS, TAPAS Y SEPARADORES | K33: 700000 | L33: 4 | M33: HARINA CRUDA | P33: =VLOOKUP(K33,Maestro!J:K,2,0) -> HARINA CRUDA | Q33: =VLOOKUP(P33,Maestro!E:F,2,0) -> Molienda de Crudo | R33: =VLOOKUP(P33,ORD!$A:$C,3,0) -> 3 | S33: =A33&J33&Q33 -> 7355250322ANILLOS, TAPAS Y SEPARADORESMolienda de Crudo | T33: =IFERROR(VLOOKUP(S33,Maestro!$A:$H,8,0),"Producción") -> Anillos, Tapas y Separadores | U33: Clinker
A34: 7105040101 | B34: MP CORRECT HIERO NAL | C34: =Datos!$I$48*D34+Datos!$L$90*Base!D34 -> 9.8509076e+08 | D34: =Datos!$L$263*Datos!$L$169*(1+Datos!$L$213) -> 3275.4219 | E34: T | F34: M | G34: 1405040101 | H34: IN CORRECT HIERO NAL | I34: EC01 | J34: CORRHIERR | K34: 700000 | L34: 5 | M34: CORRECTOR DE HIERRO | P34: =VLOOKUP(K34,Maestro!J:K,2,0) -> HARINA CRUDA | Q34: =VLOOKUP(P34,Maestro!E:F,2,0) -> Molienda de Crudo | R34: =VLOOKUP(P34,ORD!$A:$C,3,0) -> 3 | S34: =A34&J34&Q34 -> 7105040101CORRHIERRMolienda de Crudo | T34: =IFERROR(VLOOKUP(S34,Maestro!$A:$H,8,0),"Producción") -> Mineral de Hierro | U34: Clinker
A35: 7105040101 | B35: MP CORRECT HIERO NAL | C35: =Datos!$L$49*D35+Datos!$L$90*D35 -> 95139013 | D35: =Datos!$L$263*Datos!$L$170*(1+Datos!$L$214) -> 558.57328 | E35: T | F35: M | G35: 1405040101 | H35: IN CORRECT HIERO NAL | I35: EC01 | J35: CALAMINA1 | K35: 700000 | L35: 5 | M35: CALAMINA | P35: =VLOOKUP(K35,Maestro!J:K,2,0) -> HARINA CRUDA | Q35: =VLOOKUP(P35,Maestro!E:F,2,0) -> Molienda de Crudo | R35: =VLOOKUP(P35,ORD!$A:$C,3,0) -> 3 | S35: =A35&J35&Q35 -> 7105040101CALAMINA1Molienda de Crudo | T35: =IFERROR(VLOOKUP(S35,Maestro!$A:$H,8,0),"Producción") -> Mineral de Hierro | U35: Clinker
A36: 7105330101 | B36: CTO. MP CALIZAS NAL | D36: =Datos!$L$263*Datos!$L$168*(1+Datos!$L$210) -> 26964.475 | E36: T | F36: M | G36: 1405330101 | H36: INV. CALIZAS NAL | I36: EC01 | J36: CALIZATRI | K36: 700000 | L36: 5 | M36: CALIZA TRITURADA | P36: =VLOOKUP(K36,Maestro!J:K,2,0) -> HARINA CRUDA | Q36: =VLOOKUP(P36,Maestro!E:F,2,0) -> Molienda de Crudo | R36: =VLOOKUP(P36,ORD!$A:$C,3,0) -> 3 | S36: =A36&J36&Q36 -> 7105330101CALIZATRIMolienda de Crudo | T36: =IFERROR(VLOOKUP(S36,Maestro!$A:$H,8,0),"Producción") -> Caliza | U36: Clinker
A37: 7105330101 | B37: CTO. MP CALIZAS NAL | D37: =Datos!$L$263*Datos!$L$167*(1+Datos!$L$212) -> 122618.5 | E37: T | F37: M | G37: 1405330101 | H37: INV. CALIZAS NAL | I37: EC01 | J37: MEZCPREHO | K37: 700000 | L37: 5 | M37: MEZCLA PREHOMO | P37: =VLOOKUP(K37,Maestro!J:K,2,0) -> HARINA CRUDA | Q37: =VLOOKUP(P37,Maestro!E:F,2,0) -> Molienda de Crudo | R37: =VLOOKUP(P37,ORD!$A:$C,3,0) -> 3 | S37: =A37&J37&Q37 -> 7105330101MEZCPREHOMolienda de Crudo | T37: =IFERROR(VLOOKUP(S37,Maestro!$A:$H,8,0),"Producción") -> Prehomo | U37: Clinker
A38: 7999999995 | B38: TRASLADO DE COSTOS | D38: =-Datos!$L$263 -> -147500 | E38: T | F38: M | G38: 1410900101 | H38: INV. SEMIELABORADO | I38: EC01 | J38: HARINACRUD | K38: 700000 | L38: 5 | M38: HARINA CRUDA | P38: =VLOOKUP(K38,Maestro!J:K,2,0) -> HARINA CRUDA | Q38: =VLOOKUP(P38,Maestro!E:F,2,0) -> Molienda de Crudo | R38: =VLOOKUP(P38,ORD!$A:$C,3,0) -> 3 | S38: =A38&J38&Q38 -> 7999999995HARINACRUDMolienda de Crudo | T38: =IFERROR(VLOOKUP(S38,Maestro!$A:$H,8,0),"Producción") -> Producción | U38: Clinker
A39: 7355250320 | B39: RTOS VARIA IMPO | C39: =Datos!$L$112*D39 -> 24648653 | D39: =Datos!$L$263 -> 147500 | I39: EC01 | J39: CUERPOS MOLEDORES | K39: 700000 | L39: 5 | M39: HARINA CRUDA | P39: =VLOOKUP(K39,Maestro!J:K,2,0) -> HARINA CRUDA | Q39: =VLOOKUP(P39,Maestro!E:F,2,0) -> Molienda de Crudo | R39: =VLOOKUP(P39,ORD!$A:$C,3,0) -> 3 | S39: =A39&J39&Q39 -> 7355250320CUERPOS MOLEDORESMolienda de Crudo | T39: =IFERROR(VLOOKUP(S39,Maestro!$A:$H,8,0),"Producción") -> Cuerpos Moledores | U39: Clinker
A40: 7355250321 | B40: RTOS VARIA IMPO | C40: =Datos!$L$114*D40 -> 17682729 | D40: =Datos!$L$263 -> 147500 | I40: EC01 | J40: LAMINAS | K40: 700000 | L40: 5 | M40: HARINA CRUDA | P40: =VLOOKUP(K40,Maestro!J:K,2,0) -> HARINA CRUDA | Q40: =VLOOKUP(P40,Maestro!E:F,2,0) -> Molienda de Crudo | R40: =VLOOKUP(P40,ORD!$A:$C,3,0) -> 3 | S40: =A40&J40&Q40 -> 7355250321LAMINASMolienda de Crudo | T40: =IFERROR(VLOOKUP(S40,Maestro!$A:$H,8,0),"Producción") -> Láminas | U40: Clinker
A41: 7355250322 | B41: RTOS VARIA IMPO | C41: =Datos!$L$118*D41 -> 73558851 | D41: =Datos!$L$263 -> 147500 | I41: EC01 | J41: ANILLOS, TAPAS Y SEPARADORES | K41: 700000 | L41: 5 | M41: HARINA CRUDA | P41: =VLOOKUP(K41,Maestro!J:K,2,0) -> HARINA CRUDA | Q41: =VLOOKUP(P41,Maestro!E:F,2,0) -> Molienda de Crudo | R41: =VLOOKUP(P41,ORD!$A:$C,3,0) -> 3 | S41: =A41&J41&Q41 -> 7355250322ANILLOS, TAPAS Y SEPARADORESMolienda de Crudo | T41: =IFERROR(VLOOKUP(S41,Maestro!$A:$H,8,0),"Producción") -> Anillos, Tapas y Separadores | U41: Clinker
A42: 7105040101 | B42: MP CORRECT HIERO NAL | C42: =Datos!$I$48*D42+Datos!$M$90*Base!D42 -> 4.3482593e+08 | D42: =Datos!$M$263*Datos!$M$169*(1+Datos!$M$213) -> 1443.4062 | E42: T | F42: M | G42: 1405040101 | H42: IN CORRECT HIERO NAL | I42: EC01 | J42: CORRHIERR | K42: 700000 | L42: 6 | M42: CORRECTOR DE HIERRO | P42: =VLOOKUP(K42,Maestro!J:K,2,0) -> HARINA CRUDA | Q42: =VLOOKUP(P42,Maestro!E:F,2,0) -> Molienda de Crudo | R42: =VLOOKUP(P42,ORD!$A:$C,3,0) -> 3 | S42: =A42&J42&Q42 -> 7105040101CORRHIERRMolienda de Crudo | T42: =IFERROR(VLOOKUP(S42,Maestro!$A:$H,8,0),"Producción") -> Mineral de Hierro | U42: Clinker
A43: 7105040101 | B43: MP CORRECT HIERO NAL | C43: =Datos!$M$49*D43+Datos!$M$90*D43 -> 42048133 | D43: =Datos!$M$263*Datos!$M$170*(1+Datos!$M$214) -> 246.15094 | E43: T | F43: M | G43: 1405040101 | H43: IN CORRECT HIERO NAL | I43: EC01 | J43: CALAMINA1 | K43: 700000 | L43: 6 | M43: CALAMINA | P43: =VLOOKUP(K43,Maestro!J:K,2,0) -> HARINA CRUDA | Q43: =VLOOKUP(P43,Maestro!E:F,2,0) -> Molienda de Crudo | R43: =VLOOKUP(P43,ORD!$A:$C,3,0) -> 3 | S43: =A43&J43&Q43 -> 7105040101CALAMINA1Molienda de Crudo | T43: =IFERROR(VLOOKUP(S43,Maestro!$A:$H,8,0),"Producción") -> Mineral de Hierro | U43: Clinker
A44: 7105330101 | B44: CTO. MP CALIZAS NAL | D44: =Datos!$M$263*Datos!$M$168*(1+Datos!$M$210) -> 11882.65 | E44: T | F44: M | G44: 1405330101 | H44: INV. CALIZAS NAL | I44: EC01 | J44: CALIZATRI | K44: 700000 | L44: 6 | M44: CALIZA TRITURADA | P44: =VLOOKUP(K44,Maestro!J:K,2,0) -> HARINA CRUDA | Q44: =VLOOKUP(P44,Maestro!E:F,2,0) -> Molienda de Crudo | R44: =VLOOKUP(P44,ORD!$A:$C,3,0) -> 3 | S44: =A44&J44&Q44 -> 7105330101CALIZATRIMolienda de Crudo | T44: =IFERROR(VLOOKUP(S44,Maestro!$A:$H,8,0),"Producción") -> Caliza | U44: Clinker
A45: 7105330101 | B45: CTO. MP CALIZAS NAL | D45: =Datos!$M$263*Datos!$M$167*(1+Datos!$M$212) -> 54035.269 | E45: T | F45: M | G45: 1405330101 | H45: INV. CALIZAS NAL | I45: EC01 | J45: MEZCPREHO | K45: 700000 | L45: 6 | M45: MEZCLA PREHOMO | P45: =VLOOKUP(K45,Maestro!J:K,2,0) -> HARINA CRUDA | Q45: =VLOOKUP(P45,Maestro!E:F,2,0) -> Molienda de Crudo | R45: =VLOOKUP(P45,ORD!$A:$C,3,0) -> 3 | S45: =A45&J45&Q45 -> 7105330101MEZCPREHOMolienda de Crudo | T45: =IFERROR(VLOOKUP(S45,Maestro!$A:$H,8,0),"Producción") -> Prehomo | U45: Clinker
A46: 7999999995 | B46: TRASLADO DE COSTOS | D46: =-Datos!$M$263 -> -65000 | E46: T | F46: M | G46: 1410900101 | H46: INV. SEMIELABORADO | I46: EC01 | J46: HARINACRUD | K46: 700000 | L46: 6 | M46: HARINA CRUDA | P46: =VLOOKUP(K46,Maestro!J:K,2,0) -> HARINA CRUDA | Q46: =VLOOKUP(P46,Maestro!E:F,2,0) -> Molienda de Crudo | R46: =VLOOKUP(P46,ORD!$A:$C,3,0) -> 3 | S46: =A46&J46&Q46 -> 7999999995HARINACRUDMolienda de Crudo | T46: =IFERROR(VLOOKUP(S46,Maestro!$A:$H,8,0),"Producción") -> Producción | U46: Clinker
A47: 7355250320 | B47: RTOS VARIA IMPO | C47: =Datos!$M$112*D47 -> 10862118 | D47: =Datos!$M$263 -> 65000 | I47: EC01 | J47: CUERPOS MOLEDORES | K47: 700000 | L47: 6 | M47: HARINA CRUDA | P47: =VLOOKUP(K47,Maestro!J:K,2,0) -> HARINA CRUDA | Q47: =VLOOKUP(P47,Maestro!E:F,2,0) -> Molienda de Crudo | R47: =VLOOKUP(P47,ORD!$A:$C,3,0) -> 3 | S47: =A47&J47&Q47 -> 7355250320CUERPOS MOLEDORESMolienda de Crudo | T47: =IFERROR(VLOOKUP(S47,Maestro!$A:$H,8,0),"Producción") -> Cuerpos Moledores | U47: Clinker
A48: 7355250321 | B48: RTOS VARIA IMPO | C48: =Datos!$M$114*D48 -> 7792389.1 | D48: =Datos!$M$263 -> 65000 | I48: EC01 | J48: LAMINAS | K48: 700000 | L48: 6 | M48: HARINA CRUDA | P48: =VLOOKUP(K48,Maestro!J:K,2,0) -> HARINA CRUDA | Q48: =VLOOKUP(P48,Maestro!E:F,2,0) -> Molienda de Crudo | R48: =VLOOKUP(P48,ORD!$A:$C,3,0) -> 3 | S48: =A48&J48&Q48 -> 7355250321LAMINASMolienda de Crudo | T48: =IFERROR(VLOOKUP(S48,Maestro!$A:$H,8,0),"Producción") -> Láminas | U48: Clinker
A49: 7355250322 | B49: RTOS VARIA IMPO | C49: =Datos!$M$118*D49 -> 32415765 | D49: =Datos!$M$263 -> 65000 | I49: EC01 | J49: ANILLOS, TAPAS Y SEPARADORES | K49: 700000 | L49: 6 | M49: HARINA CRUDA | P49: =VLOOKUP(K49,Maestro!J:K,2,0) -> HARINA CRUDA | Q49: =VLOOKUP(P49,Maestro!E:F,2,0) -> Molienda de Crudo | R49: =VLOOKUP(P49,ORD!$A:$C,3,0) -> 3 | S49: =A49&J49&Q49 -> 7355250322ANILLOS, TAPAS Y SEPARADORESMolienda de Crudo | T49: =IFERROR(VLOOKUP(S49,Maestro!$A:$H,8,0),"Producción") -> Anillos, Tapas y Separadores | U49: Clinker
A50: 7105040101 | B50: MP CORRECT HIERO NAL | C50: =Datos!$I$48*D50+Datos!$N$90*Base!D50 -> 8.18279e+08 | D50: =Datos!$N$263*Datos!$N$169*(1+Datos!$N$213) -> 2720.2656 | E50: T | F50: M | G50: 1405040101 | H50: IN CORRECT HIERO NAL | I50: EC01 | J50: CORRHIERR | K50: 700000 | L50: 7 | M50: CORRECTOR DE HIERRO | P50: =VLOOKUP(K50,Maestro!J:K,2,0) -> HARINA CRUDA | Q50: =VLOOKUP(P50,Maestro!E:F,2,0) -> Molienda de Crudo | R50: =VLOOKUP(P50,ORD!$A:$C,3,0) -> 3 | S50: =A50&J50&Q50 -> 7105040101CORRHIERRMolienda de Crudo | T50: =IFERROR(VLOOKUP(S50,Maestro!$A:$H,8,0),"Producción") -> Mineral de Hierro | U50: Clinker
A51: 7105040101 | B51: MP CORRECT HIERO NAL | C51: =Datos!$N$49*D51+Datos!$N$90*D51 -> 79039809 | D51: =Datos!$N$263*Datos!$N$170*(1+Datos!$N$214) -> 463.89984 | E51: T | F51: M | G51: 1405040101 | H51: IN CORRECT HIERO NAL | I51: EC01 | J51: CALAMINA1 | K51: 700000 | L51: 7 | M51: CALAMINA | P51: =VLOOKUP(K51,Maestro!J:K,2,0) -> HARINA CRUDA | Q51: =VLOOKUP(P51,Maestro!E:F,2,0) -> Molienda de Crudo | R51: =VLOOKUP(P51,ORD!$A:$C,3,0) -> 3 | S51: =A51&J51&Q51 -> 7105040101CALAMINA1Molienda de Crudo | T51: =IFERROR(VLOOKUP(S51,Maestro!$A:$H,8,0),"Producción") -> Mineral de Hierro | U51: Clinker
A52: 7105330101 | B52: CTO. MP CALIZAS NAL | D52: =Datos!$N$263*Datos!$N$168*(1+Datos!$N$210) -> 22394.225 | E52: T | F52: M | G52: 1405330101 | H52: INV. CALIZAS NAL | I52: EC01 | J52: CALIZATRI | K52: 700000 | L52: 7 | M52: CALIZA TRITURADA | P52: =VLOOKUP(K52,Maestro!J:K,2,0) -> HARINA CRUDA | Q52: =VLOOKUP(P52,Maestro!E:F,2,0) -> Molienda de Crudo | R52: =VLOOKUP(P52,ORD!$A:$C,3,0) -> 3 | S52: =A52&J52&Q52 -> 7105330101CALIZATRIMolienda de Crudo | T52: =IFERROR(VLOOKUP(S52,Maestro!$A:$H,8,0),"Producción") -> Caliza | U52: Clinker
A53: 7105330101 | B53: CTO. MP CALIZAS NAL | D53: =Datos!$N$263*Datos!$N$167*(1+Datos!$N$212) -> 101835.7 | E53: T | F53: M | G53: 1405330101 | H53: INV. CALIZAS NAL | I53: EC01 | J53: MEZCPREHO | K53: 700000 | L53: 7 | M53: MEZCLA PREHOMO | P53: =VLOOKUP(K53,Maestro!J:K,2,0) -> HARINA CRUDA | Q53: =VLOOKUP(P53,Maestro!E:F,2,0) -> Molienda de Crudo | R53: =VLOOKUP(P53,ORD!$A:$C,3,0) -> 3 | S53: =A53&J53&Q53 -> 7105330101MEZCPREHOMolienda de Crudo | T53: =IFERROR(VLOOKUP(S53,Maestro!$A:$H,8,0),"Producción") -> Prehomo | U53: Clinker
A54: 7999999995 | B54: TRASLADO DE COSTOS | D54: =-Datos!$N$263 -> -122500 | E54: T | F54: M | G54: 1410900101 | H54: INV. SEMIELABORADO | I54: EC01 | J54: HARINACRUD | K54: 700000 | L54: 7 | M54: HARINA CRUDA | P54: =VLOOKUP(K54,Maestro!J:K,2,0) -> HARINA CRUDA | Q54: =VLOOKUP(P54,Maestro!E:F,2,0) -> Molienda de Crudo | R54: =VLOOKUP(P54,ORD!$A:$C,3,0) -> 3 | S54: =A54&J54&Q54 -> 7999999995HARINACRUDMolienda de Crudo | T54: =IFERROR(VLOOKUP(S54,Maestro!$A:$H,8,0),"Producción") -> Producción | U54: Clinker
A55: 7355250320 | B55: RTOS VARIA IMPO | C55: =Datos!$N$112*D55 -> 20470915 | D55: =Datos!$N$263 -> 122500 | I55: EC01 | J55: CUERPOS MOLEDORES | K55: 700000 | L55: 7 | M55: HARINA CRUDA | P55: =VLOOKUP(K55,Maestro!J:K,2,0) -> HARINA CRUDA | Q55: =VLOOKUP(P55,Maestro!E:F,2,0) -> Molienda de Crudo | R55: =VLOOKUP(P55,ORD!$A:$C,3,0) -> 3 | S55: =A55&J55&Q55 -> 7355250320CUERPOS MOLEDORESMolienda de Crudo | T55: =IFERROR(VLOOKUP(S55,Maestro!$A:$H,8,0),"Producción") -> Cuerpos Moledores | U55: Clinker
A56: 7355250321 | B56: RTOS VARIA IMPO | C56: =Datos!$N$114*D56 -> 14685656 | D56: =Datos!$N$263 -> 122500 | I56: EC01 | J56: LAMINAS | K56: 700000 | L56: 7 | M56: HARINA CRUDA | P56: =VLOOKUP(K56,Maestro!J:K,2,0) -> HARINA CRUDA | Q56: =VLOOKUP(P56,Maestro!E:F,2,0) -> Molienda de Crudo | R56: =VLOOKUP(P56,ORD!$A:$C,3,0) -> 3 | S56: =A56&J56&Q56 -> 7355250321LAMINASMolienda de Crudo | T56: =IFERROR(VLOOKUP(S56,Maestro!$A:$H,8,0),"Producción") -> Láminas | U56: Clinker
A57: 7355250322 | B57: RTOS VARIA IMPO | C57: =Datos!$N$118*D57 -> 61091249 | D57: =Datos!$N$263 -> 122500 | I57: EC01 | J57: ANILLOS, TAPAS Y SEPARADORES | K57: 700000 | L57: 7 | M57: HARINA CRUDA | P57: =VLOOKUP(K57,Maestro!J:K,2,0) -> HARINA CRUDA | Q57: =VLOOKUP(P57,Maestro!E:F,2,0) -> Molienda de Crudo | R57: =VLOOKUP(P57,ORD!$A:$C,3,0) -> 3 | S57: =A57&J57&Q57 -> 7355250322ANILLOS, TAPAS Y SEPARADORESMolienda de Crudo | T57: =IFERROR(VLOOKUP(S57,Maestro!$A:$H,8,0),"Producción") -> Anillos, Tapas y Separadores | U57: Clinker
A58: 7105040101 | B58: MP CORRECT HIERO NAL | C58: =Datos!$I$48*D58+Datos!$O$90*Base!D58 -> 9.7836561e+08 | D58: =Datos!$O$263*Datos!$O$169*(1+Datos!$O$213) -> 3253.2156 | E58: T | F58: M | G58: 1405040101 | H58: IN CORRECT HIERO NAL | I58: EC01 | J58: CORRHIERR | K58: 700000 | L58: 8 | M58: CORRECTOR DE HIERRO | P58: =VLOOKUP(K58,Maestro!J:K,2,0) -> HARINA CRUDA | Q58: =VLOOKUP(P58,Maestro!E:F,2,0) -> Molienda de Crudo | R58: =VLOOKUP(P58,ORD!$A:$C,3,0) -> 3 | S58: =A58&J58&Q58 -> 7105040101CORRHIERRMolienda de Crudo | T58: =IFERROR(VLOOKUP(S58,Maestro!$A:$H,8,0),"Producción") -> Mineral de Hierro | U58: Clinker
A59: 7105040101 | B59: MP CORRECT HIERO NAL | C59: =Datos!$O$49*D59+Datos!$O$90*D59 -> 94486060 | D59: =Datos!$O$263*Datos!$O$170*(1+Datos!$O$214) -> 554.78634 | E59: T | F59: M | G59: 1405040101 | H59: IN CORRECT HIERO NAL | I59: EC01 | J59: CALAMINA1 | K59: 700000 | L59: 8 | M59: CALAMINA | P59: =VLOOKUP(K59,Maestro!J:K,2,0) -> HARINA CRUDA | Q59: =VLOOKUP(P59,Maestro!E:F,2,0) -> Molienda de Crudo | R59: =VLOOKUP(P59,ORD!$A:$C,3,0) -> 3 | S59: =A59&J59&Q59 -> 7105040101CALAMINA1Molienda de Crudo | T59: =IFERROR(VLOOKUP(S59,Maestro!$A:$H,8,0),"Producción") -> Mineral de Hierro | U59: Clinker
A60: 7105330101 | B60: CTO. MP CALIZAS NAL | D60: =Datos!$O$263*Datos!$O$168*(1+Datos!$O$210) -> 26781.665 | E60: T | F60: M | G60: 1405330101 | H60: INV. CALIZAS NAL | I60: EC01 | J60: CALIZATRI | K60: 700000 | L60: 8 | M60: CALIZA TRITURADA | P60: =VLOOKUP(K60,Maestro!J:K,2,0) -> HARINA CRUDA | Q60: =VLOOKUP(P60,Maestro!E:F,2,0) -> Molienda de Crudo | R60: =VLOOKUP(P60,ORD!$A:$C,3,0) -> 3 | S60: =A60&J60&Q60 -> 7105330101CALIZATRIMolienda de Crudo | T60: =IFERROR(VLOOKUP(S60,Maestro!$A:$H,8,0),"Producción") -> Caliza | U60: Clinker
A61: 7105330101 | B61: CTO. MP CALIZAS NAL | D61: =Datos!$O$263*Datos!$O$167*(1+Datos!$O$212) -> 121787.18 | E61: T | F61: M | G61: 1405330101 | H61: INV. CALIZAS NAL | I61: EC01 | J61: MEZCPREHO | K61: 700000 | L61: 8 | M61: MEZCLA PREHOMO | P61: =VLOOKUP(K61,Maestro!J:K,2,0) -> HARINA CRUDA | Q61: =VLOOKUP(P61,Maestro!E:F,2,0) -> Molienda de Crudo | R61: =VLOOKUP(P61,ORD!$A:$C,3,0) -> 3 | S61: =A61&J61&Q61 -> 7105330101MEZCPREHOMolienda de Crudo | T61: =IFERROR(VLOOKUP(S61,Maestro!$A:$H,8,0),"Producción") -> Prehomo | U61: Clinker
A62: 7999999995 | B62: TRASLADO DE COSTOS | D62: =-Datos!$O$263 -> -146500 | E62: T | F62: M | G62: 1410900101 | H62: INV. SEMIELABORADO | I62: EC01 | J62: HARINACRUD | K62: 700000 | L62: 8 | M62: HARINA CRUDA | P62: =VLOOKUP(K62,Maestro!J:K,2,0) -> HARINA CRUDA | Q62: =VLOOKUP(P62,Maestro!E:F,2,0) -> Molienda de Crudo | R62: =VLOOKUP(P62,ORD!$A:$C,3,0) -> 3 | S62: =A62&J62&Q62 -> 7999999995HARINACRUDMolienda de Crudo | T62: =IFERROR(VLOOKUP(S62,Maestro!$A:$H,8,0),"Producción") -> Producción | U62: Clinker
A63: 7355250320 | B63: RTOS VARIA IMPO | C63: =Datos!$O$112*D63 -> 24481543 | D63: =Datos!$O$263 -> 146500 | I63: EC01 | J63: CUERPOS MOLEDORES | K63: 700000 | L63: 8 | M63: HARINA CRUDA | P63: =VLOOKUP(K63,Maestro!J:K,2,0) -> HARINA CRUDA | Q63: =VLOOKUP(P63,Maestro!E:F,2,0) -> Molienda de Crudo | R63: =VLOOKUP(P63,ORD!$A:$C,3,0) -> 3 | S63: =A63&J63&Q63 -> 7355250320CUERPOS MOLEDORESMolienda de Crudo | T63: =IFERROR(VLOOKUP(S63,Maestro!$A:$H,8,0),"Producción") -> Cuerpos Moledores | U63: Clinker
A64: 7355250321 | B64: RTOS VARIA IMPO | C64: =Datos!$O$114*D64 -> 17562846 | D64: =Datos!$O$263 -> 146500 | I64: EC01 | J64: LAMINAS | K64: 700000 | L64: 8 | M64: HARINA CRUDA | P64: =VLOOKUP(K64,Maestro!J:K,2,0) -> HARINA CRUDA | Q64: =VLOOKUP(P64,Maestro!E:F,2,0) -> Molienda de Crudo | R64: =VLOOKUP(P64,ORD!$A:$C,3,0) -> 3 | S64: =A64&J64&Q64 -> 7355250321LAMINASMolienda de Crudo | T64: =IFERROR(VLOOKUP(S64,Maestro!$A:$H,8,0),"Producción") -> Láminas | U64: Clinker
A65: 7355250322 | B65: RTOS VARIA IMPO | C65: =Datos!$O$118*D65 -> 73060147 | D65: =Datos!$O$263 -> 146500 | I65: EC01 | J65: ANILLOS, TAPAS Y SEPARADORES | K65: 700000 | L65: 8 | M65: HARINA CRUDA | P65: =VLOOKUP(K65,Maestro!J:K,2,0) -> HARINA CRUDA | Q65: =VLOOKUP(P65,Maestro!E:F,2,0) -> Molienda de Crudo | R65: =VLOOKUP(P65,ORD!$A:$C,3,0) -> 3 | S65: =A65&J65&Q65 -> 7355250322ANILLOS, TAPAS Y SEPARADORESMolienda de Crudo | T65: =IFERROR(VLOOKUP(S65,Maestro!$A:$H,8,0),"Producción") -> Anillos, Tapas y Separadores | U65: Clinker
A66: 7105040101 | B66: MP CORRECT HIERO NAL | C66: =Datos!$I$48*D66+Datos!$P$90*Base!D66 -> 7.5996055e+08 | D66: =Datos!$P$263*Datos!$P$169*(1+Datos!$P$213) -> 2525.9609 | E66: T | F66: M | G66: 1405040101 | H66: IN CORRECT HIERO NAL | I66: EC01 | J66: CORRHIERR | K66: 700000 | L66: 9 | M66: CORRECTOR DE HIERRO | P66: =VLOOKUP(K66,Maestro!J:K,2,0) -> HARINA CRUDA | Q66: =VLOOKUP(P66,Maestro!E:F,2,0) -> Molienda de Crudo | R66: =VLOOKUP(P66,ORD!$A:$C,3,0) -> 3 | S66: =A66&J66&Q66 -> 7105040101CORRHIERRMolienda de Crudo | T66: =IFERROR(VLOOKUP(S66,Maestro!$A:$H,8,0),"Producción") -> Mineral de Hierro | U66: Clinker
A67: 7105040101 | B67: MP CORRECT HIERO NAL | C67: =Datos!$P$49*D67+Datos!$P$90*D67 -> 73416288 | D67: =Datos!$P$263*Datos!$P$170*(1+Datos!$P$214) -> 430.76414 | E67: T | F67: M | G67: 1405040101 | H67: IN CORRECT HIERO NAL | I67: EC01 | J67: CALAMINA1 | K67: 700000 | L67: 9 | M67: CALAMINA | P67: =VLOOKUP(K67,Maestro!J:K,2,0) -> HARINA CRUDA | Q67: =VLOOKUP(P67,Maestro!E:F,2,0) -> Molienda de Crudo | R67: =VLOOKUP(P67,ORD!$A:$C,3,0) -> 3 | S67: =A67&J67&Q67 -> 7105040101CALAMINA1Molienda de Crudo | T67: =IFERROR(VLOOKUP(S67,Maestro!$A:$H,8,0),"Producción") -> Mineral de Hierro | U67: Clinker
A68: 7105330101 | B68: CTO. MP CALIZAS NAL | D68: =Datos!$P$263*Datos!$P$168*(1+Datos!$P$210) -> 20794.638 | E68: T | F68: M | G68: 1405330101 | H68: INV. CALIZAS NAL | I68: EC01 | J68: CALIZATRI | K68: 700000 | L68: 9 | M68: CALIZA TRITURADA | P68: =VLOOKUP(K68,Maestro!J:K,2,0) -> HARINA CRUDA | Q68: =VLOOKUP(P68,Maestro!E:F,2,0) -> Molienda de Crudo | R68: =VLOOKUP(P68,ORD!$A:$C,3,0) -> 3 | S68: =A68&J68&Q68 -> 7105330101CALIZATRIMolienda de Crudo | T68: =IFERROR(VLOOKUP(S68,Maestro!$A:$H,8,0),"Producción") -> Caliza | U68: Clinker
A69: 7105330101 | B69: CTO. MP CALIZAS NAL | D69: =Datos!$P$263*Datos!$P$167*(1+Datos!$P$212) -> 94561.721 | E69: T | F69: M | G69: 1405330101 | H69: INV. CALIZAS NAL | I69: EC01 | J69: MEZCPREHO | K69: 700000 | L69: 9 | M69: MEZCLA PREHOMO | P69: =VLOOKUP(K69,Maestro!J:K,2,0) -> HARINA CRUDA | Q69: =VLOOKUP(P69,Maestro!E:F,2,0) -> Molienda de Crudo | R69: =VLOOKUP(P69,ORD!$A:$C,3,0) -> 3 | S69: =A69&J69&Q69 -> 7105330101MEZCPREHOMolienda de Crudo | T69: =IFERROR(VLOOKUP(S69,Maestro!$A:$H,8,0),"Producción") -> Prehomo | U69: Clinker
A70: 7999999995 | B70: TRASLADO DE COSTOS | D70: =-Datos!$P$263 -> -113750 | E70: T | F70: M | G70: 1410900101 | H70: INV. SEMIELABORADO | I70: EC01 | J70: HARINACRUD | K70: 700000 | L70: 9 | M70: HARINA CRUDA | P70: =VLOOKUP(K70,Maestro!J:K,2,0) -> HARINA CRUDA | Q70: =VLOOKUP(P70,Maestro!E:F,2,0) -> Molienda de Crudo | R70: =VLOOKUP(P70,ORD!$A:$C,3,0) -> 3 | S70: =A70&J70&Q70 -> 7999999995HARINACRUDMolienda de Crudo | T70: =IFERROR(VLOOKUP(S70,Maestro!$A:$H,8,0),"Producción") -> Producción | U70: Clinker
A71: 7355250320 | B71: RTOS VARIA IMPO | C71: =Datos!$P$112*D71 -> 19008707 | D71: =Datos!$P$263 -> 113750 | I71: EC01 | J71: CUERPOS MOLEDORES | K71: 700000 | L71: 9 | M71: HARINA CRUDA | P71: =VLOOKUP(K71,Maestro!J:K,2,0) -> HARINA CRUDA | Q71: =VLOOKUP(P71,Maestro!E:F,2,0) -> Molienda de Crudo | R71: =VLOOKUP(P71,ORD!$A:$C,3,0) -> 3 | S71: =A71&J71&Q71 -> 7355250320CUERPOS MOLEDORESMolienda de Crudo | T71: =IFERROR(VLOOKUP(S71,Maestro!$A:$H,8,0),"Producción") -> Cuerpos Moledores | U71: Clinker
A72: 7355250321 | B72: RTOS VARIA IMPO | C72: =Datos!$P$114*D72 -> 13636681 | D72: =Datos!$P$263 -> 113750 | I72: EC01 | J72: LAMINAS | K72: 700000 | L72: 9 | M72: HARINA CRUDA | P72: =VLOOKUP(K72,Maestro!J:K,2,0) -> HARINA CRUDA | Q72: =VLOOKUP(P72,Maestro!E:F,2,0) -> Molienda de Crudo | R72: =VLOOKUP(P72,ORD!$A:$C,3,0) -> 3 | S72: =A72&J72&Q72 -> 7355250321LAMINASMolienda de Crudo | T72: =IFERROR(VLOOKUP(S72,Maestro!$A:$H,8,0),"Producción") -> Láminas | U72: Clinker
A73: 7355250322 | B73: RTOS VARIA IMPO | C73: =Datos!$P$118*D73 -> 56727588 | D73: =Datos!$P$263 -> 113750 | I73: EC01 | J73: ANILLOS, TAPAS Y SEPARADORES | K73: 700000 | L73: 9 | M73: HARINA CRUDA | P73: =VLOOKUP(K73,Maestro!J:K,2,0) -> HARINA CRUDA | Q73: =VLOOKUP(P73,Maestro!E:F,2,0) -> Molienda de Crudo | R73: =VLOOKUP(P73,ORD!$A:$C,3,0) -> 3 | S73: =A73&J73&Q73 -> 7355250322ANILLOS, TAPAS Y SEPARADORESMolienda de Crudo | T73: =IFERROR(VLOOKUP(S73,Maestro!$A:$H,8,0),"Producción") -> Anillos, Tapas y Separadores | U73: Clinker
A74: 7105040101 | B74: MP CORRECT HIERO NAL | C74: =Datos!$I$48*D74+Datos!$Q$90*Base!D74 -> 5.9819372e+08 | D74: =Datos!$Q$263*Datos!$Q$169*(1+Datos!$Q$213) -> 1987.4594 | E74: T | F74: M | G74: 1405040101 | H74: IN CORRECT HIERO NAL | I74: EC01 | J74: CORRHIERR | K74: 700000 | L74: 10 | M74: CORRECTOR DE HIERRO | P74: =VLOOKUP(K74,Maestro!J:K,2,0) -> HARINA CRUDA | Q74: =VLOOKUP(P74,Maestro!E:F,2,0) -> Molienda de Crudo | R74: =VLOOKUP(P74,ORD!$A:$C,3,0) -> 3 | S74: =A74&J74&Q74 -> 7105040101CORRHIERRMolienda de Crudo | T74: =IFERROR(VLOOKUP(S74,Maestro!$A:$H,8,0),"Producción") -> Mineral de Hierro | U74: Clinker
A75: 7105040101 | B75: MP CORRECT HIERO NAL | C75: =Datos!$Q$49*D75+Datos!$Q$90*D75 -> 57806979 | D75: =Datos!$Q$263*Datos!$Q$170*(1+Datos!$Q$214) -> 338.93091 | E75: T | F75: M | G75: 1405040101 | H75: IN CORRECT HIERO NAL | I75: EC01 | J75: CALAMINA1 | K75: 700000 | L75: 10 | M75: CALAMINA | P75: =VLOOKUP(K75,Maestro!J:K,2,0) -> HARINA CRUDA | Q75: =VLOOKUP(P75,Maestro!E:F,2,0) -> Molienda de Crudo | R75: =VLOOKUP(P75,ORD!$A:$C,3,0) -> 3 | S75: =A75&J75&Q75 -> 7105040101CALAMINA1Molienda de Crudo | T75: =IFERROR(VLOOKUP(S75,Maestro!$A:$H,8,0),"Producción") -> Mineral de Hierro | U75: Clinker
A76: 7105330101 | B76: CTO. MP CALIZAS NAL | D76: =Datos!$Q$263*Datos!$Q$168*(1+Datos!$Q$210) -> 16361.495 | E76: T | F76: M | G76: 1405330101 | H76: INV. CALIZAS NAL | I76: EC01 | J76: CALIZATRI | K76: 700000 | L76: 10 | M76: CALIZA TRITURADA | P76: =VLOOKUP(K76,Maestro!J:K,2,0) -> HARINA CRUDA | Q76: =VLOOKUP(P76,Maestro!E:F,2,0) -> Molienda de Crudo | R76: =VLOOKUP(P76,ORD!$A:$C,3,0) -> 3 | S76: =A76&J76&Q76 -> 7105330101CALIZATRIMolienda de Crudo | T76: =IFERROR(VLOOKUP(S76,Maestro!$A:$H,8,0),"Producción") -> Caliza | U76: Clinker
A77: 7105330101 | B77: CTO. MP CALIZAS NAL | D77: =Datos!$Q$263*Datos!$Q$167*(1+Datos!$Q$212) -> 74402.409 | E77: T | F77: M | G77: 1405330101 | H77: INV. CALIZAS NAL | I77: EC01 | J77: MEZCPREHO | K77: 700000 | L77: 10 | M77: MEZCLA PREHOMO | P77: =VLOOKUP(K77,Maestro!J:K,2,0) -> HARINA CRUDA | Q77: =VLOOKUP(P77,Maestro!E:F,2,0) -> Molienda de Crudo | R77: =VLOOKUP(P77,ORD!$A:$C,3,0) -> 3 | S77: =A77&J77&Q77 -> 7105330101MEZCPREHOMolienda de Crudo | T77: =IFERROR(VLOOKUP(S77,Maestro!$A:$H,8,0),"Producción") -> Prehomo | U77: Clinker
A78: 7999999995 | B78: TRASLADO DE COSTOS | D78: =-Datos!$Q$263 -> -89500 | E78: T | F78: M | G78: 1410900101 | H78: INV. SEMIELABORADO | I78: EC01 | J78: HARINACRUD | K78: 700000 | L78: 10 | M78: HARINA CRUDA | P78: =VLOOKUP(K78,Maestro!J:K,2,0) -> HARINA CRUDA | Q78: =VLOOKUP(P78,Maestro!E:F,2,0) -> Molienda de Crudo | R78: =VLOOKUP(P78,ORD!$A:$C,3,0) -> 3 | S78: =A78&J78&Q78 -> 7999999995HARINACRUDMolienda de Crudo | T78: =IFERROR(VLOOKUP(S78,Maestro!$A:$H,8,0),"Producción") -> Producción | U78: Clinker
A79: 7355250320 | B79: RTOS VARIA IMPO | C79: =Datos!$Q$112*D79 -> 14956301 | D79: =Datos!$Q$263 -> 89500 | I79: EC01 | J79: CUERPOS MOLEDORES | K79: 700000 | L79: 10 | M79: HARINA CRUDA | P79: =VLOOKUP(K79,Maestro!J:K,2,0) -> HARINA CRUDA | Q79: =VLOOKUP(P79,Maestro!E:F,2,0) -> Molienda de Crudo | R79: =VLOOKUP(P79,ORD!$A:$C,3,0) -> 3 | S79: =A79&J79&Q79 -> 7355250320CUERPOS MOLEDORESMolienda de Crudo | T79: =IFERROR(VLOOKUP(S79,Maestro!$A:$H,8,0),"Producción") -> Cuerpos Moledores | U79: Clinker
A80: 7355250321 | B80: RTOS VARIA IMPO | C80: =Datos!$Q$114*D80 -> 10729520 | D80: =Datos!$Q$263 -> 89500 | I80: EC01 | J80: LAMINAS | K80: 700000 | L80: 10 | M80: HARINA CRUDA | P80: =VLOOKUP(K80,Maestro!J:K,2,0) -> HARINA CRUDA | Q80: =VLOOKUP(P80,Maestro!E:F,2,0) -> Molienda de Crudo | R80: =VLOOKUP(P80,ORD!$A:$C,3,0) -> 3 | S80: =A80&J80&Q80 -> 7355250321LAMINASMolienda de Crudo | T80: =IFERROR(VLOOKUP(S80,Maestro!$A:$H,8,0),"Producción") -> Láminas | U80: Clinker
A81: 7355250322 | B81: RTOS VARIA IMPO | C81: =Datos!$Q$118*D81 -> 44634015 | D81: =Datos!$Q$263 -> 89500 | I81: EC01 | J81: ANILLOS, TAPAS Y SEPARADORES | K81: 700000 | L81: 10 | M81: HARINA CRUDA | P81: =VLOOKUP(K81,Maestro!J:K,2,0) -> HARINA CRUDA | Q81: =VLOOKUP(P81,Maestro!E:F,2,0) -> Molienda de Crudo | R81: =VLOOKUP(P81,ORD!$A:$C,3,0) -> 3 | S81: =A81&J81&Q81 -> 7355250322ANILLOS, TAPAS Y SEPARADORESMolienda de Crudo | T81: =IFERROR(VLOOKUP(S81,Maestro!$A:$H,8,0),"Producción") -> Anillos, Tapas y Separadores | U81: Clinker
A82: 7105040101 | B82: MP CORRECT HIERO NAL | C82: =Datos!$I$48*D82+Datos!$R$90*Base!D82 -> 9.5170592e+08 | D82: =Datos!$R$263*Datos!$R$169*(1+Datos!$R$213) -> 3164.3906 | E82: T | F82: M | G82: 1405040101 | H82: IN CORRECT HIERO NAL | I82: EC01 | J82: CORRHIERR | K82: 700000 | L82: 11 | M82: CORRECTOR DE HIERRO | P82: =VLOOKUP(K82,Maestro!J:K,2,0) -> HARINA CRUDA | Q82: =VLOOKUP(P82,Maestro!E:F,2,0) -> Molienda de Crudo | R82: =VLOOKUP(P82,ORD!$A:$C,3,0) -> 3 | S82: =A82&J82&Q82 -> 7105040101CORRHIERRMolienda de Crudo | T82: =IFERROR(VLOOKUP(S82,Maestro!$A:$H,8,0),"Producción") -> Mineral de Hierro | U82: Clinker
A83: 7105040101 | B83: MP CORRECT HIERO NAL | C83: =Datos!$R$49*D83+Datos!$R$90*D83 -> 91915337 | D83: =Datos!$R$263*Datos!$R$170*(1+Datos!$R$214) -> 539.63859 | E83: T | F83: M | G83: 1405040101 | H83: IN CORRECT HIERO NAL | I83: EC01 | J83: CALAMINA1 | K83: 700000 | L83: 11 | M83: CALAMINA | P83: =VLOOKUP(K83,Maestro!J:K,2,0) -> HARINA CRUDA | Q83: =VLOOKUP(P83,Maestro!E:F,2,0) -> Molienda de Crudo | R83: =VLOOKUP(P83,ORD!$A:$C,3,0) -> 3 | S83: =A83&J83&Q83 -> 7105040101CALAMINA1Molienda de Crudo | T83: =IFERROR(VLOOKUP(S83,Maestro!$A:$H,8,0),"Producción") -> Mineral de Hierro | U83: Clinker
A84: 7105330101 | B84: CTO. MP CALIZAS NAL | D84: =Datos!$R$263*Datos!$R$168*(1+Datos!$R$210) -> 26050.425 | E84: T | F84: M | G84: 1405330101 | H84: INV. CALIZAS NAL | I84: EC01 | J84: CALIZATRI | K84: 700000 | L84: 11 | M84: CALIZA TRITURADA | P84: =VLOOKUP(K84,Maestro!J:K,2,0) -> HARINA CRUDA | Q84: =VLOOKUP(P84,Maestro!E:F,2,0) -> Molienda de Crudo | R84: =VLOOKUP(P84,ORD!$A:$C,3,0) -> 3 | S84: =A84&J84&Q84 -> 7105330101CALIZATRIMolienda de Crudo | T84: =IFERROR(VLOOKUP(S84,Maestro!$A:$H,8,0),"Producción") -> Caliza | U84: Clinker
A85: 7105330101 | B85: CTO. MP CALIZAS NAL | D85: =Datos!$R$263*Datos!$R$167*(1+Datos!$R$212) -> 118461.94 | E85: T | F85: M | G85: 1405330101 | H85: INV. CALIZAS NAL | I85: EC01 | J85: MEZCPREHO | K85: 700000 | L85: 11 | M85: MEZCLA PREHOMO | P85: =VLOOKUP(K85,Maestro!J:K,2,0) -> HARINA CRUDA | Q85: =VLOOKUP(P85,Maestro!E:F,2,0) -> Molienda de Crudo | R85: =VLOOKUP(P85,ORD!$A:$C,3,0) -> 3 | S85: =A85&J85&Q85 -> 7105330101MEZCPREHOMolienda de Crudo | T85: =IFERROR(VLOOKUP(S85,Maestro!$A:$H,8,0),"Producción") -> Prehomo | U85: Clinker
A86: 7999999995 | B86: TRASLADO DE COSTOS | D86: =-Datos!$R$263 -> -142500 | E86: T | F86: M | G86: 1410900101 | H86: INV. SEMIELABORADO | I86: EC01 | J86: HARINACRUD | K86: 700000 | L86: 11 | M86: HARINA CRUDA | P86: =VLOOKUP(K86,Maestro!J:K,2,0) -> HARINA CRUDA | Q86: =VLOOKUP(P86,Maestro!E:F,2,0) -> Molienda de Crudo | R86: =VLOOKUP(P86,ORD!$A:$C,3,0) -> 3 | S86: =A86&J86&Q86 -> 7999999995HARINACRUDMolienda de Crudo | T86: =IFERROR(VLOOKUP(S86,Maestro!$A:$H,8,0),"Producción") -> Producción | U86: Clinker
A87: 7355250320 | B87: RTOS VARIA IMPO | C87: =Datos!$R$112*D87 -> 23813105 | D87: =Datos!$R$263 -> 142500 | I87: EC01 | J87: CUERPOS MOLEDORES | K87: 700000 | L87: 11 | M87: HARINA CRUDA | P87: =VLOOKUP(K87,Maestro!J:K,2,0) -> HARINA CRUDA | Q87: =VLOOKUP(P87,Maestro!E:F,2,0) -> Molienda de Crudo | R87: =VLOOKUP(P87,ORD!$A:$C,3,0) -> 3 | S87: =A87&J87&Q87 -> 7355250320CUERPOS MOLEDORESMolienda de Crudo | T87: =IFERROR(VLOOKUP(S87,Maestro!$A:$H,8,0),"Producción") -> Cuerpos Moledores | U87: Clinker
A88: 7355250321 | B88: RTOS VARIA IMPO | C88: =Datos!$R$114*D88 -> 17083315 | D88: =Datos!$R$263 -> 142500 | I88: EC01 | J88: LAMINAS | K88: 700000 | L88: 11 | M88: HARINA CRUDA | P88: =VLOOKUP(K88,Maestro!J:K,2,0) -> HARINA CRUDA | Q88: =VLOOKUP(P88,Maestro!E:F,2,0) -> Molienda de Crudo | R88: =VLOOKUP(P88,ORD!$A:$C,3,0) -> 3 | S88: =A88&J88&Q88 -> 7355250321LAMINASMolienda de Crudo | T88: =IFERROR(VLOOKUP(S88,Maestro!$A:$H,8,0),"Producción") -> Láminas | U88: Clinker
A89: 7355250322 | B89: RTOS VARIA IMPO | C89: =Datos!$R$118*D89 -> 71065330 | D89: =Datos!$R$263 -> 142500 | I89: EC01 | J89: ANILLOS, TAPAS Y SEPARADORES | K89: 700000 | L89: 11 | M89: HARINA CRUDA | P89: =VLOOKUP(K89,Maestro!J:K,2,0) -> HARINA CRUDA | Q89: =VLOOKUP(P89,Maestro!E:F,2,0) -> Molienda de Crudo | R89: =VLOOKUP(P89,ORD!$A:$C,3,0) -> 3 | S89: =A89&J89&Q89 -> 7355250322ANILLOS, TAPAS Y SEPARADORESMolienda de Crudo | T89: =IFERROR(VLOOKUP(S89,Maestro!$A:$H,8,0),"Producción") -> Anillos, Tapas y Separadores | U89: Clinker
A90: 7105040101 | B90: MP CORRECT HIERO NAL | C90: =Datos!$I$48*D90+Datos!$S$90*Base!D90 -> 6.1055197e+08 | D90: =Datos!$S$263*Datos!$S$169*(1+Datos!$S$213) -> 2028.3848 | E90: T | F90: M | G90: 1405040101 | H90: IN CORRECT HIERO NAL | I90: EC01 | J90: CORRHIERR | K90: 700000 | L90: 12 | M90: CORRECTOR DE HIERRO | P90: =VLOOKUP(K90,Maestro!J:K,2,0) -> HARINA CRUDA | Q90: =VLOOKUP(P90,Maestro!E:F,2,0) -> Molienda de Crudo | R90: =VLOOKUP(P90,ORD!$A:$C,3,0) -> 3 | S90: =A90&J90&Q90 -> 7105040101CORRHIERRMolienda de Crudo | T90: =IFERROR(VLOOKUP(S90,Maestro!$A:$H,8,0),"Producción") -> Mineral de Hierro | U90: Clinker
A91: 7105040101 | B91: MP CORRECT HIERO NAL | C91: =Datos!$S$49*D91+Datos!$S$90*D91 -> 59004212 | D91: =Datos!$S$263*Datos!$S$170*(1+Datos!$S$214) -> 345.91011 | E91: T | F91: M | G91: 1405040101 | H91: IN CORRECT HIERO NAL | I91: EC01 | J91: CALAMINA1 | K91: 700000 | L91: 12 | M91: CALAMINA | P91: =VLOOKUP(K91,Maestro!J:K,2,0) -> HARINA CRUDA | Q91: =VLOOKUP(P91,Maestro!E:F,2,0) -> Molienda de Crudo | R91: =VLOOKUP(P91,ORD!$A:$C,3,0) -> 3 | S91: =A91&J91&Q91 -> 7105040101CALAMINA1Molienda de Crudo | T91: =IFERROR(VLOOKUP(S91,Maestro!$A:$H,8,0),"Producción") -> Mineral de Hierro | U91: Clinker
A92: 7105330101 | B92: CTO. MP CALIZAS NAL | D92: =Datos!$S$263*Datos!$S$168*(1+Datos!$S$210) -> 16698.408 | E92: T | F92: M | G92: 1405330101 | H92: INV. CALIZAS NAL | I92: EC01 | J92: CALIZATRI | K92: 700000 | L92: 12 | M92: CALIZA TRITURADA | P92: =VLOOKUP(K92,Maestro!J:K,2,0) -> HARINA CRUDA | Q92: =VLOOKUP(P92,Maestro!E:F,2,0) -> Molienda de Crudo | R92: =VLOOKUP(P92,ORD!$A:$C,3,0) -> 3 | S92: =A92&J92&Q92 -> 7105330101CALIZATRIMolienda de Crudo | T92: =IFERROR(VLOOKUP(S92,Maestro!$A:$H,8,0),"Producción") -> Caliza | U92: Clinker
A93: 7105330101 | B93: CTO. MP CALIZAS NAL | D93: =Datos!$S$263*Datos!$S$167*(1+Datos!$S$212) -> 75934.49 | E93: T | F93: M | G93: 1405330101 | H93: INV. CALIZAS NAL | I93: EC01 | J93: MEZCPREHO | K93: 700000 | L93: 12 | M93: MEZCLA PREHOMO | P93: =VLOOKUP(K93,Maestro!J:K,2,0) -> HARINA CRUDA | Q93: =VLOOKUP(P93,Maestro!E:F,2,0) -> Molienda de Crudo | R93: =VLOOKUP(P93,ORD!$A:$C,3,0) -> 3 | S93: =A93&J93&Q93 -> 7105330101MEZCPREHOMolienda de Crudo | T93: =IFERROR(VLOOKUP(S93,Maestro!$A:$H,8,0),"Producción") -> Prehomo | U93: Clinker
A94: 7999999995 | B94: TRASLADO DE COSTOS | D94: =-Datos!$S$263 -> -91342.968 | E94: T | F94: M | G94: 1410900101 | H94: INV. SEMIELABORADO | I94: EC01 | J94: HARINACRUD | K94: 700000 | L94: 12 | M94: HARINA CRUDA | P94: =VLOOKUP(K94,Maestro!J:K,2,0) -> HARINA CRUDA | Q94: =VLOOKUP(P94,Maestro!E:F,2,0) -> Molienda de Crudo | R94: =VLOOKUP(P94,ORD!$A:$C,3,0) -> 3 | S94: =A94&J94&Q94 -> 7999999995HARINACRUDMolienda de Crudo | T94: =IFERROR(VLOOKUP(S94,Maestro!$A:$H,8,0),"Producción") -> Producción | U94: Clinker
A95: 7355250320 | B95: RTOS VARIA IMPO | C95: =Datos!$S$112*D95 -> 15264279 | D95: =Datos!$S$263 -> 91342.968 | I95: EC01 | J95: CUERPOS MOLEDORES | K95: 700000 | L95: 12 | M95: HARINA CRUDA | P95: =VLOOKUP(K95,Maestro!J:K,2,0) -> HARINA CRUDA | Q95: =VLOOKUP(P95,Maestro!E:F,2,0) -> Molienda de Crudo | R95: =VLOOKUP(P95,ORD!$A:$C,3,0) -> 3 | S95: =A95&J95&Q95 -> 7355250320CUERPOS MOLEDORESMolienda de Crudo | T95: =IFERROR(VLOOKUP(S95,Maestro!$A:$H,8,0),"Producción") -> Cuerpos Moledores | U95: Clinker
A96: 7355250321 | B96: RTOS VARIA IMPO | C96: =Datos!$S$114*D96 -> 10950461 | D96: =Datos!$S$263 -> 91342.968 | I96: EC01 | J96: LAMINAS | K96: 700000 | L96: 12 | M96: HARINA CRUDA | P96: =VLOOKUP(K96,Maestro!J:K,2,0) -> HARINA CRUDA | Q96: =VLOOKUP(P96,Maestro!E:F,2,0) -> Molienda de Crudo | R96: =VLOOKUP(P96,ORD!$A:$C,3,0) -> 3 | S96: =A96&J96&Q96 -> 7355250321LAMINASMolienda de Crudo | T96: =IFERROR(VLOOKUP(S96,Maestro!$A:$H,8,0),"Producción") -> Láminas | U96: Clinker
A97: 7355250322 | B97: RTOS VARIA IMPO | C97: =Datos!$S$118*D97 -> 45553110 | D97: =Datos!$S$263 -> 91342.968 | I97: EC01 | J97: ANILLOS, TAPAS Y SEPARADORES | K97: 700000 | L97: 12 | M97: HARINA CRUDA | P97: =VLOOKUP(K97,Maestro!J:K,2,0) -> HARINA CRUDA | Q97: =VLOOKUP(P97,Maestro!E:F,2,0) -> Molienda de Crudo | R97: =VLOOKUP(P97,ORD!$A:$C,3,0) -> 3 | S97: =A97&J97&Q97 -> 7355250322ANILLOS, TAPAS Y SEPARADORESMolienda de Crudo | T97: =IFERROR(VLOOKUP(S97,Maestro!$A:$H,8,0),"Producción") -> Anillos, Tapas y Separadores | U97: Clinker
A98: 7199990001 | B98: CONSUMOS SEMIELBORAD | D98: =Datos!$H$449 -> 9193.1271 | E98: T | F98: M | G98: 1410900101 | H98: INV. SEMIELABORADO | I98: EC01 | J98: CARBONMOL | K98: 700001 | L98: 1 | M98: CARBON MOLIDO | P98: =VLOOKUP(K98,Maestro!J:K,2,0) -> CLINKER | Q98: =VLOOKUP(P98,Maestro!E:F,2,0) -> Clinkerización | R98: =VLOOKUP(P98,ORD!$A:$C,3,0) -> 5 | S98: =A98&J98&Q98 -> 7199990001CARBONMOLClinkerización | T98: =IFERROR(VLOOKUP(S98,Maestro!$A:$H,8,0),"Producción") -> Carbón Molido | U98: Clinker
A99: 7199990001 | B99: CONSUMOS SEMIELBORAD | D99: =Datos!$H$260*Datos!$H$178*(1+Datos!$H$217) -> 128466 | E99: T | F99: M | G99: 1410900101 | H99: INV. SEMIELABORADO | I99: EC01 | J99: HARINACRUD | K99: 700001 | L99: 1 | M99: HARINA CRUDA | P99: =VLOOKUP(K99,Maestro!J:K,2,0) -> CLINKER | Q99: =VLOOKUP(P99,Maestro!E:F,2,0) -> Clinkerización | R99: =VLOOKUP(P99,ORD!$A:$C,3,0) -> 5 | S99: =A99&J99&Q99 -> 7199990001HARINACRUDClinkerización | T99: =IFERROR(VLOOKUP(S99,Maestro!$A:$H,8,0),"Producción") -> Crudo | U99: Clinker
A100: 7999999995 | B100: TRASLADO DE COSTOS | D100: =-Datos!$H$260 -> -82350 | E100: T | F100: M | G100: 1410900101 | H100: INV. SEMIELABORADO | I100: EC01 | J100: CLINKER001 | K100: 700001 | L100: 1 | M100: CLINKER | P100: =VLOOKUP(K100,Maestro!J:K,2,0) -> CLINKER | Q100: =VLOOKUP(P100,Maestro!E:F,2,0) -> Clinkerización | R100: =VLOOKUP(P100,ORD!$A:$C,3,0) -> 5 | S100: =A100&J100&Q100 -> 7999999995CLINKER001Clinkerización | T100: =IFERROR(VLOOKUP(S100,Maestro!$A:$H,8,0),"Producción") -> Producción | U100: Clinker
...

Sheet TD
A1: Período | B1: (Todas) | J1: ORD | K1: (Todas)
J2: Proceso | K2: (Todas)
A3: ORD | B3: Proceso | C3: Tipo | D3: Cantidad | E3: Valor | F3: Suma de Costo
A4: 1 | B4: Trituración | C4: Arcilla | D4: 238400.87 | E4: 2.5325674e+09 | F4: 10623.146 | J4: Arrastre | K4: Tipo | L4: Cantidad | M4: Valor | N4: Suma de Costo
C5: Caliza | D5: 908193.8 | E5: 1.2694853e+10 | F5: 13978.132 | J5: Clinker | K5: Arcilla | L5: 238400.87 | M5: 2.5325674e+09 | N5: 10623.146
C6: Producción | D6: -1146594.7 | E6: 0 | F6: 0 | K6: Caliza | L6: 1761940.1 | M6: 2.1111604e+10 | N6: 11982.021
C7: Barras y Placas | D7: 1146594.7 | E7: 1.035962e+09 | F7: 903.51194 | K7: Caliza Triturada | L7: 347555.55 | M7: 0 | N7: 0
C8: Material Dique | D8: 1146594.7 | E8: 4.2328095e+08 | F8: 369.16354 | K8: Carbón | L8: 101742.73 | M8: 3.4210282e+10 | N8: 336243.02
C9: Energía | D9: 1456175.2 | E9: 7.6470168e+08 | F9: 525.144 | K9: Carbón Molido | L9: 95434.68 | M9: 0 | N9: 0
C10: Regalías | D10: 1146594.7 | E10: 1.7476606e+08 | F10: 152.42183 | K10: Clinker | L10: 825956.5 | M10: 0 | N10: 0
A11: 2 | B11: Adiciones | C11: Caliza | D11: 602137.06 | E11: 8.4167512e+09 | F11: 13978.132 | K11: Crudo | L11: 1336232.2 | M11: 0 | N11: 0
C12: Producción | D12: -602137.06 | E12: 0 | F12: 0 | K12: Mineral de Hierro | L12: 35775.541 | M12: 1.0083725e+10 | N12: 281860.87
C13: Barras y Placas | D13: 602137.06 | E13: 5.4403802e+08 | F13: 903.51194 | K13: Prehomo | L13: 1144170.2 | M13: 0 | N13: 0
C14: Material Dique | D14: 602137.06 | E14: 2.2228705e+08 | F14: 369.16354 | K14: Producción | L14: -25558259 | M14: 0 | N14: 0
C15: Energía | D15: 764714.07 | E15: 4.0166155e+08 | F15: 525.24409 | K15: Yeso | L15: 71664.583 | M15: 1.6671009e+10 | N15: 232625.49
C16: Regalías | D16: 602137.06 | E16: 71405480 | F16: 118.58675 | K16: Cemento ART | L16: 92101.888 | M16: 0 | N16: 0
A17: 3 | B17: Molienda de Crudo | C17: Caliza | D17: 251609.26 | E17: 0 | F17: 0 | K17: Sacos | L17: 19242063 | M17: 1.9054949e+10 | N17: 990.27577
C18: Mineral de Hierro | D18: 35775.541 | E18: 1.0083725e+10 | F18: 281860.87 | K18: Cemento UG | L18: 787665.77 | M18: 0 | N18: 0
C19: Prehomo | D19: 1144170.2 | E19: 0 | F19: 0 | K19: Gasoil | L19: 1364000 | M19: 768000000 | N19: 563.04985
C20: Producción | D20: -1376343 | E20: 0 | F20: 0 | K20: Cuerpos Moledores | L20: 1376343 | M20: 230000000 | N20: 167.10951
C21: Cuerpos Moledores | D21: 1376343 | E21: 230000000 | F21: 167.10951 | K21: Ductos | L21: 856559.09 | M21: 0 | N21: 0
C22: Láminas | D22: 1376343 | E22: 1.65e+08 | F22: 119.88291 | K22: Enfriador | L22: 856559.09 | M22: 158000000 | N22: 184.45896
C23: Anillos, Tapas y Separadores | D23: 1376343 | E23: 6.8638784e+08 | F23: 498.70407 | K23: Placas | L23: 856559.09 | M23: 1082101107 | N23: 1263.3117
C24: Energía | D24: 20782779 | E24: 1.0913977e+10 | F24: 525.1452 | K24: Refractarios | L24: 856559.09 | M24: 3.0841314e+09 | N24: 3600.6055
A25: 4 | B25: Molienda de Carbón | C25: Carbón | D25: 101742.73 | E25: 3.4210282e+10 | F25: 336243.02 | K25: Sal Marina | L25: 0 | M25: 0 | N25: 0
C26: Producción | D26: -95434.68 | E26: 0 | F26: 0 | K26: Cemento UG TP | L26: 33980.72 | M26: 0 | N26: 0
C27: Descargue Finos Carbón | D27: 20348.546 | E27: 1.7703235e+08 | F27: 8700 | K27: Láminas | L27: 1376343 | M27: 1.65e+08 | N27: 119.88291
C28: Cuerpos Moledores y Láminas | D28: 95434.68 | E28: 361600000 | F28: 3788.979 | K28: Sellado | L28: 856559.09 | M28: 0 | N28: 0
C29: Desatasque De Carbón | D29: 95434.68 | E29: 4.2598263e+08 | F29: 4463.604 | K29: Placas y Segmentos | L29: 1300000 | M29: 1.9792431e+09 | N29: 1522.4947
C30: Energía | D30: 2672171.1 | E30: 1.4032679e+09 | F30: 525.1415 | K30: Anillos, Tapas y Separadores | L30: 1376343 | M30: 6.8638784e+08 | N30: 498.70407
C31: Cargador Carbón | D31: 101742.73 | E31: 6.4352276e+08 | F31: 6325 | K31: Descargue Finos Carbón | L31: 20348.546 | M31: 1.7703235e+08 | N31: 8700
A32: 5 | B32: Clinkerización | C32: Carbón Molido | D32: 95434.68 | E32: 0 | F32: 0 | K32: Cargue Clinker | L32: 30000 | M32: 184800000 | N32: 6160
C33: Crudo | D33: 1336232.2 | E33: 0 | F33: 0 | K33: Dosificador de Sal | L33: 0 | M33: 0 | N33: 0
C34: Producción | D34: -856559.09 | E34: 0 | F34: 0 | K34: Cargue Ck Tolva | L34: 0 | M34: 0 | N34: 0
C35: Gasoil | D35: 64000 | E35: 768000000 | F35: 12000 | K35: Cuerpos Moledores y Láminas | L35: 95434.68 | M35: 361600000 | N35: 3788.979
C36: Ductos | D36: 856559.09 | E36: 0 | F36: 0 | K36: Barras y Placas | L36: 1748731.7 | M36: 1.58e+09 | N36: 903.51194
C37: Enfriador | D37: 856559.09 | E37: 158000000 | F37: 184.45896 | K37: Combustibles Alternos | L37: 0 | M37: 0 | N37: 0
C38: Placas | D38: 856559.09 | E38: 1082101107 | F38: 1263.3117 | K38: CDR | L38: 13374.908 | M38: 4.2562935e+09 | N38: 318229.74
C39: Refractarios | D39: 856559.09 | E39: 3.0841314e+09 | F39: 3600.6055 | K39: Llanta Picada | L39: 3047.6678 | M39: 9.7044632e+08 | N39: 318422.6
C40: Sellado | D40: 856559.09 | E40: 0 | F40: 0 | K40: Aditivo Molienda | L40: 633.12956 | M40: 2.7834655e+09 | N40: 4396360
C41: Cargue Clinker | D41: 30000 | E41: 184800000 | F41: 6160 | K41: Puzolana | L41: 24762.361 | M41: 2.6020302e+09 | N41: 105080.05
C42: Cargue Ck Tolva | D42: 0 | E42: 0 | F42: 0 | K42: Finos Filtro | L42: 38133.408 | M42: 0 | N42: 0
C43: Combustibles Alternos | D43: 16422.576 | E43: 0 | F43: 0 | K43: Chip de Madera | L43: 0 | M43: 0 | N43: 0
C44: Energía | D44: 26296364 | E44: 1.3809376e+10 | F44: 525.14393 | K44: Briquetas | L44: 0 | M44: 0 | N44: 0
A45: 6 | B45: Cemento UG | C45: Caliza Triturada | D45: 320127.8 | E45: 0 | F45: 0 | K45: Material Dique | L45: 1748731.7 | M45: 6.45568e+08 | N45: 369.16354
C46: Clinker | D46: 429214.26 | E46: 0 | F46: 0 | K46: Desatasque De Carbón | L46: 95434.68 | M46: 4.2598263e+08 | N46: 4463.604
C47: Producción | D47: -825412.03 | E47: 0 | F47: 0 | K47: Energía | L47: 95524304 | M47: 5.0169824e+10 | N47: 525.2048
C48: Yeso | D48: 33877.138 | E48: 7.8806997e+09 | F48: 232625.89 | K48: Cargador Carbón | L48: 101742.73 | M48: 6.4352276e+08 | N48: 6325
C49: Gasoil | D49: 825412.03 | E49: 0 | F49: 0 | K49: Regalías | L49: 1748731.7 | M49: 2.4617154e+08 | N49: 140.77147
C50: Sal Marina | D50: 0 | E50: 0 | F50: 0 | K50: Cargue Alternos | L50: 16422.576 | M50: 144000000 | N50: 8768.4175
C51: Placas y Segmentos | D51: 825412.03 | E51: 1.2708349e+09 | F51: 1539.637 | K51: Descargue Alternos | L51: 16422.576 | M51: 1.7613212e+08 | N51: 10725
C52: Dosificador de Sal | D52: 0 | E52: 0 | F52: 0 | K52: Empaque y Granel | L52: 1300000 | M52: 4783980000 | N52: 3679.9846
C53: Aditivo Molienda | D53: 412.70602 | E53: 1.8144042e+09 | F53: 4396360 | J53: (en blanco) | K53: (en blanco) | L53: 0 | M53: 0 | N53: 0
C54: Puzolana | D54: 24762.361 | E54: 2.6020302e+09 | F54: 105080.05 | J54: Total general | L54: 1.1415851e+08 | M54: 1.8196785e+11 | N54: 1593.9929
C55: Finos Filtro | D55: 24886.173 | E55: 0 | F55: 0
C56: Energía | D56: 21213089 | E56: 1.1142821e+10 | F56: 525.28045
A57: 7 | B57: Cemento ART | C57: Caliza Triturada | D57: 27427.743 | E57: 0 | F57: 0
C58: Clinker | D58: 365903.09 | E58: 0 | F58: 0
C59: Producción | D59: -440847.09 | E59: 0 | F59: 0
C60: Yeso | D60: 34846.847 | E60: 8.1062535e+09 | F60: 232625.17
C61: Gasoil | D61: 440847.09 | E61: 0 | F61: 0
C62: Sal Marina | D62: 0 | E62: 0 | F62: 0
C63: Placas y Segmentos | D63: 440847.09 | E63: 6.5804383e+08 | F63: 1492.6804
C64: Dosificador de Sal | D64: 0 | E64: 0 | F64: 0
C65: Aditivo Molienda | D65: 220.42355 | E65: 9.6906126e+08 | F65: 4396360
C66: Puzolana | D66: 0 | E66: 0 | F66: 0
C67: Finos Filtro | D67: 13247.235 | E67: 0 | F67: 0
C68: Energía | D68: 15253309 | E68: 8.0122414e+09 | F68: 525.27889
A69: 8 | B69: CEMENTO UG 50 KG | C69: Producción | D69: -14943954 | E69: 0 | F69: 0
C70: Sacos | D70: 15242833 | E70: 1.5254989e+10 | F70: 1000.7975
C71: Cemento UG | D71: 747197.68 | E71: 0 | F71: 0
C72: Energía | D72: 764714.07 | E72: 4.0166155e+08 | F72: 525.24409
A73: 9 | B73: CEMENTO UG 42,5 KG | C73: Producción | D73: -778038.59 | E73: 0 | F73: 0
C74: Sacos | D74: 793599.36 | E74: 7.7485737e+08 | F74: 976.38356
C75: Cemento UG | D75: 33066.64 | E75: 0 | F75: 0
C76: Energía | D76: 764714.07 | E76: 4.0166155e+08 | F76: 525.24409
A77: 10 | B77: CEMENTO UG 25 KG | C77: Producción | D77: -296058.23 | E77: 0 | F77: 0
C78: Sacos | D78: 301979.4 | E78: 2.2509045e+08 | F78: 745.38347
C79: Cemento UG | D79: 7401.4558 | E79: 0 | F79: 0
C80: Energía | D80: 764714.07 | E80: 4.0166155e+08 | F80: 525.24409
A81: 11 | B81: CEMENTO ART 42,5 KG | C81: Producción | D81: -2167103.2 | E81: 0 | F81: 0
C82: Cemento ART | D82: 92101.888 | E82: 0 | F82: 0
C83: Sacos | D83: 2210445.3 | E83: 2.0075619e+09 | F83: 908.21604
C84: Energía | D84: 764714.07 | E84: 4.0166155e+08 | F84: 525.24409
A85: 14 | B85: CEMENTO TOPEX 50 KG | C85: Producción | D85: -679614.41 | E85: 0 | F85: 0
C86: Sacos | D86: 693206.7 | E86: 7.9245003e+08 | F86: 1143.1656
C87: Cemento UG TP | D87: 33980.72 | E87: 0 | F87: 0
C88: Energía | D88: 764714.07 | E88: 4.0166155e+08 | F88: 525.24409
A89: 15 | B89: Cemento UG TP | C89: Caliza Triturada | D89: 0 | E89: 0 | F89: 0
C90: Clinker | D90: 0 | E90: 0 | F90: 0
C91: Producción | D91: 0 | E91: 0 | F91: 0
C92: Yeso | D92: 0 | E92: 0 | F92: 0
C93: Gasoil | D93: 0 | E93: 0 | F93: 0
C94: Sal Marina | D94: 0 | E94: 0 | F94: 0
C95: Placas y Segmentos | D95: 0 | E95: 0 | F95: 0
A96: 16 | B96: Fibrocemento | C96: Caliza Triturada | D96: 0 | E96: 0 | F96: 0
C97: Clinker | D97: 30839.158 | E97: 0 | F97: 0
C98: Producción | D98: -33740.873 | E98: 0 | F98: 0
C99: Yeso | D99: 2940.598 | E99: 6.8405545e+08 | F99: 232624.6
C100: Gasoil | D100: 33740.873 | E100: 0 | F100: 0
...

Sheet Costo
E4: PPTO 2026 | L4: REAL 2025 (Estim. Último trim. con 100% bitumi) F25 | R4: VARIACIONES
E5: Var Mtto + Refract | F5: =I15*I10+I25*I19+I37*(I30+I31+I32)+I46*I43+I75*(I73+I72+I69)+I84*(I91+I107+I168) -> 9348748404
D6: ORD 1 | E6: Proceso | F6: Tipo | G6: Consumo | H6: Costo | I6: Total | K6: ORD 1 | L6: Proceso | M6: Tipo | N6: Consumo | O6: Costo | P6: Total | R6: VP | S6: VC | T6: Total
D7: 1 | E7: Trituración | F7: Arcilla | G7: =IFERROR(GETPIVOTDATA(" Cantidad",TD!$A$3,"Proceso",$E$7,"ORD",$D$7,"Tipo",F7)/GETPIVOTDATA(" Cantidad",TD!$A$3,"Proceso",$E$7,"ORD",$D$7,"Tipo","Producción")*-1,0) -> 0.20792079 | H7: =IFERROR(GETPIVOTDATA("Suma de Costo",TD!$A$3,"Proceso",$E$7,"ORD",$D$7,"Tipo",F7),0) -> 10623.146 | I7: =H7*G7 -> 2208.773 | K7: 1 | L7: Trituración | M7: Arcilla | N7: 0.21731513 | O7: 10136.59 | P7: =N7*O7 -> 2202.8343 | R7: =+(O7-H7)*N7 -> -105.73605 | S7: =+(N7-G7)*H7 -> 99.797399 | T7: =+P7-I7 -> -5.9386497
F8: Caliza | G8: =IFERROR(GETPIVOTDATA(" Cantidad",TD!$A$3,"Proceso","Trituración","ORD",1,"Tipo",F8)/GETPIVOTDATA(" Cantidad",TD!$A$3,"Proceso","Trituración","ORD",1,"Tipo","Producción")*-1,0) -> 0.79207921 | H8: =IFERROR(GETPIVOTDATA("Suma de Costo",TD!$A$3,"Proceso",$E$7,"ORD",$D$7,"Tipo",F8),0) -> 13978.132 | I8: =H8*G8 -> 11071.788 | M8: Caliza | N8: 0.78268487 | O8: 13349.966 | P8: =N8*O8 -> 10448.817 | R8: =+(O8-H8)*N8 -> -491.65578 | S8: =+(N8-G8)*H8 -> -131.31526 | T8: =+P8-I8 -> -622.97104
F9: Energía | G9: =GETPIVOTDATA(" Cantidad",TD!$A$3,"Proceso","Trituración","ORD",1,"Tipo",F9)/((GETPIVOTDATA(" Cantidad",TD!$A$3,"Proceso","Trituración","ORD",1,"Tipo","Producción"))*-1) -> 1.27 | H9: =IFERROR(GETPIVOTDATA("Suma de Costo",TD!$A$3,"Proceso",$E$7,"ORD",$D$7,"Tipo",F9),0) -> 525.144 | I9: =H9*G9 -> 666.93287 | M9: Energía | N9: 1.2925727 | O9: 485.33891 | P9: =N9*O9 -> 627.33584 | R9: =+(O9-H9)*N9 -> -51.450966 | S9: =+(N9-G9)*H9 -> 11.853936 | T9: =+P9-I9 -> -39.597031
C10: P | F10: Barras y Placas | G10: =IFERROR(GETPIVOTDATA(" Cantidad",TD!$A$3,"Proceso","Trituración","ORD",1,"Tipo",F10)/GETPIVOTDATA(" Cantidad",TD!$A$3,"Proceso","Trituración","ORD",1,"Tipo","Producción")*-1,0) -> 1 | H10: =IFERROR(GETPIVOTDATA("Suma de Costo",TD!$A$3,"Proceso",$E$7,"ORD",$D$7,"Tipo",F10),0) -> 903.51194 | I10: =H10*G10 -> 903.51194 | M10: Barras y Placas | N10: 1 | O10: 477.17063 | P10: =N10*O10 -> 477.17063 | R10: =+(O10-H10)*N10 -> -426.34131 | S10: =+(N10-G10)*H10 -> 0 | T10: =+P10-I10 -> -426.34131
F11: Material Dique | G11: =IFERROR(GETPIVOTDATA(" Cantidad",TD!$A$3,"Proceso","Trituración","ORD",1,"Tipo",F11)/GETPIVOTDATA(" Cantidad",TD!$A$3,"Proceso","Trituración","ORD",1,"Tipo","Producción")*-1,0) -> 1 | H11: =IFERROR(GETPIVOTDATA("Suma de Costo",TD!$A$3,"Proceso",$E$7,"ORD",$D$7,"Tipo",F11),0) -> 369.16354 | I11: =H11*G11 -> 369.16354 | M11: Material Dique | N11: 0 | O11: 0 | P11: =N11*O11 -> 0 | R11: =+(O11-H11)*N11 -> 0 | S11: =+(N11-G11)*H11 -> -369.16354 | T11: =+P11-I11 -> -369.16354
F12: Desmantelamiento | G12: 1 | H12: =(IFERROR(GETPIVOTDATA("Suma de Costo",TD!$A$3,"Proceso",$E$7,"ORD",$D$7,"Tipo",F12),0)) -> 0 | I12: =H12*G12 -> 0 | M12: Desmantelamiento | N12: 1 | O12: 0 | P12: =N12*O12 -> 0 | R12: =+(O12-H12)*N12 -> 0 | S12: =+(N12-G12)*H12 -> 0 | T12: =+P12-I12 -> 0
F13: Regalías | G13: 1 | H13: =(IFERROR(GETPIVOTDATA("Suma de Costo",TD!$A$3,"Proceso",$E$7,"ORD",$D$7,"Tipo",F13),0)) -> 152.42183 | I13: =H13*G13 -> 152.42183 | M13: Regalías | N13: 1 | O13: 146.6227 | P13: =N13*O13 -> 146.6227 | R13: =+(O13-H13)*N13 -> -5.7991332 | S13: =+(N13-G13)*H13 -> 0 | T13: =+P13-I13 -> -5.7991332
E14: Total Trituración | I14: =SUM(I7:I13) -> 15372.591 | L14: Total Trituración | P14: =SUM(P7:P13) -> 13902.78 | R14: =+SUM(R7:R13) -> -1080.9832 | S14: =+SUM(S7:S13) -> -388.82746 | T14: =+SUM(T7:T13) -> -1469.8107
E15: TN | I15: =IFERROR(GETPIVOTDATA(" Cantidad",TD!$A$3,"Proceso",E7,"ORD",D7,"Tipo","Producción")*-1,0) -> 1146594.7 | L15: TN | P15: 1234040.9
D17: ORD 2 | E17: Proceso | F17: Tipo | G17: Consumo | H17: Costo | I17: Total | K17: ORD 1 | L17: Proceso | M17: Tipo | N17: Consumo | O17: Costo | P17: Total | R17: VP | S17: VC | T17: Total
D18: 2 | E18: Adiciones | F18: Caliza | G18: =IFERROR(GETPIVOTDATA(" Cantidad",TD!$A$3,"Proceso",$E$18,"ORD",$D$18,"Tipo",F18)/GETPIVOTDATA(" Cantidad",TD!$A$3,"Proceso",$E$18,"ORD",$D$18,"Tipo","Producción")*-1,0) -> 1 | H18: =IFERROR(GETPIVOTDATA("Suma de Costo",TD!$A$3,"Proceso",$E$18,"ORD",$D$18,"Tipo",F18),0) -> 13978.132 | I18: =H18*G18 -> 13978.132 | K18: 2 | L18: Adiciones | M18: Caliza | N18: 1 | O18: 13868.791 | P18: =N18*O18 -> 13868.791 | R18: =+(O18-H18)*N18 -> -109.34051 | S18: =+(N18-G18)*H18 -> 0 | T18: =+P18-I18 -> -109.34051
C19: P | F19: Barras y Placas | G19: =IFERROR(GETPIVOTDATA(" Cantidad",TD!$A$3,"Proceso",$E$18,"ORD",$D$18,"Tipo",F19)/GETPIVOTDATA(" Cantidad",TD!$A$3,"Proceso",$E$18,"ORD",$D$18,"Tipo","Producción")*-1,0) -> 1 | H19: =IFERROR(GETPIVOTDATA("Suma de Costo",TD!$A$3,"Proceso",$E$18,"ORD",$D$18,"Tipo",F19),0) -> 903.51194 | I19: =H19*G19 -> 903.51194 | M19: Barras y Placas | N19: 1 | O19: 477.17063 | P19: =N19*O19 -> 477.17063 | R19: =+(O19-H19)*N19 -> -426.34131 | S19: =+(N19-G19)*H19 -> 0 | T19: =+P19-I19 -> -426.34131
F20: Material Dique | G20: =IFERROR(GETPIVOTDATA(" Cantidad",TD!$A$3,"Proceso",$E$18,"ORD",$D$18,"Tipo",F20)/GETPIVOTDATA(" Cantidad",TD!$A$3,"Proceso",$E$18,"ORD",$D$18,"Tipo","Producción")*-1,0) -> 1 | H20: =IFERROR(GETPIVOTDATA("Suma de Costo",TD!$A$3,"Proceso",$E$18,"ORD",$D$18,"Tipo",F20),0) -> 369.16354 | I20: =H20*G20 -> 369.16354 | M20: Material Dique | N20: 0 | O20: 0 | P20: =N20*O20 -> 0 | R20: =+(O20-H20)*N20 -> 0 | S20: =+(N20-G20)*H20 -> -369.16354 | T20: =+P20-I20 -> -369.16354
F21: Desmantelamiento | G21: =IFERROR(GETPIVOTDATA(" Cantidad",TD!$A$3,"Proceso","Trituración","ORD",1,"Tipo",F21)/GETPIVOTDATA(" Cantidad",TD!$A$3,"Proceso","Trituración","ORD",1,"Tipo","Producción")*-1,0)*0+1 -> 1 | H21: =(IFERROR(GETPIVOTDATA("Suma de Costo",TD!$A$3,"Proceso",$E$18,"ORD",$D$18,"Tipo",F21),0)) -> 0 | I21: =H21*G21 -> 0 | M21: Desmantelamiento | N21: 1 | O21: 0 | P21: =N21*O21 -> 0 | R21: =+(O21-H21)*N21 -> 0 | S21: =+(N21-G21)*H21 -> 0 | T21: =+P21-I21 -> 0
F22: Regalías | G22: =IFERROR(GETPIVOTDATA(" Cantidad",TD!$A$3,"Proceso","Trituración","ORD",1,"Tipo",F22)/GETPIVOTDATA(" Cantidad",TD!$A$3,"Proceso","Trituración","ORD",1,"Tipo","Producción")*-1,0)*0+1 -> 1 | H22: =(IFERROR(GETPIVOTDATA("Suma de Costo",TD!$A$3,"Proceso",$E$18,"ORD",$D$18,"Tipo",F22),0)) -> 118.58675 | I22: =H22*G22 -> 118.58675 | M22: Regalías | N22: 1 | O22: 113.59304 | P22: =N22*O22 -> 113.59304 | R22: =+(O22-H22)*N22 -> -4.9937111 | S22: =+(N22-G22)*H22 -> 0 | T22: =+P22-I22 -> -4.9937111
F23: Energía | G23: =GETPIVOTDATA(" Cantidad",TD!$A$3,"Proceso","Adiciones","ORD",2,"Tipo",F23)/((GETPIVOTDATA(" Cantidad",TD!$A$3,"Proceso","Adiciones","ORD",2,"Tipo","Producción"))*-1) -> 1.27 | H23: =IFERROR(GETPIVOTDATA("Suma de Costo",TD!$A$3,"Proceso",$E$18,"ORD",$D$18,"Tipo",F23),0) -> 525.24409 | I23: =H23*G23 -> 667.06 | M23: Energía | N23: 1.2925727 | O23: 485.33891 | P23: =N23*O23 -> 627.33584 | R23: =+(O23-H23)*N23 -> -51.580351 | S23: =+(N23-G23)*H23 -> 11.856195 | T23: =+P23-I23 -> -39.724156
E24: Total Adiciones | I24: =SUM(I18:I23) -> 16036.454 | L24: Total Adiciones | P24: =SUM(P18:P23) -> 15086.891 | R24: =+SUM(R18:R23) -> -592.25588 | S24: =+SUM(S18:S23) -> -357.30735 | T24: =+SUM(T18:T23) -> -949.56323
E25: TN | I25: =IFERROR(GETPIVOTDATA(" Cantidad",TD!$A$3,"Proceso",E18,"ORD",D18,"Tipo","Producción")*-1,0) -> 602137.06 | L25: TN | P25: 484054.62
D27: ORD 3 | E27: Proceso | F27: Tipo | G27: Consumo | H27: Costo | I27: Total | K27: ORD 3 | L27: Proceso | M27: Tipo | N27: Consumo | O27: Costo | P27: Total | R27: VP | S27: VC | T27: Total
D28: 3 | E28: Molienda de Crudo | F28: Prehomo | G28: =IFERROR(GETPIVOTDATA(" Cantidad",TD!$A$3,"Proceso",$E$28,"ORD",$D$28,"Tipo",F28)/GETPIVOTDATA(" Cantidad",TD!$A$3,"Proceso",$E$28,"ORD",$D$28,"Tipo","Producción")*-1,0) -> 0.83131183 | H28: =I14 -> 15372.591 | I28: =H28*G28 -> 12779.417 | K28: 3 | L28: Molienda de Crudo | M28: Prehomo | N28: 0.89170299 | O28: =P14 -> 13902.78 | P28: =N28*O28 -> 12397.15 | R28: =+(O28-H28)*N28 -> -1310.6346 | S28: =+(N28-G28)*H28 -> 928.36851 | T28: =+P28-I28 -> -382.26608
F29: Caliza | G29: =IFERROR(GETPIVOTDATA(" Cantidad",TD!$A$3,"Proceso",$E$28,"ORD",$D$28,"Tipo",F29)/GETPIVOTDATA(" Cantidad",TD!$A$3,"Proceso",$E$28,"ORD",$D$28,"Tipo","Producción")*-1,0) -> 0.18281 | H29: =+I24 -> 16036.454 | I29: =H29*G29 -> 2931.6242 | M29: Caliza | N29: 0.1211848 | O29: =P24 -> 15086.891 | P29: =N29*O29 -> 1828.3019 | R29: =+(O29-H29)*N29 -> -115.07263 | S29: =+(N29-G29)*H29 -> -988.24965 | T29: =+P29-I29 -> -1103.3223
F30: Cuerpos Moledores | G30: =IFERROR(GETPIVOTDATA(" Cantidad",TD!$A$3,"Proceso",$E$28,"ORD",$D$28,"Tipo",F30)/GETPIVOTDATA(" Cantidad",TD!$A$3,"Proceso",$E$28,"ORD",$D$28,"Tipo","Producción")*-1,0) -> 1 | H30: =IFERROR(GETPIVOTDATA("Suma de Costo",TD!$A$3,"Proceso",$E$28,"ORD",$D$28,"Tipo",F30),0) -> 167.10951 | I30: =H30*G30 -> 167.10951 | M30: Cuerpos Moledores | N30: 1 | O30: 397.89581 | P30: =N30*O30 -> 397.89581 | R30: =+(O30-H30)*N30 -> 230.7863 | S30: =+(N30-G30)*H30 -> 0 | T30: =+P30-I30 -> 230.7863
F31: Láminas | G31: =IFERROR(GETPIVOTDATA(" Cantidad",TD!$A$3,"Proceso",$E$28,"ORD",$D$28,"Tipo",F31)/GETPIVOTDATA(" Cantidad",TD!$A$3,"Proceso",$E$28,"ORD",$D$28,"Tipo","Producción")*-1,0) -> 1 | H31: =IFERROR(GETPIVOTDATA("Suma de Costo",TD!$A$3,"Proceso",$E$28,"ORD",$D$28,"Tipo",F31),0) -> 119.88291 | I31: =H31*G31 -> 119.88291 | M31: Láminas | N31: 1 | O31: 305.60179 | P31: =N31*O31 -> 305.60179 | R31: =+(O31-H31)*N31 -> 185.71888 | S31: =+(N31-G31)*H31 -> 0 | T31: =+P31-I31 -> 185.71888
F32: Anillos, Tapas y Separadores | G32: =IFERROR(GETPIVOTDATA(" Cantidad",TD!$A$3,"Proceso",$E$28,"ORD",$D$28,"Tipo",F32)/GETPIVOTDATA(" Cantidad",TD!$A$3,"Proceso",$E$28,"ORD",$D$28,"Tipo","Producción")*-1,0) -> 1 | H32: =IFERROR(GETPIVOTDATA("Suma de Costo",TD!$A$3,"Proceso",$E$28,"ORD",$D$28,"Tipo",F32),0) -> 498.70407 | I32: =H32*G32 -> 498.70407 | M32: Anillos, Tapas y Separadores | N32: 1 | O32: 205.58666 | P32: =N32*O32 -> 205.58666 | R32: =+(O32-H32)*N32 -> -293.11742 | S32: =+(N32-G32)*H32 -> 0 | T32: =+P32-I32 -> -293.11742
F33: Energía | G33: =GETPIVOTDATA(" Cantidad",TD!$A$3,"Proceso","Molienda de Crudo","ORD",3,"Tipo",F33)/((GETPIVOTDATA(" Cantidad",TD!$A$3,"Proceso","Molienda de Crudo","ORD",3,"Tipo","Producción"))*-1) -> 15.1 | H33: =IFERROR(GETPIVOTDATA("Suma de Costo",TD!$A$3,"Proceso",$E$28,"ORD",$D$28,"Tipo",F33),0) -> 525.1452 | I33: =H33*G33 -> 7929.6925 | M33: Energía | N33: 15.261172 | O33: 485.33891 | P33: =N33*O33 -> 7406.8404 | R33: =+(O33-H33)*N33 -> -607.4906 | S33: =+(N33-G33)*H33 -> 84.63848 | T33: =+P33-I33 -> -522.85213
F34: Sílice | G34: 0 | H34: 0 | I34: =H34*G34 -> 0 | M34: Sílice | N34: 0 | O34: 0 | P34: =N34*O34 -> 0 | R34: =+(O34-H34)*N34 -> 0 | S34: =+(N34-G34)*H34 -> 0 | T34: =+P34-I34 -> 0
F35: Mineral de Hierro | G35: =IFERROR(GETPIVOTDATA(" Cantidad",TD!$A$3,"Proceso",$E$28,"ORD",$D$28,"Tipo",F35)/GETPIVOTDATA(" Cantidad",TD!$A$3,"Proceso",$E$28,"ORD",$D$28,"Tipo","Producción")*-1,0) -> 0.025993187 | H35: =IFERROR(GETPIVOTDATA("Suma de Costo",TD!$A$3,"Proceso",$E$28,"ORD",$D$28,"Tipo",F35),0) -> 281860.87 | I35: =H35*G35 -> 7326.4625 | M35: Mineral de Hierro | N35: 0.025414903 | O35: 256211.07 | P35: =N35*O35 -> 6511.5794 | R35: =+(O35-H35)*N35 -> -651.88731 | S35: =+(N35-G35)*H35 -> -162.99577 | T35: =+P35-I35 -> -814.88308 | AA35: =Z35-Y35 -> 0
E36: Total Molienda de Crudo | I36: =SUM(I28:I35) -> 31752.892 | L36: Total Molienda de Crudo | N36: } | P36: =SUM(P28:P35) -> 29052.956 | R36: =+SUM(R28:R35) -> -2561.6974 | S36: =+SUM(S28:S35) -> -138.23843 | T36: =+SUM(T28:T35) -> -2699.9358
I37: =IFERROR(GETPIVOTDATA(" Cantidad",TD!$A$3,"Proceso",E28,"ORD",D28,"Tipo","Producción")*-1,0) -> 1376343 | P37: 1413903.1
D39: ORD 4 | E39: Proceso | F39: Tipo | G39: Consumo | H39: Costo | I39: Total | K39: ORD 4 | L39: Proceso | M39: Tipo | N39: Consumo | O39: Costo | P39: Total | R39: VP | S39: VC | T39: Total
D40: 4 | E40: Molienda de Carbón | F40: Carbón | G40: =IFERROR(GETPIVOTDATA(" Cantidad",TD!$A$3,"Proceso",$E$40,"ORD",$D$40,"Tipo",F40)/GETPIVOTDATA(" Cantidad",TD!$A$3,"Proceso",$E$40,"ORD",$D$40,"Tipo","Producción")*-1,0) -> 1.0660981 | H40: =IFERROR(GETPIVOTDATA("Suma de Costo",TD!$A$3,"Proceso",$E$40,"ORD",$D$40,"Tipo",F40),0)+IFERROR(GETPIVOTDATA("Suma de Costo",TD!$A$3,"Proceso",$E$40,"ORD",$D$40,"Tipo","Desatasque De Carbón"),0) -> 340706.62 | I40: =H40*G40 -> 363226.67 | K40: 4 | L40: Molienda de Carbón | M40: Carbón | N40: 1.0943444 | O40: 251126.22 | P40: =N40*O40 -> 274818.56 | R40: =+(O40-H40)*N40 -> -98031.805 | S40: =+(N40-G40)*H40 -> 9623.6954 | T40: =+P40-I40 -> -88408.11
F41: Descargue Finos Carbón | G41: =IFERROR(GETPIVOTDATA(" Cantidad",TD!$A$3,"Proceso",$E$40,"ORD",$D$40,"Tipo",F41),0)/IFERROR(GETPIVOTDATA(" Cantidad",TD!$A$3,"Proceso",E40,"ORD",D40,"Tipo","Producción")*-1,0) -> 0.21321962 | H41: =IFERROR(GETPIVOTDATA("Suma de Costo",TD!$A$3,"Proceso",$E$40,"ORD",$D$40,"Tipo",F41),0) -> 8700 | I41: =H41*G41 -> 1855.0107 | M41: Descargue Finos Carbón | N41: 0.27679132 | O41: 7508.9803 | P41: =N41*O41 -> 2078.4206 | R41: =+(O41-H41)*N41 -> -329.6639 | S41: =+(N41-G41)*H41 -> 553.0738 | T41: =+P41-I41 -> 223.40989
F42: Cargador Carbón | G42: =IFERROR(GETPIVOTDATA(" Cantidad",TD!$A$3,"Proceso",$E$40,"ORD",$D$40,"Tipo",F40),0)/IFERROR(GETPIVOTDATA(" Cantidad",TD!$A$3,"Proceso",E40,"ORD",D40,"Tipo","Producción")*-1,0) -> 1.0660981 | H42: =IFERROR(GETPIVOTDATA("Suma de Costo",TD!$A$3,"Proceso",$E$40,"ORD",$D$40,"Tipo",F42),0) -> 6325 | I42: =H42*G42 -> 6743.0704 | M42: Cargador Carbón | N42: 1.0710661 | O42: 7209.7752 | P42: =N42*O42 -> 7722.1455 | R42: =+(O42-H42)*N42 -> 947.65269 | S42: =+(N42-G42)*H42 -> 31.422465 | T42: =+P42-I42 -> 979.07515
F43: Cuerpos Moledores y Láminas | G43: =IFERROR(GETPIVOTDATA(" Cantidad",TD!$A$3,"Proceso",$E$40,"ORD",$D$40,"Tipo",F43)/GETPIVOTDATA(" Cantidad",TD!$A$3,"Proceso",$E$40,"ORD",$D$40,"Tipo","Producción")*-1,0) -> 1 | H43: =IFERROR(GETPIVOTDATA("Suma de Costo",TD!$A$3,"Proceso",$E$40,"ORD",$D$40,"Tipo",F43),0) -> 3788.979 | I43: =H43*G43 -> 3788.979 | M43: Cuerpos Moledores | N43: 1 | O43: 1034.9866 | P43: =N43*O43 -> 1034.9866 | R43: =+(O43-H43)*N43 -> -2753.9924 | S43: =+(N43-G43)*H43 -> 0 | T43: =+P43-I43 -> -2753.9924
F44: Energía | G44: =GETPIVOTDATA(" Cantidad",TD!$A$3,"Proceso","Molienda de Carbón","ORD",4,"Tipo",F44)/((GETPIVOTDATA(" Cantidad",TD!$A$3,"Proceso","Molienda de Carbón","ORD",4,"Tipo","Producción"))*-1) -> 28 | H44: =IFERROR(GETPIVOTDATA("Suma de Costo",TD!$A$3,"Proceso",$E$40,"ORD",$D$40,"Tipo",F44),0) -> 525.1415 | I44: =H44*G44 -> 14703.962 | M44: Energía | N44: 34.339796 | O44: 485.33891 | P44: =N44*O44 -> 16666.439 | R44: =+(O44-H44)*N44 -> -1366.8127 | S44: =+(N44-G44)*H44 -> 3329.2897 | T44: =+P44-I44 -> 1962.4771
E45: Total Molienda de Carbón | I45: =SUM(I40:I44) -> 390317.7 | L45: Total Molienda de Carbón | P45: =SUM(P40:P44) -> 302320.56 | R45: =+SUM(R40:R44) -> -101534.62 | S45: =+SUM(S40:S44) -> 13537.481 | T45: =+SUM(T40:T44) -> -87997.14 | AA45: =Z45-Y45 -> 0
I46: =IFERROR(GETPIVOTDATA(" Cantidad",TD!$A$3,"Proceso",E40,"ORD",D40,"Tipo","Producción")*-1,0) -> 95434.68 | P46: 124970.9
D48: ORD 20 | E48: Proceso | F48: Tipo | G48: Consumo | H48: Costo | I48: Total | L48: Proceso | M48: Tipo | N48: Consumo | O48: Costo | P48: Total | R48: VP | S48: VC | T48: Total
D49: 20 | E49: Combustibles Alternos | F49: CDR | G49: =IFERROR(GETPIVOTDATA(" Cantidad",TD!$A$3,"Proceso",$E$49,"ORD",$D$49,"Tipo",F49)/GETPIVOTDATA(" Cantidad",TD!$A$3,"Proceso",$E$49,"ORD",$D$49,"Tipo","Producción")*-1,0) -> 0.81442206 | H49: =IFERROR(GETPIVOTDATA("Suma de Costo",TD!$A$3,"Proceso",$E$49,"ORD",$D$49,"Tipo",F49),0) -> 318229.74 | I49: =H49*G49 -> 259173.32 | L49: Combustibles Alternos | M49: CDR | N49: 0.42523649 | O49: 293738.62 | P49: =N49*O49 -> 124908.38 | R49: =+(O49-H49)*N49 -> -10414.517 | S49: =+(N49-G49)*H49 -> -123850.42 | T49: =+P49-I49 -> -134264.94
F50: Llanta Picada | G50: =IFERROR(GETPIVOTDATA(" Cantidad",TD!$A$3,"Proceso",$E$49,"ORD",$D$49,"Tipo",F50)/GETPIVOTDATA(" Cantidad",TD!$A$3,"Proceso",$E$49,"ORD",$D$49,"Tipo","Producción")*-1,0) -> 0.18557794 | H50: =IFERROR(GETPIVOTDATA("Suma de Costo",TD!$A$3,"Proceso",$E$49,"ORD",$D$49,"Tipo",F50),0) -> 318422.6 | I50: =H50*G50 -> 59092.212 | M50: Llanta Picada | N50: 0.37053385 | O50: 338940.44 | P50: =N50*O50 -> 125588.91 | R50: =+(O50-H50)*N50 -> 7602.5545 | S50: =+(N50-G50)*H50 -> 58894.142 | T50: =+P50-I50 -> 66496.696
F51: Mezcla | G51: 0 | H51: 0 | I51: =H51*G51 -> 0 | M51: Mezcla | N51: 0.063860476 | O51: 248821.46 | P51: =N51*O51 -> 15889.857 | R51: =+(O51-H51)*N51 -> 15889.857 | S51: =+(N51-G51)*H51 -> 0 | T51: =+P51-I51 -> 15889.857
F52: Chip de Madera | G52: =IFERROR(GETPIVOTDATA(" Cantidad",TD!$A$3,"Proceso",$E$49,"ORD",$D$49,"Tipo",F52)/GETPIVOTDATA(" Cantidad",TD!$A$3,"Proceso",$E$49,"ORD",$D$49,"Tipo","Producción")*-1,0) -> 0 | H52: =IFERROR(GETPIVOTDATA("Suma de Costo",TD!$A$3,"Proceso",$E$49,"ORD",$D$49,"Tipo",F52),0) -> 0 | I52: =H52*G52 -> 0 | M52: Chip de Madera | N52: =0.140369187012787/2 -> 0.070184594 | O52: 332985.22 | P52: =N52*O52 -> 23370.432 | R52: =+(O52-H52)*N52 -> 23370.432 | S52: =+(N52-G52)*H52 -> 0 | T52: =+P52-I52 -> 23370.432
F53: Briquetas | G53: =IFERROR(GETPIVOTDATA(" Cantidad",TD!$A$3,"Proceso",$E$49,"ORD",$D$49,"Tipo",F53)/GETPIVOTDATA(" Cantidad",TD!$A$3,"Proceso",$E$49,"ORD",$D$49,"Tipo","Producción")*-1,0) -> 0 | H53: =IFERROR(GETPIVOTDATA("Suma de Costo",TD!$A$3,"Proceso",$E$49,"ORD",$D$49,"Tipo",F53),0) -> 0 | I53: =H53*G53 -> 0 | M53: Briquetas | N53: =0.140369187012787/2 -> 0.070184594 | O53: 332985.22 | P53: =N53*O53 -> 23370.432 | R53: =+(O53-H53)*N53 -> 23370.432 | S53: =+(N53-G53)*H53 -> 0 | T53: =+P53-I53 -> 23370.432
F54: Cargue | G54: =IFERROR(GETPIVOTDATA(" Cantidad",TD!$A$3,"Proceso",$E$49,"ORD",$D$49,"Tipo","Cargue Alternos")/GETPIVOTDATA(" Cantidad",TD!$A$3,"Proceso",$E$49,"ORD",$D$49,"Tipo","Producción")*-1,0) -> 1 | H54: =IFERROR(GETPIVOTDATA("Suma de Costo",TD!$A$3,"Proceso",$E$49,"ORD",$D$49,"Tipo","Cargue Alternos"),0) -> 8768.4175 | I54: =H54*G54 -> 8768.4175 | M54: Cargue | N54: 1 | O54: 5481.4315 | P54: =N54*O54 -> 5481.4315 | R54: =+(O54-H54)*N54 -> -3286.986 | S54: =+(N54-G54)*H54 -> 0 | T54: =+P54-I54 -> -3286.986
F55: Descargue | G55: =IFERROR(GETPIVOTDATA(" Cantidad",TD!$A$3,"Proceso",$E$49,"ORD",$D$49,"Tipo","Descargue Alternos")/GETPIVOTDATA(" Cantidad",TD!$A$3,"Proceso",$E$49,"ORD",$D$49,"Tipo","Producción")*-1,0) -> 1 | H55: =IFERROR(GETPIVOTDATA("Suma de Costo",TD!$A$3,"Proceso",$E$49,"ORD",$D$49,"Tipo","Descargue Alternos"),0) -> 10725 | I55: =H55*G55 -> 10725 | M55: Descargue | N55: 1 | O55: 4364.6696 | P55: =N55*O55 -> 4364.6696 | R55: =+(O55-H55)*N55 -> -6360.3304 | S55: =+(N55-G55)*H55 -> 0 | T55: =+P55-I55 -> -6360.3304
F56: Energía | G56: =GETPIVOTDATA(" Cantidad",TD!$A$3,"Proceso","Combustibles Alternos","ORD",20,"Tipo",F56)/((GETPIVOTDATA(" Cantidad",TD!$A$3,"Proceso","Combustibles Alternos","ORD",20,"Tipo","Producción"))*-1) -> 8.4 | H56: =IFERROR(GETPIVOTDATA("Suma de Costo",TD!$A$3,"Proceso",$E$49,"ORD",$D$49,"Tipo",F56),0) -> 525.14393 | I56: =H56*G56 -> 4411.209 | M56: Energía | N56: 7.8357651 | O56: 485.33891 | P56: =N56*O56 -> 3803.0017 | R56: =+(O56-H56)*N56 -> -311.90279 | S56: =+(N56-G56)*H56 -> -296.30454 | T56: =+P56-I56 -> -608.20733
F57: Variables | G57: 1 | H57: 0 | I57: =H57*G57 -> 0 | M57: Variables | N57: 1 | O57: 0 | P57: =N57*O57 -> 0 | R57: =+(O57-H57)*N57 -> 0 | S57: =+(N57-G57)*H57 -> 0 | T57: =+P57-I57 -> 0
E58: Total Combustibles Alternos | I58: =SUM(I49:I57) -> 342170.16 | L58: Total Combustibles Alternos | P58: =SUM(P49:P57) -> 326777.11 | R58: =+SUM(R53:R57) -> 13411.213 | S58: =+SUM(S53:S57) -> -296.30454 | T58: =+SUM(T53:T57) -> 13114.909 | AA58: =Z58-Y58 -> 0
I59: =IFERROR(GETPIVOTDATA(" Cantidad",TD!$A$3,"Proceso",E49,"ORD",D49,"Tipo","Combustibles Alternos")*-1,0) -> 16422.576 | P59: 14853.021
D61: ORD 5 | E61: Proceso | F61: Tipo | G61: Consumo | H61: Costo | I61: Total | K61: ORD 5 | L61: Proceso | M61: Tipo | N61: Consumo | O61: Costo | P61: Total | R61: VP | S61: VC | T61: Total
D62: 5 | E62: Clinkerización | F62: Crudo | G62: =IFERROR(GETPIVOTDATA(" Cantidad",TD!$A$3,"Proceso",$E$62,"ORD",$D$62,"Tipo",F62)/GETPIVOTDATA(" Cantidad",TD!$A$3,"Proceso",$E$62,"ORD",$D$62,"Tipo","Producción")*-1,0) -> 1.56 | H62: =I36 -> 31752.892 | I62: =H62*G62 -> 49534.512 | K62: 5 | L62: Clinkerización | M62: Crudo | N62: 1.5600005 | O62: =P36 -> 29052.956 | P62: =N62*O62 -> 45322.625 | R62: =+(O62-H62)*N62 -> -4211.9011 | S62: =+(N62-G62)*H62 -> 0.014296247 | T62: =+P62-I62 -> -4211.8868
F63: Carbón Molido | G63: =IFERROR(GETPIVOTDATA(" Cantidad",TD!$A$3,"Proceso",$E$62,"ORD",$D$62,"Tipo",F63)/GETPIVOTDATA(" Cantidad",TD!$A$3,"Proceso",$E$62,"ORD",$D$62,"Tipo","Producción")*-1,0) -> 0.11141634 | H63: =I45 -> 390317.7 | I63: =H63*G63 -> 43487.77 | M63: Carbón Molido | N63: 0.13154945 | O63: =P45 -> 302320.56 | P63: =N63*O63 -> 39770.104 | R63: =+(O63-H63)*N63 -> -11575.976 | S63: =+(N63-G63)*H63 -> 7858.3097 | T63: =+P63-I63 -> -3717.666
F64: Combustibles Alternos | G64: =IFERROR(GETPIVOTDATA(" Cantidad",TD!$A$3,"Proceso",$E$62,"ORD",$D$62,"Tipo",F64)/GETPIVOTDATA(" Cantidad",TD!$A$3,"Proceso",$E$62,"ORD",$D$62,"Tipo","Producción")*-1,0) -> 0.01917273 | H64: =I58 -> 342170.16 | I64: =H64*G64 -> 6560.336 | M64: Alternos | N64: 0.016480649 | O64: =P58 -> 326777.11 | P64: =N64*O64 -> 5385.4987 | R64: =+(O64-H64)*N64 -> -253.6874 | S64: =+(N64-G64)*H64 -> -921.14981 | T64: =+P64-I64 -> -1174.8372
F65: Ductos | G65: =IFERROR(GETPIVOTDATA(" Cantidad",TD!$A$3,"Proceso",$E$62,"ORD",$D$62,"Tipo",F65)/GETPIVOTDATA(" Cantidad",TD!$A$3,"Proceso",$E$62,"ORD",$D$62,"Tipo","Producción")*-1,0) -> 1 | H65: =IFERROR(GETPIVOTDATA("Suma de Costo",TD!$A$3,"Proceso",$E$62,"ORD",$D$62,"Tipo",F65),0) -> 0 | I65: =H65*G65 -> 0 | M65: Ductos | N65: 1 | O65: 0 | P65: =N65*O65 -> 0 | R65: =+(O65-H65)*N65 -> 0 | S65: =+(N65-G65)*H65 -> 0 | T65: =+P65-I65 -> 0
F66: Energía | G66: =GETPIVOTDATA(" Cantidad",TD!$A$3,"Proceso","Clinkerización","ORD",5,"Tipo",F66)/((GETPIVOTDATA(" Cantidad",TD!$A$3,"Proceso","Clinkerización","ORD",5,"Tipo","Producción"))*-1) -> 30.7 | H66: =IFERROR(GETPIVOTDATA("Suma de Costo",TD!$A$3,"Proceso",$E$62,"ORD",$D$62,"Tipo",F66),0) -> 525.14393 | I66: =H66*G66 -> 16121.919 | M66: Energía | N66: 31.830556 | O66: 485.33891 | P66: =N66*O66 -> 15448.607 | R66: =+(O66-H66)*N66 -> -1267.0159 | S66: =+(N66-G66)*H66 -> 593.70444 | T66: =+P66-I66 -> -673.31146
F67: Cargue Clinker | G67: =IFERROR(GETPIVOTDATA(" Cantidad",TD!$A$3,"Proceso",$E$62,"ORD",$D$62,"Tipo",F67)/GETPIVOTDATA(" Cantidad",TD!$A$3,"Proceso",$E$62,"ORD",$D$62,"Tipo","Producción")*-1,0) -> 0.035023854 | H67: =IFERROR(GETPIVOTDATA("Suma de Costo",TD!$A$3,"Proceso",$E$62,"ORD",$D$62,"Tipo",F67),0) -> 6160 | I67: =H67*G67 -> 215.74694 | M67: Cargue Clinker | N67: 0.041532854 | O67: 7256.0685 | P67: =N67*O67 -> 301.36523 | R67: =+(O67-H67)*N67 -> 45.522852 | S67: =+(N67-G67)*H67 -> 40.095444 | T67: =+P67-I67 -> 85.618295 | AA67: =Z67-Y67 -> 0
F68: Sellado | G68: =IFERROR(GETPIVOTDATA(" Cantidad",TD!$A$3,"Proceso",$E$62,"ORD",$D$62,"Tipo",F68)/GETPIVOTDATA(" Cantidad",TD!$A$3,"Proceso",$E$62,"ORD",$D$62,"Tipo","Producción")*-1,0) -> 1 | H68: =IFERROR(GETPIVOTDATA("Suma de Costo",TD!$A$3,"Proceso",$E$62,"ORD",$D$62,"Tipo",F68),0) -> 0 | I68: =H68*G68 -> 0 | M68: Sellado | N68: 1 | O68: 0 | P68: =N68*O68 -> 0 | R68: =+(O68-H68)*N68 -> 0 | S68: =+(N68-G68)*H68 -> 0 | T68: =+P68-I68 -> 0
F69: Enfriador | G69: =IFERROR(GETPIVOTDATA(" Cantidad",TD!$A$3,"Proceso",$E$62,"ORD",$D$62,"Tipo",F69)/GETPIVOTDATA(" Cantidad",TD!$A$3,"Proceso",$E$62,"ORD",$D$62,"Tipo","Producción")*-1,0) -> 1 | H69: =IFERROR(GETPIVOTDATA("Suma de Costo",TD!$A$3,"Proceso",$E$62,"ORD",$D$62,"Tipo",F69),0) -> 184.45896 | I69: =H69*G69 -> 184.45896 | M69: Enfriador | N69: 1 | O69: 52.460973 | P69: =N69*O69 -> 52.460973 | R69: =+(O69-H69)*N69 -> -131.99799 | S69: =+(N69-G69)*H69 -> 0 | T69: =+P69-I69 -> -131.99799
F70: Cargue Ck Tolva | G70: =IFERROR(GETPIVOTDATA("Suma de Costo",TD!$A$3,"Proceso",$E$62,"ORD",$D$62,"Tipo",F70),0) -> 0 | H70: =IFERROR(GETPIVOTDATA("Suma de Costo",TD!$A$3,"Proceso",$E$62,"ORD",$D$62,"Tipo",F70),0) -> 0 | I70: =H70*G70 -> 0 | M70: Cargue Ck Tolva | N70: 0.14633443 | O70: 13.795097 | P70: =N70*O70 -> 2.0186976 | R70: =+(O70-H70)*N70 -> 2.0186976 | S70: =+(N70-G70)*H70 -> 0 | T70: =+P70-I70 -> 2.0186976
F71: Gasoil | G71: =IFERROR(GETPIVOTDATA(" Cantidad",TD!$A$3,"Proceso",$E$62,"ORD",$D$62,"Tipo",F71)/GETPIVOTDATA(" Cantidad",TD!$A$3,"Proceso",$E$62,"ORD",$D$62,"Tipo","Producción")*-1,0) -> 0.074717554 | H71: =IFERROR(GETPIVOTDATA("Suma de Costo",TD!$A$3,"Proceso",$E$62,"ORD",$D$62,"Tipo",F71),0) -> 12000 | I71: =H71*G71 -> 896.61065 | M71: Gasoil | N71: 0.12853227 | O71: 8663.0042 | P71: =N71*O71 -> 1113.4756 | R71: =+(O71-H71)*N71 -> -428.91164 | S71: =+(N71-G71)*H71 -> 645.7766 | T71: =+P71-I71 -> 216.86495 | AA71: =Z71-Y71 -> 0
F72: Placas | G72: =IFERROR(GETPIVOTDATA(" Cantidad",TD!$A$3,"Proceso",$E$62,"ORD",$D$62,"Tipo",F72)/GETPIVOTDATA(" Cantidad",TD!$A$3,"Proceso",$E$62,"ORD",$D$62,"Tipo","Producción")*-1,0) -> 1 | H72: =IFERROR(GETPIVOTDATA("Suma de Costo",TD!$A$3,"Proceso",$E$62,"ORD",$D$62,"Tipo",F72),0) -> 1263.3117 | I72: =H72*G72 -> 1263.3117 | M72: Placas | N72: 1 | O72: 3045.2609 | P72: =N72*O72 -> 3045.2609 | R72: =+(O72-H72)*N72 -> 1781.9492 | S72: =+(N72-G72)*H72 -> 0 | T72: =+P72-I72 -> 1781.9492 | AA72: =Z72-Y72 -> 0
F73: Refractarios | G73: =IFERROR(GETPIVOTDATA(" Cantidad",TD!$A$3,"Proceso",$E$62,"ORD",$D$62,"Tipo",F73)/GETPIVOTDATA(" Cantidad",TD!$A$3,"Proceso",$E$62,"ORD",$D$62,"Tipo","Producción")*-1,0) -> 1 | H73: =IFERROR(GETPIVOTDATA("Suma de Costo",TD!$A$3,"Proceso",$E$62,"ORD",$D$62,"Tipo",F73),0) -> 3600.6055 | I73: =H73*G73 -> 3600.6055 | M73: Refractarios | N73: 1 | O73: 3021.5659 | P73: =N73*O73 -> 3021.5659 | R73: =+(O73-H73)*N73 -> -579.03961 | S73: =+(N73-G73)*H73 -> 0 | T73: =+P73-I73 -> -579.03961 | AA73: =Z73-Y73 -> 0
E74: Total Clinkerización | I74: =SUM(I62:I73) -> 121865.27 | L74: Total Clinkerización | P74: =SUM(P62:P73) -> 113462.98 | R74: =+SUM(R62:R73) -> -16619.039 | S74: =+SUM(S62:S73) -> 8216.7507 | T74: =+SUM(T62:T73) -> -8402.2878
I75: =IFERROR(GETPIVOTDATA(" Cantidad",TD!$A$3,"Proceso",E62,"ORD",D62,"Tipo","Producción")*-1,0) -> 856559.09 | P75: 887315.43
D77: ORD 6 | E77: Proceso | F77: Tipo | G77: Consumo | H77: Costo | I77: Total | K77: ORD 6 | L77: Proceso | M77: Tipo | N77: Consumo | O77: Costo | P77: Total | R77: VP | S77: VC | T77: Total
D78: 6 | E78: Cemento UG | F78: Clinker | G78: =IFERROR(GETPIVOTDATA(" Cantidad",TD!$A$3,"Proceso",$E$78,"ORD",$D$78,"Tipo",F78)/GETPIVOTDATA(" Cantidad",TD!$A$3,"Proceso",$E$78,"ORD",$D$78,"Tipo","Producción")*-1,0) -> 0.52 | H78: =I74 -> 121865.27 | I78: =H78*G78 -> 63369.941 | K78: 6 | L78: Cemento UG | M78: Clinker | N78: 0.53491329 | O78: =P74 -> 113462.98 | P78: =N78*O78 -> 60692.857 | R78: =+(O78-H78)*N78 -> -4494.4955 | S78: =+(N78-G78)*H78 -> 1817.4124 | T78: =+P78-I78 -> -2677.0831
F79: Caliza Triturada | G79: =IFERROR(GETPIVOTDATA(" Cantidad",TD!$A$3,"Proceso",$E$78,"ORD",$D$78,"Tipo",F79)/GETPIVOTDATA(" Cantidad",TD!$A$3,"Proceso",$E$78,"ORD",$D$78,"Tipo","Producción")*-1,0) -> 0.38784 | H79: =+I24 -> 16036.454 | I79: =H79*G79 -> 6219.5783 | M79: Caliza Triturada | N79: 0.37435214 | O79: =P24 -> 15086.891 | P79: =N79*O79 -> 5647.8098 | R79: =+(O79-H79)*N79 -> -355.47103 | S79: =+(N79-G79)*H79 -> -216.29745 | T79: =+P79-I79 -> -571.76847
F80: Aditivo Molienda | G80: =IFERROR(GETPIVOTDATA(" Cantidad",TD!$A$3,"Proceso",$E$78,"ORD",$D$78,"Tipo",F80)/GETPIVOTDATA(" Cantidad",TD!$A$3,"Proceso",$E$78,"ORD",$D$78,"Tipo","Producción")*-1,0) -> 0.0005 | H80: =IFERROR(GETPIVOTDATA("Suma de Costo",TD!$A$3,"Proceso",$E$78,"ORD",$D$78,"Tipo",F80),0) -> 4396360 | I80: =H80*G80 -> 2198.18 | M80: Aditivo Molienda | N80: 0.00050303889 | O80: 4014954.5 | P80: =N80*O80 -> 2019.6782 | R80: =+(O80-H80)*N80 -> -191.86182 | S80: =+(N80-G80)*H80 -> 13.360052 | T80: =+P80-I80 -> -178.50177
F81: Puzolana | G81: =IFERROR(GETPIVOTDATA(" Cantidad",TD!$A$3,"Proceso",$E$78,"ORD",$D$78,"Tipo",F81)/GETPIVOTDATA(" Cantidad",TD!$A$3,"Proceso",$E$78,"ORD",$D$78,"Tipo","Producción")*-1,0) -> 0.03 | H81: =IFERROR(GETPIVOTDATA("Suma de Costo",TD!$A$3,"Proceso",$E$78,"ORD",$D$78,"Tipo",F81),0) -> 105080.05 | I81: =H81*G81 -> 3152.4016 | M81: Puzolana | N81: 0.028487188 | O81: 109078.76 | P81: =N81*O81 -> 3107.347 | R81: =+(O81-H81)*N81 -> 113.91183 | S81: =+(N81-G81)*H81 -> -158.96642 | T81: =+P81-I81 -> -45.054589
F82: Finos Filtro | G82: =IFERROR(GETPIVOTDATA(" Cantidad",TD!$A$3,"Proceso",$E$78,"ORD",$D$78,"Tipo",F82)/GETPIVOTDATA(" Cantidad",TD!$A$3,"Proceso",$E$78,"ORD",$D$78,"Tipo","Producción")*-1,0) -> 0.03015 | H82: =I36 -> 31752.892 | I82: =H82*G82 -> 957.3497 | M82: Finos Filtro | N82: 0.02494618 | O82: =P36 -> 29052.956 | P82: =N82*O82 -> 724.76027 | R82: =+(O82-H82)*N82 -> -67.353084 | S82: =+(N82-G82)*H82 -> -165.23634 | T82: =+P82-I82 -> -232.58943
C83: P | F83: Cuerpos Moledores | G83: =IFERROR(GETPIVOTDATA(" Cantidad",TD!$A$3,"Proceso",$E$78,"ORD",$D$78,"Tipo",F83)/GETPIVOTDATA(" Cantidad",TD!$A$3,"Proceso",$E$78,"ORD",$D$78,"Tipo","Producción")*-1,0) -> 0 | H83: =IFERROR(GETPIVOTDATA("Suma de Costo",TD!$A$3,"Proceso",$E$78,"ORD",$D$78,"Tipo",F83),0) -> 0 | I83: =H83*G83 -> 0 | M83: Cuerpos Moledores | N83: 0 | O83: 0 | P83: =N83*O83 -> 0 | R83: =+(O83-H83)*N83 -> 0 | S83: =+(N83-G83)*H83 -> 0 | T83: =+P83-I83 -> 0
F84: Placas y Segmentos | G84: 1 | H84: =IFERROR(GETPIVOTDATA("Suma de Costo",TD!$A$3,"Proceso",$E$78,"ORD",$D$78,"Tipo",F84),0) -> 1539.637 | I84: =H84*G84 -> 1539.637 | M84: Placas y Segmentos | N84: 1 | O84: 1117.2996 | P84: =N84*O84 -> 1117.2996 | R84: =+(O84-H84)*N84 -> -422.33738 | S84: =+(N84-G84)*H84 -> 0 | T84: =+P84-I84 -> -422.33738
F85: Energía | G85: =GETPIVOTDATA(" Cantidad",TD!$A$3,"Proceso","Cemento UG","ORD",6,"Tipo",F85)/((GETPIVOTDATA(" Cantidad",TD!$A$3,"Proceso","Cemento UG","ORD",6,"Tipo","Producción"))*-1) -> 25.7 | H85: =IFERROR(GETPIVOTDATA("Suma de Costo",TD!$A$3,"Proceso",$E$78,"ORD",$D$78,"Tipo",F85),0) -> 525.28045 | I85: =H85*G85 -> 13499.708 | M85: Energía | N85: 26.405728 | O85: 485.33891 | P85: =N85*O85 -> 12815.727 | R85: =+(O85-H85)*N85 -> -1054.6854 | S85: =+(N85-G85)*H85 -> 370.70521 | T85: =+P85-I85 -> -683.98017
F86: Gasoil | G86: =IFERROR(GETPIVOTDATA(" Cantidad",TD!$A$3,"Proceso",$E$78,"ORD",$D$78,"Tipo",F86)/GETPIVOTDATA(" Cantidad",TD!$A$3,"Proceso",$E$78,"ORD",$D$78,"Tipo","Producción")*-1,0) -> 1 | H86: =IFERROR(GETPIVOTDATA("Suma de Costo",TD!$A$3,"Proceso",$E$78,"ORD",$D$78,"Tipo",F86),0) -> 0 | I86: =H86*G86 -> 0 | M86: Gasoil | N86: 0 | O86: 0 | P86: =N86*O86 -> 0 | R86: =+(O86-H86)*N86 -> 0 | S86: =+(N86-G86)*H86 -> 0 | T86: =+P86-I86 -> 0
F87: Sal Marina | G87: =IFERROR(GETPIVOTDATA(" Cantidad",TD!$A$3,"Proceso",$E$78,"ORD",$D$78,"Tipo",F87)/GETPIVOTDATA(" Cantidad",TD!$A$3,"Proceso",$E$78,"ORD",$D$78,"Tipo","Producción")*-1,0) -> 0 | H87: =IFERROR(GETPIVOTDATA("Suma de Costo",TD!$A$3,"Proceso",$E$78,"ORD",$D$78,"Tipo",F87),0) -> 0 | I87: =H87*G87 -> 0 | M87: Sal Marina | N87: 0 | O87: 0 | P87: =N87*O87 -> 0 | R87: =+(O87-H87)*N87 -> 0 | S87: =+(N87-G87)*H87 -> 0 | T87: =+P87-I87 -> 0
F88: Dosificador de Sal | G88: =IFERROR(GETPIVOTDATA(" Cantidad",TD!$A$3,"Proceso",$E$78,"ORD",$D$78,"Tipo",F88)/GETPIVOTDATA(" Cantidad",TD!$A$3,"Proceso",$E$78,"ORD",$D$78,"Tipo","Producción")*-1,0) -> 0 | H88: =IFERROR(GETPIVOTDATA("Suma de Costo",TD!$A$3,"Proceso",$E$78,"ORD",$D$78,"Tipo",F88),0) -> 0 | I88: =H88*G88 -> 0 | M88: Dosificador de Sal | N88: 0 | O88: 0 | P88: =N88*O88 -> 0 | R88: =+(O88-H88)*N88 -> 0 | S88: =+(N88-G88)*H88 -> 0 | T88: =+P88-I88 -> 0
F89: Yeso | G89: =IFERROR(GETPIVOTDATA(" Cantidad",TD!$A$3,"Proceso",$E$78,"ORD",$D$78,"Tipo",F89)/GETPIVOTDATA(" Cantidad",TD!$A$3,"Proceso",$E$78,"ORD",$D$78,"Tipo","Producción")*-1,0) -> 0.0410427 | H89: =IFERROR(GETPIVOTDATA("Suma de Costo",TD!$A$3,"Proceso",$E$78,"ORD",$D$78,"Tipo",F89),0) -> 232625.89 | I89: =H89*G89 -> 9547.5948 | M89: Yeso | N89: 0.044430291 | O89: 220009.06 | P89: =N89*O89 -> 9775.0665 | R89: =+(O89-H89)*N89 -> -560.56972 | S89: =+(N89-G89)*H89 -> 788.04144 | T89: =+P89-I89 -> 227.47173
E90: Total Cemento UG | I90: =SUM(I78:I89) -> 100484.39 | L90: Total Cemento UG | P90: =SUM(P78:P89) -> 95900.546 | R90: =+SUM(R78:R89) -> -7032.862 | S90: =+SUM(S78:S89) -> 2449.0189 | T90: =+SUM(T78:T89) -> -4583.8432
I91: =IFERROR(GETPIVOTDATA(" Cantidad",TD!$A$3,"Proceso",E78,"ORD",D78,"Tipo","Producción")*-1,0) -> 825412.03 | P91: 770686.4 | Y91: =P91/(P91+P107+P168) -> 0.62450123
I92: =I168/(I91+I107+I168) -> 0.025954517 | Y92: =P107/(P91+P107+P168) -> 0.34095486
D93: ORD 6 | E93: Proceso | F93: Tipo | G93: Consumo | H93: Costo | I93: Total | K93: ORD 6 | L93: Proceso | M93: Tipo | N93: Consumo | O93: Costo | P93: Total | R93: VP | S93: VC | T93: Total | Y93: =P168/(P91+P107+P168) -> 0.034543916
D94: 7 | E94: Cemento ART | F94: Clinker | G94: =IFERROR(GETPIVOTDATA(" Cantidad",TD!$A$3,"Proceso",$E$94,"ORD",$D$94,"Tipo",F94)/GETPIVOTDATA(" Cantidad",TD!$A$3,"Proceso",$E$94,"ORD",$D$94,"Tipo","Producción")*-1,0) -> 0.83 | H94: =+I74 -> 121865.27 | I94: =H94*G94 -> 101148.17 | K94: 7 | L94: Cemento ART | M94: Clinker | N94: 0.83470233 | O94: =P74 -> 113462.98 | P94: =N94*O94 -> 94707.816 | R94: =+(O94-H94)*N94 -> -7013.4092 | S94: =+(N94-G94)*H94 -> 573.05042 | T94: =+P94-I94 -> -6440.3588
F95: Caliza Triturada | G95: =IFERROR(GETPIVOTDATA(" Cantidad",TD!$A$3,"Proceso",$E$94,"ORD",$D$94,"Tipo",F95)/GETPIVOTDATA(" Cantidad",TD!$A$3,"Proceso",$E$94,"ORD",$D$94,"Tipo","Producción")*-1,0) -> 0.062216 | H95: =+I24 -> 16036.454 | I95: =H95*G95 -> 997.72402 | M95: Caliza Triturada | N95: 0.06114641 | O95: =P24 -> 15086.891 | P95: =N95*O95 -> 922.5092 | R95: =+(O95-H95)*N95 -> -58.062382 | S95: =+(N95-G95)*H95 -> -17.152438 | T95: =+P95-I95 -> -75.21482
F96: Aditivo Molienda | G96: =IFERROR(GETPIVOTDATA(" Cantidad",TD!$A$3,"Proceso",$E$94,"ORD",$D$94,"Tipo",F96)/GETPIVOTDATA(" Cantidad",TD!$A$3,"Proceso",$E$94,"ORD",$D$94,"Tipo","Producción")*-1,0) -> 0.0005 | H96: =IFERROR(GETPIVOTDATA("Suma de Costo",TD!$A$3,"Proceso",$E$94,"ORD",$D$94,"Tipo",F96),0) -> 4396360 | I96: =H96*G96 -> 2198.18 | M96: Aditivo Molienda | N96: 0.00050095345 | O96: 4014954.5 | P96: =N96*O96 -> 2011.3053
F97: Puzolana | G97: =IFERROR(GETPIVOTDATA(" Cantidad",TD!$A$3,"Proceso",$E$94,"ORD",$D$94,"Tipo",F97)/GETPIVOTDATA(" Cantidad",TD!$A$3,"Proceso",$E$94,"ORD",$D$94,"Tipo","Producción")*-1,0) -> 0 | H97: =IFERROR(GETPIVOTDATA("Suma de Costo",TD!$A$3,"Proceso",$E$94,"ORD",$D$94,"Tipo",F97),0) -> 0 | I97: =H97*G97 -> 0 | M97: Puzolana | N97: 0 | O97: =O81 -> 109078.76 | P97: =N97*O97 -> 0 | R97: =+(O97-H97)*N97 -> 0 | S97: =+(N97-G97)*H97 -> 0 | T97: =+P97-I97 -> 0
F98: Finos Filtro | G98: =IFERROR(GETPIVOTDATA(" Cantidad",TD!$A$3,"Proceso",$E$94,"ORD",$D$94,"Tipo",F98)/GETPIVOTDATA(" Cantidad",TD!$A$3,"Proceso",$E$94,"ORD",$D$94,"Tipo","Producción")*-1,0) -> 0.0300495 | H98: =I36 -> 31752.892 | I98: =H98*G98 -> 954.15853 | M98: Finos Filtro | N98: 0.024630431 | O98: =P36 -> 29052.956 | P98: =N98*O98 -> 715.58684 | R98: =+(O98-H98)*N98 -> -66.500583 | S98: =+(N98-G98)*H98 -> -172.07111 | T98: =+P98-I98 -> -238.57169
C99: P | F99: Cuerpos Moledores | G99: =IFERROR(GETPIVOTDATA(" Cantidad",TD!$A$3,"Proceso",$E$94,"ORD",$D$94,"Tipo",F99)/GETPIVOTDATA(" Cantidad",TD!$A$3,"Proceso",$E$94,"ORD",$D$94,"Tipo","Producción")*-1,0) -> 0 | H99: =IFERROR(GETPIVOTDATA("Suma de Costo",TD!$A$3,"Proceso",$E$78,"ORD",$D$78,"Tipo",F99),0) -> 0 | I99: =H99*G99 -> 0 | M99: Cuerpos Moledores | N99: 0 | O99: 0 | P99: =N99*O99 -> 0 | R99: =+(O99-H99)*N99 -> 0 | S99: =+(N99-G99)*H99 -> 0 | T99: =+P99-I99 -> 0
F100: Placas y Segmentos | G100: =IFERROR(GETPIVOTDATA(" Cantidad",TD!$A$3,"Proceso",$E$78,"ORD",$D$78,"Tipo",F100)/GETPIVOTDATA(" Cantidad",TD!$A$3,"Proceso",$E$78,"ORD",$D$78,"Tipo","Producción")*-1,0) -> 1 | H100: =IFERROR(GETPIVOTDATA("Suma de Costo",TD!$A$3,"Proceso",$E$78,"ORD",$D$78,"Tipo",F100),0) -> 1539.637 | I100: =H100*G100 -> 1539.637 | M100: Placas y Segmentos | N100: 1 | O100: 1117.2996 | P100: =N100*O100 -> 1117.2996 | R100: =+(O100-H100)*N100 -> -422.33738 | S100: =+(N100-G100)*H100 -> 0 | T100: =+P100-I100 -> -422.33738
F101: Energía | G101: =GETPIVOTDATA(" Cantidad",TD!$A$3,"Proceso","Cemento ART","ORD",7,"Tipo",F101)/((GETPIVOTDATA(" Cantidad",TD!$A$3,"Proceso","Cemento ART","ORD",7,"Tipo","Producción"))*-1) -> 34.6 | H101: =IFERROR(GETPIVOTDATA("Suma de Costo",TD!$A$3,"Proceso",$E$94,"ORD",$D$94,"Tipo",F101),0) -> 525.27889 | I101: =H101*G101 -> 18174.65 | M101: Energía | N101: 36.732237 | O101: 485.33891 | P101: =N101*O101 -> 17827.584 | R101: =+(O101-H101)*N101 -> -1467.0847 | S101: =+(N101-G101)*H101 -> 1120.0192 | T101: =+P101-I101 -> -347.06556
F102: Gasoil | G102: =IFERROR(GETPIVOTDATA(" Cantidad",TD!$A$3,"Proceso",$E$94,"ORD",$D$94,"Tipo",F102)/GETPIVOTDATA(" Cantidad",TD!$A$3,"Proceso",$E$94,"ORD",$D$94,"Tipo","Producción")*-1,0) -> 1 | H102: =IFERROR(GETPIVOTDATA("Suma de Costo",TD!$A$3,"Proceso",$E$94,"ORD",$D$94,"Tipo",F102),0) -> 0 | I102: =H102*G102 -> 0 | M102: Gasoil | N102: 0 | O102: 0 | P102: =N102*O102 -> 0 | R102: =+(O102-H102)*N102 -> 0 | S102: =+(N102-G102)*H102 -> 0 | T102: =+P102-I102 -> 0 | Y102: Ponderados
F103: Sal Marina | G103: =IFERROR(GETPIVOTDATA(" Cantidad",TD!$A$3,"Proceso",$E$94,"ORD",$D$94,"Tipo",F103)/GETPIVOTDATA(" Cantidad",TD!$A$3,"Proceso",$E$94,"ORD",$D$94,"Tipo","Producción")*-1,0) -> 0 | H103: =IFERROR(GETPIVOTDATA("Suma de Costo",TD!$A$3,"Proceso",$E$94,"ORD",$D$94,"Tipo",F103),0) -> 0 | I103: =H103*G103 -> 0 | M103: Sal Marina | N103: 0 | O103: 0 | P103: =N103*O103 -> 0 | R103: =+(O103-H103)*N103 -> 0 | S103: =+(N103-G103)*H103 -> 0 | T103: =+P103-I103 -> 0 | Y103: CV POND CEM P2026 | Z103: =((I114*I115)+(I122*I123)+(I130*I131)+(I138*I139)+(I146*I147)+(I196*I197)+(I210*I211)+(I203*I204))/(I115+I123+I131+I139+I147+I197+I204+I211) -> 135484.08
F104: Dosificador de Sal | G104: =IFERROR(GETPIVOTDATA(" Cantidad",TD!$A$3,"Proceso",$E$94,"ORD",$D$94,"Tipo",F104)/GETPIVOTDATA(" Cantidad",TD!$A$3,"Proceso",$E$94,"ORD",$D$94,"Tipo","Producción")*-1,0) -> 0 | H104: =IFERROR(GETPIVOTDATA("Suma de Costo",TD!$A$3,"Proceso",$E$94,"ORD",$D$94,"Tipo",F104),0) -> 0 | I104: =H104*G104 -> 0 | M104: Dosificador de Sal | N104: 0 | O104: 0 | P104: =N104*O104 -> 0 | R104: =+(O104-H104)*N104 -> 0 | S104: =+(N104-G104)*H104 -> 0 | T104: =+P104-I104 -> 0 | Y104: CV POND CEM P2025 | Z104: 127923.08
F105: Yeso | G105: =IFERROR(GETPIVOTDATA(" Cantidad",TD!$A$3,"Proceso",$E$94,"ORD",$D$94,"Tipo",F105)/GETPIVOTDATA(" Cantidad",TD!$A$3,"Proceso",$E$94,"ORD",$D$94,"Tipo","Producción")*-1,0) -> 0.0790452 | H105: =+H89 -> 232625.89 | I105: =H105*G105 -> 18387.96 | M105: Yeso | N105: 0.082426671 | O105: 220009.06 | P105: =N105*O105 -> 18134.614 | R105: =+(O105-H105)*N105 -> -1039.9638 | S105: =+(N105-G105)*H105 -> 786.61769 | T105: =+P105-I105 -> -253.34613 | Y105: CV POND CEM R2025 | Z105: =((P114*P115)+(P122*P123)+(P130*P131)+(P138*P139)+(P146*P147)+(P196*P197)+(P203*P204)+(P210*P211))/(P115+P123+P131+P139+P147+P197+P204+P211) -> 129090.1
E106: Total Cemento ART | I106: =SUM(I94:I105) -> 143400.48 | L106: Total Cemento ART | P106: =SUM(P94:P105) -> 135436.71 | R106: =+SUM(R94:R105) -> -10067.358 | S106: =+SUM(S94:S105) -> 2290.4637 | T106: =+SUM(T94:T105) -> -7776.8944 | Y106: P2026 vs P2025 | Z106: =Z103-Z104 -> 7561.0035
I107: =IFERROR(GETPIVOTDATA(" Cantidad",TD!$A$3,"Proceso",E94,"ORD",D94,"Tipo","Producción")*-1,0) -> 440847.09 | P107: 420766.62 | Y107: P2026 vs R2025 | Z107: =Z103-Z105 -> 6393.9778
D109: ORD 6 | E109: Proceso | F109: Tipo | G109: Consumo | H109: Costo | I109: Total | K109: ORD 6 | L109: Proceso | M109: Tipo | N109: Consumo | O109: Costo | P109: Total | R109: VP | S109: VC | T109: Total
D110: 8 | E110: Cemento UG 50 KG | F110: Cemento a Granel | G110: =+GETPIVOTDATA(" Cantidad",TD!$A$3,"Proceso","CEMENTO UG 50 KG","ORD",8,"Tipo","Cemento UG")/I115 -> 1 | H110: =+I90 -> 100484.39 | I110: =H110*G110 -> 100484.39 | K110: 8 | L110: Cemento UG 50 KG | M110: Cemento a Granel | N110: 1.0000005 | O110: =+P90 -> 95900.546 | P110: =N110*O110 -> 95900.591 | R110: =+(O110-H110)*N110 -> -4583.8453 | S110: =+(N110-G110)*H110 -> 0.046626674 | T110: =+P110-I110 -> -4583.7987
...

Sheet Costo Arrastrado
Y1: Costo Arrastrado por tipo de Cemento
C2: CLINKER | D2: PRESUPUESTO | J2: CLINKER | K2: REAL | O2: VARIACIONES | Z2: REAL | AC2: PPTO | AH2: Costo Resumido hasta Clinker
C3: Tipo | D3: Consumo | E3: Costo | F3: Total | J3: Tipo | K3: Consumo | L3: Costo | M3: Total | N3: Bridge | O3: VP | P3: VC | Q3: Total | Y3: Tipo | Z3: UG | AA3: ART | AB3: FIBRO | AC3: UG | AD3: ART | AE3: FIBRO | AH3: Materias Primas | AI3: =F4+F5+F10+F6 -> 33222.491
C4: Arcilla | D4: =(Costo!G7*Costo!G28*Costo!G62) -> 0.26964134 | E4: =Costo!H7 -> 10623.146 | F4: =+E4*D4 -> 2864.4394 | J4: Arcilla | K4: =(Costo!N7*Costo!N28*Costo!N62) -> 0.30229774 | L4: =Costo!O7 -> 10136.59 | M4: =+L4*K4 -> 3064.2683 | N4: =+M4-F4 -> 199.82884 | O4: =+(L4-E4)*K4 -> -147.08488 | P4: =+(K4-D4)*E4 -> 346.91371 | Q4: =+P4+O4 -> 199.82884 | R4: =+Q4/3900 -> 0.051238163 | S4: 25440.014 | Y4: Arcilla | Z4: =F4*$D$22 -> 1489.5085 | AA4: =F4*$D$38 -> 2377.4847 | AB4: =F4*$D$54 -> 2618.0976 | AC4: =M4*$K$22 -> 1639.1178 | AD4: =M4*$K$38 -> 2557.7519 | AE4: =M4*$K$54 -> 2798.8141 | AH4: Energía | AI4: =F9 -> 31270.165
C5: Caliza | D5: =Costo!G8*Costo!G28*Costo!G62+Costo!G29*Costo!G62 -> 1.3123887 | E5: =(Costo!G8*Costo!G28*Costo!G62/(Costo!G8*Costo!G28*Costo!G62+Costo!G29*Costo!G62))*Costo!H8+(Costo!G29*Costo!G62/(Costo!G8*Costo!G28*Costo!G62+Costo!G29*Costo!G62))*Costo!H18 -> 13978.132 | F5: =+E5*D5 -> 18344.742 | J5: Caliza | K5: =Costo!N8*Costo!N28*Costo!N62+Costo!N29*Costo!N62 -> 1.2778077 | L5: =(Costo!N8*Costo!N28*Costo!N62/(Costo!N8*Costo!N28*Costo!N62+Costo!N29*Costo!N62))*Costo!O8+(Costo!N29*Costo!N62/(Costo!N8*Costo!N28*Costo!N62+Costo!N29*Costo!N62))*Costo!O18 -> 13426.725 | M5: =+L5*K5 -> 17156.772 | N5: =+M5-F5 -> -1187.9704 | O5: =+(L5-E5)*K5 -> -704.59188 | P5: =+(K5-D5)*E5 -> -483.37848 | Q5: =+P5+O5 -> -1187.9704 | R5: =+Q5/3900 -> -0.30460778 | S5: 104500.28 | Y5: Caliza | Z5: =F5*$D$22 -> 9539.266 | AA5: =F5*$D$38 -> 15226.136 | AB5: =F5*$D$54 -> 16767.095 | AC5: =M5*$K$22 -> 9177.3854 | AD5: =M5*$K$38 -> 14320.798 | AE5: =M5*$K$54 -> 15670.5 | AH5: Combustibles | AI5: =F11+F14+F12 -> 48799.726
C6: Material Dique | D6: =Costo!G11*Costo!G28*Costo!G62+Costo!G20*Costo!G29*Costo!G62 -> 1.5820301 | E6: =+Costo!I11 -> 369.16354 | F6: =+E6*D6 -> 584.02782 | J6: Material Dique | K6: =Costo!N11*Costo!N28*Costo!N62+Costo!N20*Costo!N29*Costo!N62 -> 0 | L6: =+Costo!P11 -> 0 | M6: =+L6*K6 -> 0 | O6: =+(L6-E6)*K6 -> 0 | P6: =+(K6-D6)*E6 -> -584.02782 | Q6: =+P6+O6 -> -584.02782 | Y6: Material Dique | Z6: =F6*$D$22 -> 303.69447 | AA6: =F6*$D$38 -> 484.74309 | AB6: =F6*$D$54 -> 533.80143 | AC6: =M6*$K$22 -> 0 | AD6: =M6*$K$38 -> 0 | AE6: =M6*$K$54 -> 0 | AH6: Otros | AI6: =F7+F8+F13 -> 447.23365
C7: Regalías | D7: =Costo!G13 -> 1 | E7: =Costo!I13*Costo!G28*Costo!G62+Costo!I22*Costo!G29*Costo!G62 -> 231.48671 | F7: =+E7*D7 -> 231.48671 | J7: Regalías | K7: =Costo!N13 -> 1 | L7: =Costo!P13*Costo!N28*Costo!N62+Costo!P22*Costo!N29*Costo!N62 -> 225.43512 | M7: =+L7*K7 -> 225.43512 | N7: =+M7-F7 -> -6.051593 | O7: =+(L7-E7)*K7 -> -6.051593 | P7: =+(K7-D7)*E7 -> 0 | Q7: =+P7+O7 -> -6.051593 | R7: =+Q7/3900 -> -0.0015516905 | S7: =+S5/M18 -> 0.11777129 | Y7: Regalías | Z7: =F7*$D$22 -> 120.37309 | AA7: =F7*$D$38 -> 192.13397 | AB7: =F7*$D$54 -> 211.57885 | AC7: =M7*$K$22 -> 120.58824 | AD7: =M7*$K$38 -> 188.17122 | AE7: =M7*$K$54 -> 205.90592 | AH7: Variables de Mtto | AI7: =+F15+F16 -> 8125.5999
C8: Desmantelamiento | D8: 1 | E8: =Costo!I12*Costo!G28*Costo!G62+Costo!I21*Costo!G29*Costo!G62 -> 0 | F8: =+E8*D8 -> 0 | J8: Desmantelamiento | K8: 1 | L8: =Costo!P12*Costo!N28*Costo!N62+Costo!P21*Costo!N29*Costo!N62 -> 0 | M8: =+L8*K8 -> 0 | O8: =+(L8-E8)*K8 -> 0 | P8: =+(K8-D8)*E8 -> 0 | Q8: =+P8+O8 -> 0 | Y8: Desmantelamiento | Z8: =F8*$D$22 -> 0 | AA8: =F8*$D$38 -> 0 | AB8: =F8*$D$54 -> 0 | AC8: =M8*$K$22 -> 0 | AD8: =M8*$K$38 -> 0 | AE8: =M8*$K$54 -> 0 | AH8: TOTALES | AI8: =SUM(AI3:AI7) -> 121865.22
C9: Energía | D9: =Costo!G9*Costo!G28*Costo!G62+Costo!G33*Costo!G62+Costo!G44*Costo!G63+Costo!G56*Costo!G64+Costo!G66+Costo!G23*Costo!G29*Costo!G62 -> 59.545887 | E9: =Costo!H9 -> 525.144 | F9: =+E9*D9 -> 31270.165 | J9: Energía | K9: =Costo!N9*Costo!N28*Costo!N62+Costo!N33*Costo!N62+Costo!N44*Costo!N63+Costo!N56*Costo!N64+Costo!N66+Costo!N23*Costo!N29*Costo!N62 -> 62.326911 | L9: =Costo!O9 -> 485.33891 | M9: =+L9*K9 -> 30249.675 | N9: =+M9-F9 -> -1020.4896 | O9: =+(L9-E9)*K9 -> -2480.9279 | P9: =+(K9-D9)*E9 -> 1460.4383 | Q9: =+P9+O9 -> -1020.4896 | R9: =+Q9/3900 -> -0.261664 | Y9: Energía | Z9: =F9*$D$22 -> 16260.486 | AA9: =F9*$D$38 -> 25954.237 | AB9: =F9*$D$54 -> 28580.931 | AC9: =M9*$K$22 -> 16180.953 | AD9: =M9*$K$38 -> 25249.474 | AE9: =M9*$K$54 -> 27629.179
C10: Mineral de Hierro | D10: =Costo!G35*Costo!G62 -> 0.040549372 | E10: =Costo!H35 -> 281860.87 | F10: =+E10*D10 -> 11429.281 | J10: Mineral de Hierro | K10: =Costo!N35*Costo!N62 -> 0.03964726 | L10: =Costo!O35 -> 256211.07 | M10: =+L10*K10 -> 10158.067 | N10: =+M10-F10 -> -1271.2147 | O10: =+(L10-E10)*K10 -> -1016.9445 | P10: =+(K10-D10)*E10 -> -254.27018 | Q10: =+P10+O10 -> -1271.2147 | R10: =+Q10/3900 -> -0.32595248 | Y10: Mineral de Hierro | Z10: =F10*$D$22 -> 5943.2263 | AA10: =F10*$D$38 -> 9486.3036 | AB10: =F10*$D$54 -> 10446.363 | AC10: =M10*$K$22 -> 5433.6849 | AD10: =M10*$K$38 -> 8478.962 | AE10: =M10*$K$54 -> 9278.0846
C11: Carbón | D11: =Costo!G63 -> 0.11141634 | E11: =Costo!I45-Costo!I44-Costo!I43 -> 371824.76 | F11: =+E11*D11 -> 41427.354 | J11: Carbón | K11: =Costo!N63 -> 0.13154945 | L11: =Costo!P45-Costo!P44-Costo!P43 -> 284619.13 | M11: =+L11*K11 -> 37441.491 | N11: =+M11-F11 -> -3985.863 | O11: =+(L11-E11)*K11 -> -11471.852 | P11: =+(K11-D11)*E11 -> 7485.9892 | Q11: =M11-F11 -> -3985.863 | R11: =+Q11/3900 -> -1.0220162 | Y11: Carbón | Z11: =F11*$D$22 -> 21542.224 | AA11: =F11*$D$38 -> 34384.704 | AB11: =F11*$D$54 -> 37864.602 | AC11: =M11*$K$22 -> 20027.951 | AD11: =M11*$K$38 -> 31252.5 | AE11: =M11*$K$54 -> 34197.976
C12: Alternos | D12: =Costo!G64 -> 0.01917273 | E12: =Costo!H64-Costo!I56 -> 337758.95 | F12: =+E12*D12 -> 6475.761 | J12: Alternos | K12: =Costo!N64 -> 0.016480649 | L12: =Costo!O64-Costo!P56 -> 322974.11 | M12: =+L12*K12 -> 5322.8228 | O12: =+(L12-E12)*K12 -> -243.66375 | P12: =Q12-O12 -> -909.27447 | Q12: =M12-F12 -> -1152.9382 | Y12: Alternos | Z12: =F12*$D$22 -> 3367.3957 | AA12: =F12*$D$38 -> 5374.8817 | AB12: =F12*$D$54 -> 5918.8456 | AC12: =M12*$K$22 -> 2847.2487 | AD12: =M12*$K$38 -> 4442.9726 | AE12: =M12*$K$54 -> 4861.7125
C13: Cargue Ck | D13: 1 | E13: =Costo!I67+Costo!I70 -> 215.74694 | F13: =+E13*D13 -> 215.74694 | J13: Cargue Ck | K13: 1 | L13: =Costo!P67+Costo!P70 -> 303.38393 | M13: =+L13*K13 -> 303.38393 | O13: =+(L13-E13)*K13 -> 87.636993 | P13: =Q13-O13 -> 0 | Q13: =M13-F13 -> 87.636993 | Y13: Cargue Ck | Z13: =F13*$D$22 -> 112.18841 | AA13: =F13*$D$38 -> 179.06996 | AB13: =F13*$D$54 -> 197.1927 | AC13: =M13*$K$22 -> 162.2841 | AD13: =M13*$K$38 -> 253.23527 | AE13: =M13*$K$54 -> 277.10211
C14: Gasoil | D14: =Costo!G71 -> 0.074717554 | E14: =Costo!H71 -> 12000 | F14: =+E14*D14 -> 896.61065 | J14: Gasoil | K14: =Costo!N71 -> 0.12853227 | L14: =Costo!O71 -> 8663.0042 | M14: =+L14*K14 -> 1113.4756 | N14: =+M14-F14 -> 216.86495 | O14: =+(L14-E14)*K14 -> -428.91164 | P14: =+(K14-D14)*E14 -> 645.7766 | Q14: =+P14+O14 -> 216.86495 | R14: =+Q14/3900 -> 0.055606398 | Y14: Gasoil | Z14: =F14*$D$22 -> 466.23754 | AA14: =F14*$D$38 -> 744.18684 | AB14: =F14*$D$54 -> 819.50214 | AC14: =M14*$K$22 -> 595.6129 | AD14: =M14*$K$38 -> 929.42068 | AE14: =M14*$K$54 -> 1017.0164
C15: Refractarios | D15: 1 | E15: =(Costo!I73*Costo!I75)/F18 -> 3600.6055 | F15: =+E15*D15 -> 3600.6055 | J15: Refractarios | K15: 1 | L15: =(Costo!P73*Costo!P75)/M18 -> 3021.5659 | M15: =+L15*K15 -> 3021.5659 | N15: =+M15-F15 -> -579.03961 | O15: =+(L15-E15)*K15 -> -579.03961 | P15: =+(K15-D15)*E15 -> 0 | Q15: =+P15+O15 -> -579.03961 | R15: =+Q15/3900 -> -0.14847169 | Y15: Refractarios | Z15: =F15*$D$22 -> 1872.3149 | AA15: =F15*$D$38 -> 2988.5026 | AB15: =F15*$D$54 -> 3290.9535 | AC15: =M15*$K$22 -> 1616.2758 | AD15: =M15*$K$38 -> 2522.1081 | AE15: =M15*$K$54 -> 2759.811
C16: Var Mtto | D16: 1 | E16: =(Costo!I10*Costo!G28*Costo!G62)+(Costo!I19*Costo!G29*Costo!G62)+((Costo!I30+Costo!I31+Costo!I32)*Costo!G62)+(Costo!I43*Costo!G63)+(Costo!I57*Costo!G64)+(Costo!I65+Costo!I68+Costo!I69+Costo!I72) -> 4524.9944 | F16: =+E16*D16 -> 4524.9944 | J16: Var Mtto | K16: 1 | L16: =(Costo!P10*Costo!N28*Costo!N62)+(Costo!P19*Costo!N29*Costo!N62)+((Costo!P30+Costo!P31+Costo!P32)*Costo!N62)+(Costo!P43*Costo!N63)+(Costo!P57*Costo!N64)+(Costo!P65+Costo!P68+Costo!P69+Costo!P72) -> 5406.0256 | M16: =+L16*K16 -> 5406.0256 | N16: =+M16-F16 -> 881.03116 | O16: =+(L16-E16)*K16 -> 881.03116 | P16: =+(K16-D16)*E16 -> 0 | Q16: =+P16+O16 -> 881.03116 | R16: =+Q16/3900 -> 0.22590543 | Y16: Var Mtto | Z16: =F16*$D$22 -> 2352.9971 | AA16: =F16*$D$38 -> 3755.7454 | AB16: =F16*$D$54 -> 4135.8449 | AC16: =M16*$K$22 -> 2891.7549 | AD16: =M16*$K$38 -> 4512.4221 | AE16: =M16*$K$54 -> 4937.7075
C17: Total | F17: =SUM(F4:F16) -> 121865.22 | M17: =SUM(M4:M16) -> 113462.98 | N17: =+M17-F17 -> -8402.233 | O17: =+SUM(O4:O16) -> -16110.4 | P17: =+SUM(P4:P16) -> 7708.1669 | Q17: =+SUM(Q4:Q16) -> -8402.233 | R17: =+Q17/3900 -> -2.1544187 | S17: 26458.131 | Y17: TOTALES | Z17: =SUM(Z4:Z16) -> 63369.912 | AA17: =SUM(AA4:AA16) -> 101148.13 | AB17: =SUM(AB4:AB16) -> 111384.81 | AC17: =SUM(AC4:AC16) -> 60692.857 | AD17: =SUM(AD4:AD16) -> 94707.816 | AE17: =SUM(AE4:AE16) -> 103633.81
C18: Pcc | F18: =Costo!I75 -> 856559.09 | M18: =Costo!P75 -> 887315.43
Y19: Arcillas y Calizas
C20: CEMENTO UG | D20: PRESUPUESTO | J20: CEMENTO UG | K20: REAL | O20: VARIACIONES
C21: Tipo | D21: Consumo | E21: Costo | F21: Total | J21: Tipo | K21: Consumo | L21: Costo | M21: Total | O21: VP | P21: VC | Q21: Total | S21: =+F10*F18 -> 9.7898549e+09 | Y21: Arcillas en Ck | Z21: =(Costo!G7*Costo!G28*Costo!G62)*Costo!I75 -> 230963.74 | AA21: Arcillas
C22: Clinker | D22: =Costo!G78 -> 0.52 | E22: =Costo!H78 -> 121865.27 | F22: =E22*D22 -> 63369.941 | J22: Clinker | K22: =Costo!N78 -> 0.53491329 | L22: =Costo!O78 -> 113462.98 | M22: =L22*K22 -> 60692.857 | N22: =+M22-F22 -> -2677.0831 | O22: =+(L22-E22)*K22 -> -4494.4955 | P22: =+(K22-D22)*E22 -> 1817.4124 | Q22: =+P22+O22 -> -2677.0831 | R22: =+Q22/3900 -> -0.68643156 | S22: =+F11*F18 -> 3.5484977e+10 | Y22: Arcillas en Cem | Z22: =(Costo!G78*Costo!I91+Costo!G94*Costo!I107+Costo!G159*Costo!I168)/SUM(Costo!I91+Costo!I107+Costo!I168)*Z21 -> 146743.08
C23: Caliza Triturada | D23: =Costo!G79 -> 0.38784 | E23: =Costo!H79 -> 16036.454 | F23: =E23*D23 -> 6219.5783 | J23: Caliza Triturada | K23: =Costo!N79 -> 0.37435214 | L23: =Costo!O79 -> 15086.891 | M23: =L23*K23 -> 5647.8098 | N23: =+M23-F23 -> -571.76847 | O23: =+(L23-E23)*K23 -> -355.47103 | P23: =+(K23-D23)*E23 -> -216.29745 | Q23: =+P23+O23 -> -571.76847 | R23: =+Q23/3900 -> -0.1466073 | S23: =+F27*F34 -> 1.2708349e+09 | Y23: Calizas en Ck | Z23: =(Costo!G8*Costo!G28*Costo!G62)*Costo!I75+(Costo!G18*Costo!G29*Costo!G62)*Costo!I75 -> 1124138.5 | AA23: Calizas para Clinker
C24: Aditivo Molienta | D24: =Costo!G80 -> 0.0005 | E24: =Costo!H80 -> 4396360 | F24: =E24*D24 -> 2198.18 | J24: Aditivo Molienta | K24: =Costo!N80 -> 0.00050303889 | L24: =Costo!O80 -> 4014954.5 | M24: =L24*K24 -> 2019.6782 | O24: =+(L24-E24)*K24 -> -191.86182 | P24: =+(K24-D24)*E24 -> 13.360052 | Q24: =+P24+O24 -> -178.50177 | Y24: Calizas Totales hasta Cem | Z24: =(Costo!G78*Costo!I91+Costo!G94*Costo!I107+Costo!G159*Costo!I168)/SUM(Costo!I91+Costo!I107+Costo!I168)*Z23+(Costo!G79*Costo!I91+Costo!G95*Costo!I107+Costo!G160*Costo!I168) -> 1061778.2
C25: Puzolana | D25: =Costo!G81 -> 0.03 | E25: =Costo!H81 -> 105080.05 | F25: =E25*D25 -> 3152.4016 | J25: Puzolana | K25: =Costo!N81 -> 0.028487188 | L25: =Costo!O81 -> 109078.76 | M25: =L25*K25 -> 3107.347 | O25: =+(L25-E25)*K25 -> 113.91183 | P25: =+(K25-D25)*E25 -> -158.96642 | Q25: =+P25+O25 -> -45.054589 | Y25: Calizas solo cem | Z25: =(Costo!G79*Costo!I91+Costo!G95*Costo!I107+Costo!G160*Costo!I168) -> 347555.55 | AA25: Calizas para Cemento
C26: Finos Filtro | D26: =Costo!G82 -> 0.03015 | E26: =Costo!H82 -> 31752.892 | F26: =E26*D26 -> 957.3497 | J26: Finos Filtro | K26: =Costo!N82 -> 0.02494618 | L26: =Costo!O82 -> 29052.956 | M26: =L26*K26 -> 724.76027 | O26: =+(L26-E26)*K26 -> -67.353084 | P26: =+(K26-D26)*E26 -> -165.23634 | Q26: =+P26+O26 -> -232.58943
A27: =A23*840000 -> 0 | C27: Variables Mtto | D27: =Costo!G84 -> 1 | E27: =Costo!H84 -> 1539.637 | F27: =E27*D27 -> 1539.637 | J27: Variables Mtto | K27: =Costo!N84 -> 1 | L27: =Costo!O84 -> 1117.2996 | M27: =L27*K27 -> 1117.2996 | N27: =+M27-F27 -> -422.33738 | O27: =+(L27-E27)*K27 -> -422.33738 | P27: =+(K27-D27)*E27 -> 0 | Q27: =+P27+O27 -> -422.33738 | R27: =+Q27/3900 -> -0.10829164 | S27: =+F43*F50 -> 6.7874448e+08
C28: Energía | D28: =Costo!G85 -> 25.7 | E28: =Costo!H85 -> 525.28045 | F28: =E28*D28 -> 13499.708 | J28: Energía | K28: =Costo!N85 -> 26.405728 | L28: =Costo!O85 -> 485.33891 | M28: =L28*K28 -> 12815.727 | O28: =+(L28-E28)*K28 -> -1054.6854 | P28: =+(K28-D28)*E28 -> 370.70521 | Q28: =+P28+O28 -> -683.98017
C29: Gasoil | D29: =Costo!G86 -> 1 | E29: =Costo!H86 -> 0 | F29: =E29*D29 -> 0 | J29: Gasoil | K29: =Costo!N86 -> 0 | L29: =Costo!O86 -> 0 | M29: =L29*K29 -> 0 | N29: =+M29-F29 -> 0 | O29: =+(L29-E29)*K29 -> 0 | P29: =+(K29-D29)*E29 -> 0 | Q29: =+P29+O29 -> 0 | R29: =+Q29/3900 -> 0 | S29: #REF!
C30: Sal Marina | D30: =Costo!G87 -> 0 | E30: =Costo!H87 -> 0 | F30: =E30*D30 -> 0 | J30: Sal Marina | K30: =Costo!N87 -> 0 | L30: =Costo!O87 -> 0 | M30: =L30*K30 -> 0 | O30: =+(L30-E30)*K30 -> 0 | P30: =+(K30-D30)*E30 -> 0 | Q30: =+P30+O30 -> 0
C31: Dosificador Sal | D31: =Costo!G88 -> 0 | E31: =Costo!H88 -> 0 | F31: =E31*D31 -> 0 | J31: Dosificador Sal | K31: =Costo!N88 -> 0 | L31: =Costo!O88 -> 0 | M31: =L31*K31 -> 0 | O31: =+(L31-E31)*K31 -> 0 | P31: =+(K31-D31)*E31 -> 0 | Q31: =+P31+O31 -> 0
C32: Yeso | D32: =Costo!G89 -> 0.0410427 | E32: =Costo!H89 -> 232625.89 | F32: =E32*D32 -> 9547.5948 | J32: Yeso | K32: =Costo!N89 -> 0.044430291 | L32: =Costo!O89 -> 220009.06 | M32: =L32*K32 -> 9775.0665 | N32: =+M32-F32 -> 227.47173 | O32: =+(L32-E32)*K32 -> -560.56972 | P32: =+(K32-D32)*E32 -> 788.04144 | Q32: =+P32+O32 -> 227.47173 | R32: =+Q32/3900 -> 0.058326084 | S32: #REF!
C33: Total | F33: =SUM(F22:F32) -> 100484.39 | M33: =SUM(M22:M32) -> 95900.546 | N33: =+M33-F33 -> -4583.8432 | O33: =+SUM(O22:O32) -> -7032.862 | P33: =+SUM(P22:P32) -> 2449.0189 | Q33: =+SUM(Q22:Q32) -> -4583.8432 | R33: =+Q33/3900 -> -1.1753444 | S33: #REF!
C34: Pcc | F34: =Costo!I91 -> 825412.03 | M34: =Costo!P91 -> 770686.4 | S34: #REF!
S35: #REF!
C36: CEMENTO ART | D36: PRESUPUESTO | J36: CEMENTO ART | K36: REAL | O36: VARIACIONES
C37: Tipo | D37: Consumo | E37: Costo | F37: Total | J37: Tipo | K37: Consumo | L37: Costo | M37: Total | O37: VP | P37: VC | Q37: Total
C38: Clinker | D38: =Costo!G94 -> 0.83 | E38: =Costo!H94 -> 121865.27 | F38: =E38*D38 -> 101148.17 | J38: Clinker | K38: =Costo!N94 -> 0.83470233 | L38: =Costo!O94 -> 113462.98 | M38: =L38*K38 -> 94707.816 | N38: =+M38-F38 -> -6440.3588 | O38: =+(L38-E38)*K38 -> -7013.4092 | P38: =+(K38-D38)*E38 -> 573.05042 | Q38: =+P38+O38 -> -6440.3588 | R38: =+Q38/3900 -> -1.6513741
C39: Caliza Triturada | D39: =Costo!G95 -> 0.062216 | E39: =Costo!H95 -> 16036.454 | F39: =E39*D39 -> 997.72402 | J39: Caliza Triturada | K39: =Costo!N95 -> 0.06114641 | L39: =Costo!O95 -> 15086.891 | M39: =L39*K39 -> 922.5092 | N39: =+M39-F39 -> -75.21482 | O39: =+(L39-E39)*K39 -> -58.062382 | P39: =+(K39-D39)*E39 -> -17.152438 | Q39: =+P39+O39 -> -75.21482 | R39: =+Q39/3900 -> -0.019285851
C40: Aditivo Molienta | D40: =Costo!G96 -> 0.0005 | E40: =Costo!H96 -> 4396360 | F40: =E40*D40 -> 2198.18 | J40: Aditivo Molienta | K40: =Costo!N96 -> 0.00050095345 | L40: =Costo!O96 -> 4014954.5 | M40: =L40*K40 -> 2011.3053 | O40: =+(L40-E40)*K40 -> -191.06643 | P40: =+(K40-D40)*E40 -> 4.1917278 | Q40: =+P40+O40 -> -186.8747
C41: Puzolana | D41: =Costo!G97 -> 0 | E41: =Costo!H97 -> 0 | F41: =E41*D41 -> 0 | J41: Puzolana | M41: =L41*K41 -> 0 | O41: =+(L41-E41)*K41 -> 0 | P41: =+(K41-D41)*E41 -> 0 | Q41: =+P41+O41 -> 0
C42: Finos Filtro | D42: =Costo!G98 -> 0.0300495 | E42: =Costo!H98 -> 31752.892 | F42: =E42*D42 -> 954.15853 | J42: Finos Filtro | K42: =Costo!N98 -> 0.024630431 | L42: =Costo!O98 -> 29052.956 | M42: =L42*K42 -> 715.58684 | O42: =+(L42-E42)*K42 -> -66.500583 | P42: =+(K42-D42)*E42 -> -172.07111 | Q42: =+P42+O42 -> -238.57169
C43: Variables Mtto | D43: =Costo!G100 -> 1 | E43: =Costo!H100 -> 1539.637 | F43: =E43*D43 -> 1539.637 | J43: Variables Mtto | K43: =Costo!N100 -> 1 | L43: =Costo!O100 -> 1117.2996 | M43: =L43*K43 -> 1117.2996 | N43: =+M43-F43 -> -422.33738 | O43: =+(L43-E43)*K43 -> -422.33738 | P43: =+(K43-D43)*E43 -> 0 | Q43: =+P43+O43 -> -422.33738 | R43: =+Q43/3900 -> -0.10829164
C44: Energía | D44: =Costo!G101 -> 34.6 | E44: =Costo!H101 -> 525.27889 | F44: =E44*D44 -> 18174.65 | J44: Energía | K44: =Costo!N101 -> 36.732237 | L44: =Costo!O101 -> 485.33891 | M44: =L44*K44 -> 17827.584 | O44: =+(L44-E44)*K44 -> -1467.0847 | P44: =+(K44-D44)*E44 -> 1120.0192 | Q44: =+P44+O44 -> -347.06556
C45: Gasoil | D45: =Costo!G102 -> 1 | E45: =Costo!H102 -> 0 | F45: =E45*D45 -> 0 | J45: Gasoil | K45: =Costo!N102 -> 0 | L45: =Costo!O102 -> 0 | M45: =L45*K45 -> 0 | N45: =+M45-F45 -> 0 | O45: =+(L45-E45)*K45 -> 0 | P45: =+(K45-D45)*E45 -> 0 | Q45: =+P45+O45 -> 0 | R45: =+Q45/3900 -> 0
C46: Sal Marina | D46: =Costo!G103 -> 0 | E46: =Costo!H103 -> 0 | F46: =E46*D46 -> 0 | J46: Sal Marina | K46: =Costo!N103 -> 0 | L46: =Costo!O103 -> 0 | M46: =L46*K46 -> 0 | O46: =+(L46-E46)*K46 -> 0 | P46: =+(K46-D46)*E46 -> 0 | Q46: =+P46+O46 -> 0
C47: Dosificador Sal | D47: =Costo!G104 -> 0 | E47: =Costo!H104 -> 0 | F47: =E47*D47 -> 0 | J47: Dosificador Sal | K47: =Costo!N104 -> 0 | L47: =Costo!O104 -> 0 | M47: =L47*K47 -> 0 | O47: =+(L47-E47)*K47 -> 0 | P47: =+(K47-D47)*E47 -> 0 | Q47: =+P47+O47 -> 0
C48: Yeso | D48: =Costo!G105 -> 0.0790452 | E48: =Costo!H105 -> 232625.89 | F48: =E48*D48 -> 18387.96 | J48: Yeso | K48: =Costo!N105 -> 0.082426671 | L48: =Costo!O105 -> 220009.06 | M48: =L48*K48 -> 18134.614 | N48: =+M48-F48 -> -253.34613 | O48: =+(L48-E48)*K48 -> -1039.9638 | P48: =+(K48-D48)*E48 -> 786.61769 | Q48: =+P48+O48 -> -253.34613 | R48: =+Q48/3900 -> -0.064960545
C49: Total | F49: =SUM(F38:F48) -> 143400.48 | M49: =SUM(M38:M48) -> 135436.71 | N49: =+M49-F49 -> -7963.7691 | O49: =+SUM(O38:O48) -> -10258.425 | P49: =+SUM(P38:P48) -> 2294.6554 | Q49: =+SUM(Q38:Q48) -> -7963.7691 | R49: =+Q49/3900 -> -2.0419921
C50: Pcc | F50: =Costo!I107 -> 440847.09 | M50: =Costo!P107 -> 420766.62 | N50: =+M50-F50 -> -20080.468
C52: CEMENTO FIBROCEMENTO | D52: PRESUPUESTO | J52: CEMENTO FIBROCEMENTO | K52: REAL | O52: VARIACIONES
C53: Tipo | D53: Consumo | E53: Costo | F53: Total | J53: Tipo | K53: Consumo | L53: Costo | M53: Total | O53: VP | P53: VC | Q53: Total
C54: Clinker | D54: =Costo!G159 -> 0.914 | E54: =Costo!H159 -> 121865.27 | F54: =E54*D54 -> 111384.86 | J54: Clinker | K54: =Costo!N159 -> 0.9133711 | L54: =Costo!O159 -> 113462.98 | M54: =L54*K54 -> 103633.81 | N54: =+M54-F54 -> -7751.0484 | O54: =+(L54-E54)*K54 -> -7674.4069 | P54: =+(K54-D54)*E54 -> -76.641508 | Q54: =+P54+O54 -> -7751.0484
C55: Caliza Triturada | D55: =Costo!G160 -> 0 | E55: =Costo!H160 -> 16036.454 | F55: =E55*D55 -> 0 | J55: Caliza Triturada | K55: =Costo!N160 -> 0.0011071999 | L55: =Costo!O160 -> 15086.891 | M55: =L55*K55 -> 16.704204 | N55: =+M55-F55 -> 16.704204 | O55: =+(L55-E55)*K55 -> -1.0513563 | P55: =+(K55-D55)*E55 -> 17.75556 | Q55: =+P55+O55 -> 16.704204
C56: Aditivo Molienta | D56: 0 | E56: 0 | F56: =E56*D56 -> 0 | J56: Aditivo Molienta | K56: 0 | L56: 0 | M56: =L56*K56 -> 0 | O56: =+(L56-E56)*K56 -> 0 | P56: =+(K56-D56)*E56 -> 0 | Q56: =+P56+O56 -> 0
C57: Puzolana | D57: 0 | E57: 0 | F57: =E57*D57 -> 0 | J57: Puzolana | K57: 0 | L57: 0 | M57: =L57*K57 -> 0 | O57: =+(L57-E57)*K57 -> 0 | P57: =+(K57-D57)*E57 -> 0 | Q57: =+P57+O57 -> 0
C58: Finos Filtro | D58: =Costo!G161 -> 0 | E58: =Costo!H161 -> 31752.892 | F58: =E58*D58 -> 0 | J58: Finos Filtro | K58: =Costo!N161 -> 0.0014778303 | L58: =Costo!O161 -> 29052.956 | M58: =L58*K58 -> 42.935341 | N58: =+M58-F58 -> 42.935341 | O58: =+(L58-E58)*K58 -> -3.9900471 | P58: =+(K58-D58)*E58 -> 46.925388 | Q58: =+P58+O58 -> 42.935341
C59: Variables Mtto | D59: =Costo!G163 -> 1 | E59: =Costo!H163 -> 1539.637 | F59: =E59*D59 -> 1539.637 | J59: Variables Mtto | K59: =Costo!N163 -> 1 | L59: =Costo!O163 -> 1117.2996 | M59: =L59*K59 -> 1117.2996 | N59: =+M59-F59 -> -422.33738 | O59: =+(L59-E59)*K59 -> -422.33738 | P59: =+(K59-D59)*E59 -> 0 | Q59: =+P59+O59 -> -422.33738
C60: Energía | D60: =Costo!G164 -> 34.6 | E60: =Costo!H164 -> 525.24404 | F60: =E60*D60 -> 18173.444 | J60: Energía | K60: =Costo!N164 -> 35.488842 | L60: =Costo!O164 -> 485.33891 | M60: =L60*K60 -> 17224.116 | O60: =+(L60-E60)*K60 -> -1416.1868 | P60: =+(K60-D60)*E60 -> 466.85872 | Q60: =+P60+O60 -> -949.32811
C61: Gasoil | D61: =Costo!G165 -> 1 | E61: =Costo!H165 -> 0 | F61: =E61*D61 -> 0 | J61: Gasoil | K61: =Costo!N165 -> 0 | L61: =Costo!O165 -> 0 | M61: =L61*K61 -> 0 | N61: =+M61-F61 -> 0 | O61: =+(L61-E61)*K61 -> 0 | P61: =+(K61-D61)*E61 -> 0 | Q61: =+P61+O61 -> 0
C62: Sal Marina | D62: 0 | E62: 0 | F62: =E62*D62 -> 0 | J62: Sal Marina | K62: 0 | L62: 0 | M62: =L62*K62 -> 0 | O62: =+(L62-E62)*K62 -> 0 | P62: =+(K62-D62)*E62 -> 0 | Q62: =+P62+O62 -> 0
C63: Dosificador Sal | D63: 0 | E63: 0 | F63: =E63*D63 -> 0 | J63: Dosificador Sal | K63: 0 | L63: 0 | M63: =L63*K63 -> 0 | O63: =+(L63-E63)*K63 -> 0 | P63: =+(K63-D63)*E63 -> 0 | Q63: =+P63+O63 -> 0
C64: Yeso | D64: =Costo!G166 -> 0.0871524 | E64: =Costo!H166 -> 232625.89 | F64: =E64*D64 -> 20273.905 | J64: Yeso | K64: =Costo!N166 -> 0.086292425 | L64: =Costo!O166 -> 220009.06 | M64: =L64*K64 -> 18985.115 | N64: =+M64-F64 -> -1288.7898 | O64: =+(L64-E64)*K64 -> -1088.7374 | P64: =+(K64-D64)*E64 -> -200.05237 | Q64: =+P64+O64 -> -1288.7898
C65: Total | F65: =SUM(F54:F64) -> 151371.84 | M65: =SUM(M54:M64) -> 141019.98 | N65: =+M65-F65 -> -10351.864 | O65: =+SUM(O54:O64) -> -10606.71 | P65: =+SUM(P54:P64) -> 254.84579 | Q65: =+SUM(Q54:Q64) -> -10351.864
C66: Pcc | F66: =Costo!I168 -> 33740.873 | M66: =Costo!P168 -> 42630.062 | N66: =+M66-F66 -> 8889.1899

Sheet Costo sin Consolidar
E4: PPTO 2026 | L4: REAL 2025 (Estim. Último trim. con 100% bitumi) F25 | R4: VARIACIONES
E5: Var Mtto + Refract | F5: =I15*I10+I25*I19+I37*(I30+I31+I32)+I46*I43+I75*(I73+I72+I69)+I84*(I91+I107+I168) -> 9348748404 | O5: =(H9-O9)/O9 -> 0.082015027
D6: ORD 1 | E6: Proceso | F6: Tipo | G6: Consumo | H6: Costo | I6: Total | K6: ORD 1 | L6: Proceso | M6: Tipo | N6: Consumo | O6: Costo | P6: Total | R6: VP | S6: VC | T6: Total
D7: 1 | E7: Trituración | F7: Arcilla | G7: =IFERROR(GETPIVOTDATA(" Cantidad",TD!$A$3,"Proceso",$E$7,"ORD",$D$7,"Tipo",F7)/GETPIVOTDATA(" Cantidad",TD!$A$3,"Proceso",$E$7,"ORD",$D$7,"Tipo","Producción")*-1,0) -> 0.20792079 | H7: =IFERROR(GETPIVOTDATA("Suma de Costo",TD!$A$3,"Proceso",$E$7,"ORD",$D$7,"Tipo",F7),0) -> 10623.146 | I7: =H7*G7 -> 2208.773 | K7: 1 | L7: Trituración | M7: Arcilla | N7: 0.21731513 | O7: 10136.59 | P7: =N7*O7 -> 2202.8343 | R7: =+(O7-H7)*N7 -> -105.73605 | S7: =+(N7-G7)*H7 -> 99.797399 | T7: =+P7-I7 -> -5.9386497
F8: Caliza | G8: =IFERROR(GETPIVOTDATA(" Cantidad",TD!$A$3,"Proceso","Trituración","ORD",1,"Tipo",F8)/GETPIVOTDATA(" Cantidad",TD!$A$3,"Proceso","Trituración","ORD",1,"Tipo","Producción")*-1,0) -> 0.79207921 | H8: =IFERROR(GETPIVOTDATA("Suma de Costo",TD!$A$3,"Proceso",$E$7,"ORD",$D$7,"Tipo",F8),0) -> 13978.132 | I8: =H8*G8 -> 11071.788 | M8: Caliza | N8: 0.78268487 | O8: 13349.966 | P8: =N8*O8 -> 10448.817 | R8: =+(O8-H8)*N8 -> -491.65578 | S8: =+(N8-G8)*H8 -> -131.31526 | T8: =+P8-I8 -> -622.97104
F9: Energía | G9: =GETPIVOTDATA(" Cantidad",TD!$A$3,"Proceso","Trituración","ORD",1,"Tipo",F9)/((GETPIVOTDATA(" Cantidad",TD!$A$3,"Proceso","Trituración","ORD",1,"Tipo","Producción"))*-1) -> 1.27 | H9: =IFERROR(GETPIVOTDATA("Suma de Costo",TD!$A$3,"Proceso",$E$7,"ORD",$D$7,"Tipo",F9),0) -> 525.144 | I9: =H9*G9 -> 666.93287 | M9: Energía | N9: 1.2925727 | O9: 485.33891 | P9: =N9*O9 -> 627.33584 | R9: =+(O9-H9)*N9 -> -51.450966 | S9: =+(N9-G9)*H9 -> 11.853936 | T9: =+P9-I9 -> -39.597031
C10: P | F10: Barras y Placas | G10: =IFERROR(GETPIVOTDATA(" Cantidad",TD!$A$3,"Proceso","Trituración","ORD",1,"Tipo",F10)/GETPIVOTDATA(" Cantidad",TD!$A$3,"Proceso","Trituración","ORD",1,"Tipo","Producción")*-1,0) -> 1 | H10: =IFERROR(GETPIVOTDATA("Suma de Costo",TD!$A$3,"Proceso",$E$7,"ORD",$D$7,"Tipo",F10),0) -> 903.51194 | I10: =H10*G10 -> 903.51194 | M10: Barras y Placas | N10: 1 | O10: 477.17063 | P10: =N10*O10 -> 477.17063 | R10: =+(O10-H10)*N10 -> -426.34131 | S10: =+(N10-G10)*H10 -> 0 | T10: =+P10-I10 -> -426.34131
F11: Material Dique | G11: =IFERROR(GETPIVOTDATA(" Cantidad",TD!$A$3,"Proceso","Trituración","ORD",1,"Tipo",F11)/GETPIVOTDATA(" Cantidad",TD!$A$3,"Proceso","Trituración","ORD",1,"Tipo","Producción")*-1,0) -> 1 | H11: =IFERROR(GETPIVOTDATA("Suma de Costo",TD!$A$3,"Proceso",$E$7,"ORD",$D$7,"Tipo",F11),0) -> 369.16354 | I11: =H11*G11 -> 369.16354 | M11: Material Dique | N11: 0 | O11: 0 | P11: =N11*O11 -> 0 | R11: =+(O11-H11)*N11 -> 0 | S11: =+(N11-G11)*H11 -> -369.16354 | T11: =+P11-I11 -> -369.16354
F12: Desmantelamiento | G12: 1 | H12: =(IFERROR(GETPIVOTDATA("Suma de Costo",TD!$A$3,"Proceso",$E$7,"ORD",$D$7,"Tipo",F12),0)) -> 0 | I12: =H12*G12 -> 0 | M12: Desmantelamiento | N12: 1 | O12: 0 | P12: =N12*O12 -> 0 | R12: =+(O12-H12)*N12 -> 0 | S12: =+(N12-G12)*H12 -> 0 | T12: =+P12-I12 -> 0
F13: Regalías | G13: 1 | H13: =(IFERROR(GETPIVOTDATA("Suma de Costo",TD!$A$3,"Proceso",$E$7,"ORD",$D$7,"Tipo",F13),0)) -> 152.42183 | I13: =H13*G13 -> 152.42183 | M13: Regalías | N13: 1 | O13: 146.6227 | P13: =N13*O13 -> 146.6227 | R13: =+(O13-H13)*N13 -> -5.7991332 | S13: =+(N13-G13)*H13 -> 0 | T13: =+P13-I13 -> -5.7991332
E14: Total Trituración | I14: =SUM(I7:I13) -> 15372.591 | L14: Total Trituración | P14: =SUM(P7:P13) -> 13902.78 | R14: =+SUM(R7:R13) -> -1080.9832 | S14: =+SUM(S7:S13) -> -388.82746 | T14: =+SUM(T7:T13) -> -1469.8107
E15: TN | I15: =IFERROR(GETPIVOTDATA(" Cantidad",TD!$A$3,"Proceso",E7,"ORD",D7,"Tipo","Producción")*-1,0) -> 1146594.7 | L15: TN | P15: 1234040.9
D17: ORD 2 | E17: Proceso | F17: Tipo | G17: Consumo | H17: Costo | I17: Total | K17: ORD 1 | L17: Proceso | M17: Tipo | N17: Consumo | O17: Costo | P17: Total | R17: VP | S17: VC | T17: Total
D18: 2 | E18: Adiciones | F18: Caliza | G18: =IFERROR(GETPIVOTDATA(" Cantidad",TD!$A$3,"Proceso",$E$18,"ORD",$D$18,"Tipo",F18)/GETPIVOTDATA(" Cantidad",TD!$A$3,"Proceso",$E$18,"ORD",$D$18,"Tipo","Producción")*-1,0) -> 1 | H18: =IFERROR(GETPIVOTDATA("Suma de Costo",TD!$A$3,"Proceso",$E$18,"ORD",$D$18,"Tipo",F18),0) -> 13978.132 | I18: =H18*G18 -> 13978.132 | K18: 2 | L18: Adiciones | M18: Caliza | N18: 1 | O18: 13868.791 | P18: =N18*O18 -> 13868.791 | R18: =+(O18-H18)*N18 -> -109.34051 | S18: =+(N18-G18)*H18 -> 0 | T18: =+P18-I18 -> -109.34051
C19: P | F19: Barras y Placas | G19: =IFERROR(GETPIVOTDATA(" Cantidad",TD!$A$3,"Proceso",$E$18,"ORD",$D$18,"Tipo",F19)/GETPIVOTDATA(" Cantidad",TD!$A$3,"Proceso",$E$18,"ORD",$D$18,"Tipo","Producción")*-1,0) -> 1 | H19: =IFERROR(GETPIVOTDATA("Suma de Costo",TD!$A$3,"Proceso",$E$18,"ORD",$D$18,"Tipo",F19),0) -> 903.51194 | I19: =H19*G19 -> 903.51194 | M19: Barras y Placas | N19: 1 | O19: 477.17063 | P19: =N19*O19 -> 477.17063 | R19: =+(O19-H19)*N19 -> -426.34131 | S19: =+(N19-G19)*H19 -> 0 | T19: =+P19-I19 -> -426.34131
F20: Material Dique | G20: =IFERROR(GETPIVOTDATA(" Cantidad",TD!$A$3,"Proceso",$E$18,"ORD",$D$18,"Tipo",F20)/GETPIVOTDATA(" Cantidad",TD!$A$3,"Proceso",$E$18,"ORD",$D$18,"Tipo","Producción")*-1,0) -> 1 | H20: =IFERROR(GETPIVOTDATA("Suma de Costo",TD!$A$3,"Proceso",$E$18,"ORD",$D$18,"Tipo",F20),0) -> 369.16354 | I20: =H20*G20 -> 369.16354 | M20: Material Dique | N20: 0 | O20: 0 | P20: =N20*O20 -> 0 | R20: =+(O20-H20)*N20 -> 0 | S20: =+(N20-G20)*H20 -> -369.16354 | T20: =+P20-I20 -> -369.16354
F21: Desmantelamiento | G21: =IFERROR(GETPIVOTDATA(" Cantidad",TD!$A$3,"Proceso","Trituración","ORD",1,"Tipo",F21)/GETPIVOTDATA(" Cantidad",TD!$A$3,"Proceso","Trituración","ORD",1,"Tipo","Producción")*-1,0)*0+1 -> 1 | H21: =(IFERROR(GETPIVOTDATA("Suma de Costo",TD!$A$3,"Proceso",$E$18,"ORD",$D$18,"Tipo",F21),0)) -> 0 | I21: =H21*G21 -> 0 | M21: Desmantelamiento | N21: 1 | O21: 0 | P21: =N21*O21 -> 0 | R21: =+(O21-H21)*N21 -> 0 | S21: =+(N21-G21)*H21 -> 0 | T21: =+P21-I21 -> 0
F22: Regalías | G22: =IFERROR(GETPIVOTDATA(" Cantidad",TD!$A$3,"Proceso","Trituración","ORD",1,"Tipo",F22)/GETPIVOTDATA(" Cantidad",TD!$A$3,"Proceso","Trituración","ORD",1,"Tipo","Producción")*-1,0)*0+1 -> 1 | H22: =(IFERROR(GETPIVOTDATA("Suma de Costo",TD!$A$3,"Proceso",$E$18,"ORD",$D$18,"Tipo",F22),0)) -> 118.58675 | I22: =H22*G22 -> 118.58675 | M22: Regalías | N22: 1 | O22: 113.59304 | P22: =N22*O22 -> 113.59304 | R22: =+(O22-H22)*N22 -> -4.9937111 | S22: =+(N22-G22)*H22 -> 0 | T22: =+P22-I22 -> -4.9937111
F23: Energía | G23: =GETPIVOTDATA(" Cantidad",TD!$A$3,"Proceso","Adiciones","ORD",2,"Tipo",F23)/((GETPIVOTDATA(" Cantidad",TD!$A$3,"Proceso","Adiciones","ORD",2,"Tipo","Producción"))*-1) -> 1.27 | H23: =IFERROR(GETPIVOTDATA("Suma de Costo",TD!$A$3,"Proceso",$E$18,"ORD",$D$18,"Tipo",F23),0) -> 525.24409 | I23: =H23*G23 -> 667.06 | M23: Energía | N23: 1.2925727 | O23: 485.33891 | P23: =N23*O23 -> 627.33584 | R23: =+(O23-H23)*N23 -> -51.580351 | S23: =+(N23-G23)*H23 -> 11.856195 | T23: =+P23-I23 -> -39.724156
E24: Total Adiciones | I24: =SUM(I18:I23) -> 16036.454 | L24: Total Adiciones | P24: =SUM(P18:P23) -> 15086.891 | R24: =+SUM(R18:R23) -> -592.25588 | S24: =+SUM(S18:S23) -> -357.30735 | T24: =+SUM(T18:T23) -> -949.56323
E25: TN | I25: =IFERROR(GETPIVOTDATA(" Cantidad",TD!$A$3,"Proceso",E18,"ORD",D18,"Tipo","Producción")*-1,0) -> 602137.06 | L25: TN | P25: 484054.62
D27: ORD 3 | E27: Proceso | F27: Tipo | G27: Consumo | H27: Costo | I27: Total | K27: ORD 3 | L27: Proceso | M27: Tipo | N27: Consumo | O27: Costo | P27: Total | R27: VP | S27: VC | T27: Total
D28: 3 | E28: Molienda de Crudo | F28: Prehomo | G28: =IFERROR(GETPIVOTDATA(" Cantidad",TD!$A$3,"Proceso",$E$28,"ORD",$D$28,"Tipo",F28)/GETPIVOTDATA(" Cantidad",TD!$A$3,"Proceso",$E$28,"ORD",$D$28,"Tipo","Producción")*-1,0) -> 0.83131183 | H28: 31000 | I28: =H28*G28 -> 25770.667 | K28: 3 | L28: Molienda de Crudo | M28: Prehomo | N28: 0.89170299 | O28: 31000 | P28: =N28*O28 -> 27642.793 | R28: =+(O28-H28)*N28 -> 0 | S28: =+(N28-G28)*H28 -> 1872.1258 | T28: =+P28-I28 -> 1872.1258
F29: Caliza | G29: =IFERROR(GETPIVOTDATA(" Cantidad",TD!$A$3,"Proceso",$E$28,"ORD",$D$28,"Tipo",F29)/GETPIVOTDATA(" Cantidad",TD!$A$3,"Proceso",$E$28,"ORD",$D$28,"Tipo","Producción")*-1,0) -> 0.18281 | H29: 31500 | I29: =H29*G29 -> 5758.515 | M29: Caliza | N29: 0.1211848 | O29: 31500 | P29: =N29*O29 -> 3817.3213 | R29: =+(O29-H29)*N29 -> 0 | S29: =+(N29-G29)*H29 -> -1941.1937 | T29: =+P29-I29 -> -1941.1937
F30: Cuerpos Moledores | G30: =IFERROR(GETPIVOTDATA(" Cantidad",TD!$A$3,"Proceso",$E$28,"ORD",$D$28,"Tipo",F30)/GETPIVOTDATA(" Cantidad",TD!$A$3,"Proceso",$E$28,"ORD",$D$28,"Tipo","Producción")*-1,0) -> 1 | H30: =IFERROR(GETPIVOTDATA("Suma de Costo",TD!$A$3,"Proceso",$E$28,"ORD",$D$28,"Tipo",F30),0) -> 167.10951 | I30: =H30*G30 -> 167.10951 | M30: Cuerpos Moledores | N30: 1 | O30: 397.89581 | P30: =N30*O30 -> 397.89581 | R30: =+(O30-H30)*N30 -> 230.7863 | S30: =+(N30-G30)*H30 -> 0 | T30: =+P30-I30 -> 230.7863
F31: Láminas | G31: =IFERROR(GETPIVOTDATA(" Cantidad",TD!$A$3,"Proceso",$E$28,"ORD",$D$28,"Tipo",F31)/GETPIVOTDATA(" Cantidad",TD!$A$3,"Proceso",$E$28,"ORD",$D$28,"Tipo","Producción")*-1,0) -> 1 | H31: =IFERROR(GETPIVOTDATA("Suma de Costo",TD!$A$3,"Proceso",$E$28,"ORD",$D$28,"Tipo",F31),0) -> 119.88291 | I31: =H31*G31 -> 119.88291 | M31: Láminas | N31: 1 | O31: 305.60179 | P31: =N31*O31 -> 305.60179 | R31: =+(O31-H31)*N31 -> 185.71888 | S31: =+(N31-G31)*H31 -> 0 | T31: =+P31-I31 -> 185.71888
F32: Anillos, Tapas y Separadores | G32: =IFERROR(GETPIVOTDATA(" Cantidad",TD!$A$3,"Proceso",$E$28,"ORD",$D$28,"Tipo",F32)/GETPIVOTDATA(" Cantidad",TD!$A$3,"Proceso",$E$28,"ORD",$D$28,"Tipo","Producción")*-1,0) -> 1 | H32: =IFERROR(GETPIVOTDATA("Suma de Costo",TD!$A$3,"Proceso",$E$28,"ORD",$D$28,"Tipo",F32),0) -> 498.70407 | I32: =H32*G32 -> 498.70407 | M32: Anillos, Tapas y Separadores | N32: 1 | O32: 205.58666 | P32: =N32*O32 -> 205.58666 | R32: =+(O32-H32)*N32 -> -293.11742 | S32: =+(N32-G32)*H32 -> 0 | T32: =+P32-I32 -> -293.11742
F33: Energía | G33: =GETPIVOTDATA(" Cantidad",TD!$A$3,"Proceso","Molienda de Crudo","ORD",3,"Tipo",F33)/((GETPIVOTDATA(" Cantidad",TD!$A$3,"Proceso","Molienda de Crudo","ORD",3,"Tipo","Producción"))*-1) -> 15.1 | H33: =IFERROR(GETPIVOTDATA("Suma de Costo",TD!$A$3,"Proceso",$E$28,"ORD",$D$28,"Tipo",F33),0) -> 525.1452 | I33: =H33*G33 -> 7929.6925 | M33: Energía | N33: 15.261172 | O33: 480.42206 | P33: =N33*O33 -> 7331.8035 | R33: =+(O33-H33)*N33 -> -682.52751 | S33: =+(N33-G33)*H33 -> 84.63848 | T33: =+P33-I33 -> -597.88903
F34: Sílice | G34: 0 | H34: 0 | I34: =H34*G34 -> 0 | M34: Sílice | N34: 0 | O34: 0 | P34: =N34*O34 -> 0 | R34: =+(O34-H34)*N34 -> 0 | S34: =+(N34-G34)*H34 -> 0 | T34: =+P34-I34 -> 0
F35: Mineral de Hierro | G35: =IFERROR(GETPIVOTDATA(" Cantidad",TD!$A$3,"Proceso",$E$28,"ORD",$D$28,"Tipo",F35)/GETPIVOTDATA(" Cantidad",TD!$A$3,"Proceso",$E$28,"ORD",$D$28,"Tipo","Producción")*-1,0) -> 0.025993187 | H35: =IFERROR(GETPIVOTDATA("Suma de Costo",TD!$A$3,"Proceso",$E$28,"ORD",$D$28,"Tipo",F35),0) -> 281860.87 | I35: =H35*G35 -> 7326.4625 | M35: Mineral de Hierro | N35: 0.025414903 | O35: 256211.07 | P35: =N35*O35 -> 6511.5794 | R35: =+(O35-H35)*N35 -> -651.88731 | S35: =+(N35-G35)*H35 -> -162.99577 | T35: =+P35-I35 -> -814.88308
E36: Total Molienda de Crudo | I36: =SUM(I28:I35) -> 47571.033 | L36: Total Molienda de Crudo | N36: } | P36: =SUM(P28:P35) -> 46212.581 | R36: =+SUM(R28:R35) -> -1211.0271 | S36: =+SUM(S28:S35) -> -147.42521 | T36: =+SUM(T28:T35) -> -1358.4523
I37: =IFERROR(GETPIVOTDATA(" Cantidad",TD!$A$3,"Proceso",E28,"ORD",D28,"Tipo","Producción")*-1,0) -> 1376343 | P37: 1413903.1
D39: ORD 4 | E39: Proceso | F39: Tipo | G39: Consumo | H39: Costo | I39: Total | K39: ORD 4 | L39: Proceso | M39: Tipo | N39: Consumo | O39: Costo | P39: Total | R39: VP | S39: VC | T39: Total
D40: 4 | E40: Molienda de Carbón | F40: Carbón | G40: =IFERROR(GETPIVOTDATA(" Cantidad",TD!$A$3,"Proceso",$E$40,"ORD",$D$40,"Tipo",F40)/GETPIVOTDATA(" Cantidad",TD!$A$3,"Proceso",$E$40,"ORD",$D$40,"Tipo","Producción")*-1,0) -> 1.0660981 | H40: =IFERROR(GETPIVOTDATA("Suma de Costo",TD!$A$3,"Proceso",$E$40,"ORD",$D$40,"Tipo",F40),0)+IFERROR(GETPIVOTDATA("Suma de Costo",TD!$A$3,"Proceso",$E$40,"ORD",$D$40,"Tipo","Desatasque De Carbón"),0) -> 340706.62 | I40: =H40*G40 -> 363226.67 | K40: 4 | L40: Molienda de Carbón | M40: Carbón | N40: 1.0943444 | O40: 251126.22 | P40: =N40*O40 -> 274818.56 | R40: =+(O40-H40)*N40 -> -98031.805 | S40: =+(N40-G40)*H40 -> 9623.6954 | T40: =+P40-I40 -> -88408.11
F41: Descargue Finos Carbón | G41: =IFERROR(GETPIVOTDATA(" Cantidad",TD!$A$3,"Proceso",$E$40,"ORD",$D$40,"Tipo",F41),0)/IFERROR(GETPIVOTDATA(" Cantidad",TD!$A$3,"Proceso",E40,"ORD",D40,"Tipo","Producción")*-1,0) -> 0.21321962 | H41: =IFERROR(GETPIVOTDATA("Suma de Costo",TD!$A$3,"Proceso",$E$40,"ORD",$D$40,"Tipo",F41),0) -> 8700 | I41: =H41*G41 -> 1855.0107 | M41: Descargue Finos Carbón | N41: 0.27679132 | O41: 7508.9803 | P41: =N41*O41 -> 2078.4206 | R41: =+(O41-H41)*N41 -> -329.6639 | S41: =+(N41-G41)*H41 -> 553.0738 | T41: =+P41-I41 -> 223.40989
F42: Cargador Carbón | G42: =IFERROR(GETPIVOTDATA(" Cantidad",TD!$A$3,"Proceso",$E$40,"ORD",$D$40,"Tipo",F40),0)/IFERROR(GETPIVOTDATA(" Cantidad",TD!$A$3,"Proceso",E40,"ORD",D40,"Tipo","Producción")*-1,0) -> 1.0660981 | H42: =IFERROR(GETPIVOTDATA("Suma de Costo",TD!$A$3,"Proceso",$E$40,"ORD",$D$40,"Tipo",F42),0) -> 6325 | I42: =H42*G42 -> 6743.0704 | M42: Cargador Carbón | N42: 1.0710661 | O42: 7209.7752 | P42: =N42*O42 -> 7722.1455 | R42: =+(O42-H42)*N42 -> 947.65269 | S42: =+(N42-G42)*H42 -> 31.422465 | T42: =+P42-I42 -> 979.07515
F43: Cuerpos Moledores y Láminas | G43: =IFERROR(GETPIVOTDATA(" Cantidad",TD!$A$3,"Proceso",$E$40,"ORD",$D$40,"Tipo",F43)/GETPIVOTDATA(" Cantidad",TD!$A$3,"Proceso",$E$40,"ORD",$D$40,"Tipo","Producción")*-1,0) -> 1 | H43: =IFERROR(GETPIVOTDATA("Suma de Costo",TD!$A$3,"Proceso",$E$40,"ORD",$D$40,"Tipo",F43),0) -> 3788.979 | I43: =H43*G43 -> 3788.979 | M43: Cuerpos Moledores | N43: 1 | O43: 1034.9866 | P43: =N43*O43 -> 1034.9866 | R43: =+(O43-H43)*N43 -> -2753.9924 | S43: =+(N43-G43)*H43 -> 0 | T43: =+P43-I43 -> -2753.9924
F44: Energía | G44: =GETPIVOTDATA(" Cantidad",TD!$A$3,"Proceso","Molienda de Carbón","ORD",4,"Tipo",F44)/((GETPIVOTDATA(" Cantidad",TD!$A$3,"Proceso","Molienda de Carbón","ORD",4,"Tipo","Producción"))*-1) -> 28 | H44: =IFERROR(GETPIVOTDATA("Suma de Costo",TD!$A$3,"Proceso",$E$40,"ORD",$D$40,"Tipo",F44),0) -> 525.1415 | I44: =H44*G44 -> 14703.962 | M44: Energía | N44: 34.339796 | O44: 485.33891 | P44: =N44*O44 -> 16666.439 | R44: =+(O44-H44)*N44 -> -1366.8127 | S44: =+(N44-G44)*H44 -> 3329.2897 | T44: =+P44-I44 -> 1962.4771
E45: Total Molienda de Carbón | I45: =SUM(I40:I44) -> 390317.7 | L45: Total Molienda de Carbón | P45: =SUM(P40:P44) -> 302320.56 | R45: =+SUM(R40:R44) -> -101534.62 | S45: =+SUM(S40:S44) -> 13537.481 | T45: =+SUM(T40:T44) -> -87997.14
I46: =IFERROR(GETPIVOTDATA(" Cantidad",TD!$A$3,"Proceso",E40,"ORD",D40,"Tipo","Producción")*-1,0) -> 95434.68 | P46: 124970.9
D48: ORD 20 | E48: Proceso | F48: Tipo | G48: Consumo | H48: Costo | I48: Total | L48: Proceso | M48: Tipo | N48: Consumo | O48: Costo | P48: Total | R48: VP | S48: VC | T48: Total
D49: 20 | E49: Combustibles Alternos | F49: CDR | G49: =IFERROR(GETPIVOTDATA(" Cantidad",TD!$A$3,"Proceso",$E$49,"ORD",$D$49,"Tipo",F49)/GETPIVOTDATA(" Cantidad",TD!$A$3,"Proceso",$E$49,"ORD",$D$49,"Tipo","Producción")*-1,0) -> 0.81442206 | H49: =IFERROR(GETPIVOTDATA("Suma de Costo",TD!$A$3,"Proceso",$E$49,"ORD",$D$49,"Tipo",F49),0) -> 318229.74 | I49: =H49*G49 -> 259173.32 | L49: Combustibles Alternos | M49: CDR | N49: 0.42523649 | O49: 293738.62 | P49: =+N49*O49 -> 124908.38 | R49: =+(O49-H49)*N49 -> -10414.517 | S49: =+(N49-G49)*H49 -> -123850.42 | T49: =+P49-I49 -> -134264.94
F50: Llanta Picada | G50: =IFERROR(GETPIVOTDATA(" Cantidad",TD!$A$3,"Proceso",$E$49,"ORD",$D$49,"Tipo",F50)/GETPIVOTDATA(" Cantidad",TD!$A$3,"Proceso",$E$49,"ORD",$D$49,"Tipo","Producción")*-1,0) -> 0.18557794 | H50: =IFERROR(GETPIVOTDATA("Suma de Costo",TD!$A$3,"Proceso",$E$49,"ORD",$D$49,"Tipo",F50),0) -> 318422.6 | I50: =H50*G50 -> 59092.212 | M50: Llanta Picada | N50: 0.37053385 | O50: 338940.44 | P50: =+N50*O50 -> 125588.91 | R50: =+(O50-H50)*N50 -> 7602.5545 | S50: =+(N50-G50)*H50 -> 58894.142 | T50: =+P50-I50 -> 66496.696
F51: Mezcla | G51: 0 | H51: 0 | I51: =H51*G51 -> 0 | M51: Mezcla | N51: 0.063860476 | O51: 248821.46 | P51: =+N51*O51 -> 15889.857 | R51: =+(O51-H51)*N51 -> 15889.857 | S51: =+(N51-G51)*H51 -> 0 | T51: =+P51-I51 -> 15889.857
F52: Chip de Madera | G52: =IFERROR(GETPIVOTDATA(" Cantidad",TD!$A$3,"Proceso",$E$49,"ORD",$D$49,"Tipo",F52)/GETPIVOTDATA(" Cantidad",TD!$A$3,"Proceso",$E$49,"ORD",$D$49,"Tipo","Producción")*-1,0) -> 0 | H52: =IFERROR(GETPIVOTDATA("Suma de Costo",TD!$A$3,"Proceso",$E$49,"ORD",$D$49,"Tipo",F52),0) -> 0 | I52: =H52*G52 -> 0 | M52: Chip de Madera | N52: =0.140369187012787/2 -> 0.070184594 | O52: 332985.22 | P52: =+N52*O52 -> 23370.432 | R52: =+(O52-H52)*N52 -> 23370.432 | S52: =+(N52-G52)*H52 -> 0 | T52: =+P52-I52 -> 23370.432
F53: Briquetas | G53: =IFERROR(GETPIVOTDATA(" Cantidad",TD!$A$3,"Proceso",$E$49,"ORD",$D$49,"Tipo",F53)/GETPIVOTDATA(" Cantidad",TD!$A$3,"Proceso",$E$49,"ORD",$D$49,"Tipo","Producción")*-1,0) -> 0 | H53: =IFERROR(GETPIVOTDATA("Suma de Costo",TD!$A$3,"Proceso",$E$49,"ORD",$D$49,"Tipo",F53),0) -> 0 | I53: =H53*G53 -> 0 | M53: Briquetas | N53: =0.140369187012787/2 -> 0.070184594 | O53: 332985.22 | P53: =+N53*O53 -> 23370.432 | R53: =+(O53-H53)*N53 -> 23370.432 | S53: =+(N53-G53)*H53 -> 0 | T53: =+P53-I53 -> 23370.432
F54: Cargue | G54: =IFERROR(GETPIVOTDATA(" Cantidad",TD!$A$3,"Proceso",$E$49,"ORD",$D$49,"Tipo","Cargue Alternos")/GETPIVOTDATA(" Cantidad",TD!$A$3,"Proceso",$E$49,"ORD",$D$49,"Tipo","Producción")*-1,0) -> 1 | H54: =IFERROR(GETPIVOTDATA("Suma de Costo",TD!$A$3,"Proceso",$E$49,"ORD",$D$49,"Tipo","Cargue Alternos"),0) -> 8768.4175 | I54: =H54*G54 -> 8768.4175 | M54: Cargue | N54: 1 | O54: 5481.4315 | P54: =+N54*O54 -> 5481.4315 | R54: =+(O54-H54)*N54 -> -3286.986 | S54: =+(N54-G54)*H54 -> 0 | T54: =+P54-I54 -> -3286.986
F55: Descargue | G55: =IFERROR(GETPIVOTDATA(" Cantidad",TD!$A$3,"Proceso",$E$49,"ORD",$D$49,"Tipo","Descargue Alternos")/GETPIVOTDATA(" Cantidad",TD!$A$3,"Proceso",$E$49,"ORD",$D$49,"Tipo","Producción")*-1,0) -> 1 | H55: =IFERROR(GETPIVOTDATA("Suma de Costo",TD!$A$3,"Proceso",$E$49,"ORD",$D$49,"Tipo","Descargue Alternos"),0) -> 10725 | I55: =H55*G55 -> 10725 | M55: Descargue | N55: 1 | O55: 4364.6696 | P55: =+N55*O55 -> 4364.6696 | R55: =+(O55-H55)*N55 -> -6360.3304 | S55: =+(N55-G55)*H55 -> 0 | T55: =+P55-I55 -> -6360.3304
F56: Energía | G56: =GETPIVOTDATA(" Cantidad",TD!$A$3,"Proceso","Combustibles Alternos","ORD",20,"Tipo",F56)/((GETPIVOTDATA(" Cantidad",TD!$A$3,"Proceso","Combustibles Alternos","ORD",20,"Tipo","Producción"))*-1) -> 8.4 | H56: =IFERROR(GETPIVOTDATA("Suma de Costo",TD!$A$3,"Proceso",$E$49,"ORD",$D$49,"Tipo",F56),0) -> 525.14393 | I56: =H56*G56 -> 4411.209 | M56: Energía | N56: 7.8357651 | O56: 485.33891 | P56: =+N56*O56 -> 3803.0017 | R56: =+(O56-H56)*N56 -> -311.90279 | S56: =+(N56-G56)*H56 -> -296.30454 | T56: =+P56-I56 -> -608.20733
F57: Variables | G57: 1 | H57: 0 | I57: =H57*G57 -> 0 | M57: Variables | N57: 1 | O57: 0 | P57: =+N57*O57 -> 0 | R57: =+(O57-H57)*N57 -> 0 | S57: =+(N57-G57)*H57 -> 0 | T57: =+P57-I57 -> 0
E58: Total Combustibles Alternos | I58: =SUM(I49:I57) -> 342170.16 | L58: Total Combustibles Alternos | P58: =SUM(P49:P57) -> 326777.11 | R58: =+SUM(R53:R57) -> 13411.213 | S58: =+SUM(S53:S57) -> -296.30454 | T58: =+SUM(T53:T57) -> 13114.909
I59: =IFERROR(GETPIVOTDATA(" Cantidad",TD!$A$3,"Proceso",E49,"ORD",D49,"Tipo","Combustibles Alternos")*-1,0) -> 16422.576 | P59: 14853.021
D61: ORD 5 | E61: Proceso | F61: Tipo | G61: Consumo | H61: Costo | I61: Total | K61: ORD 5 | L61: Proceso | M61: Tipo | N61: Consumo | O61: Costo | P61: Total | R61: VP | S61: VC | T61: Total
D62: 5 | E62: Clinkerización | F62: Crudo | G62: =IFERROR(GETPIVOTDATA(" Cantidad",TD!$A$3,"Proceso",$E$62,"ORD",$D$62,"Tipo",F62)/GETPIVOTDATA(" Cantidad",TD!$A$3,"Proceso",$E$62,"ORD",$D$62,"Tipo","Producción")*-1,0) -> 1.56 | H62: =I36 -> 47571.033 | I62: =H62*G62 -> 74210.812 | K62: 5 | L62: Clinkerización | M62: Crudo | N62: 1.5600005 | O62: =P36 -> 46212.581 | P62: =+N62*O62 -> 72091.647 | R62: =+(O62-H62)*N62 -> -2119.1861 | S62: =+(N62-G62)*H62 -> 0.021418119 | T62: =+P62-I62 -> -2119.1647
F63: Carbón Molido | G63: =IFERROR(GETPIVOTDATA(" Cantidad",TD!$A$3,"Proceso",$E$62,"ORD",$D$62,"Tipo",F63)/GETPIVOTDATA(" Cantidad",TD!$A$3,"Proceso",$E$62,"ORD",$D$62,"Tipo","Producción")*-1,0) -> 0.11141634 | H63: =I45 -> 390317.7 | I63: =H63*G63 -> 43487.77 | M63: Carbón Molido | N63: 0.13154945 | O63: 302160.49 | P63: =+N63*O63 -> 39749.047 | R63: =+(O63-H63)*N63 -> -11597.032 | S63: =+(N63-G63)*H63 -> 7858.3097 | T63: =+P63-I63 -> -3738.7226
F64: Combustibles Alternos | G64: =IFERROR(GETPIVOTDATA(" Cantidad",TD!$A$3,"Proceso",$E$62,"ORD",$D$62,"Tipo",F64)/GETPIVOTDATA(" Cantidad",TD!$A$3,"Proceso",$E$62,"ORD",$D$62,"Tipo","Producción")*-1,0) -> 0.01917273 | H64: =I58 -> 342170.16 | I64: =H64*G64 -> 6560.336 | M64: Alternos | N64: 0.016480649 | O64: 326777.11 | P64: =+N64*O64 -> 5385.4987 | R64: =+(O64-H64)*N64 -> -253.6874 | S64: =+(N64-G64)*H64 -> -921.14981 | T64: =+P64-I64 -> -1174.8372
F65: Ductos | G65: =IFERROR(GETPIVOTDATA(" Cantidad",TD!$A$3,"Proceso",$E$62,"ORD",$D$62,"Tipo",F65)/GETPIVOTDATA(" Cantidad",TD!$A$3,"Proceso",$E$62,"ORD",$D$62,"Tipo","Producción")*-1,0) -> 1 | H65: =IFERROR(GETPIVOTDATA("Suma de Costo",TD!$A$3,"Proceso",$E$62,"ORD",$D$62,"Tipo",F65),0) -> 0 | I65: =H65*G65 -> 0 | M65: Ductos | N65: 1 | O65: 0 | P65: =+N65*O65 -> 0 | R65: =+(O65-H65)*N65 -> 0 | S65: =+(N65-G65)*H65 -> 0 | T65: =+P65-I65 -> 0
F66: Energía | G66: =GETPIVOTDATA(" Cantidad",TD!$A$3,"Proceso","Clinkerización","ORD",5,"Tipo",F66)/((GETPIVOTDATA(" Cantidad",TD!$A$3,"Proceso","Clinkerización","ORD",5,"Tipo","Producción"))*-1) -> 30.7 | H66: =IFERROR(GETPIVOTDATA("Suma de Costo",TD!$A$3,"Proceso",$E$62,"ORD",$D$62,"Tipo",F66),0) -> 525.14393 | I66: =H66*G66 -> 16121.919 | M66: Energía | N66: 31.830556 | O66: 485.33891 | P66: =+N66*O66 -> 15448.607 | R66: =+(O66-H66)*N66 -> -1267.0159 | S66: =+(N66-G66)*H66 -> 593.70444 | T66: =+P66-I66 -> -673.31146
F67: Cargue Clinker | G67: =IFERROR(GETPIVOTDATA(" Cantidad",TD!$A$3,"Proceso",$E$62,"ORD",$D$62,"Tipo",F67)/GETPIVOTDATA(" Cantidad",TD!$A$3,"Proceso",$E$62,"ORD",$D$62,"Tipo","Producción")*-1,0) -> 0.035023854 | H67: =IFERROR(GETPIVOTDATA("Suma de Costo",TD!$A$3,"Proceso",$E$62,"ORD",$D$62,"Tipo",F67),0) -> 6160 | I67: =H67*G67 -> 215.74694 | M67: Cargue Clinker | N67: 0.041532854 | O67: 7256.0685 | P67: =+N67*O67 -> 301.36523 | R67: =+(O67-H67)*N67 -> 45.522852 | S67: =+(N67-G67)*H67 -> 40.095444 | T67: =+P67-I67 -> 85.618295
F68: Sellado | G68: =IFERROR(GETPIVOTDATA(" Cantidad",TD!$A$3,"Proceso",$E$62,"ORD",$D$62,"Tipo",F68)/GETPIVOTDATA(" Cantidad",TD!$A$3,"Proceso",$E$62,"ORD",$D$62,"Tipo","Producción")*-1,0) -> 1 | H68: =IFERROR(GETPIVOTDATA("Suma de Costo",TD!$A$3,"Proceso",$E$62,"ORD",$D$62,"Tipo",F68),0) -> 0 | I68: =H68*G68 -> 0 | M68: Sellado | N68: 1 | O68: 0 | P68: =+N68*O68 -> 0 | R68: =+(O68-H68)*N68 -> 0 | S68: =+(N68-G68)*H68 -> 0 | T68: =+P68-I68 -> 0
F69: Enfriador | G69: =IFERROR(GETPIVOTDATA(" Cantidad",TD!$A$3,"Proceso",$E$62,"ORD",$D$62,"Tipo",F69)/GETPIVOTDATA(" Cantidad",TD!$A$3,"Proceso",$E$62,"ORD",$D$62,"Tipo","Producción")*-1,0) -> 1 | H69: =IFERROR(GETPIVOTDATA("Suma de Costo",TD!$A$3,"Proceso",$E$62,"ORD",$D$62,"Tipo",F69),0) -> 184.45896 | I69: =H69*G69 -> 184.45896 | M69: Enfriador | N69: 1 | O69: 52.460973 | P69: =+N69*O69 -> 52.460973 | R69: =+(O69-H69)*N69 -> -131.99799 | S69: =+(N69-G69)*H69 -> 0 | T69: =+P69-I69 -> -131.99799
